Workbook

Sheet Inicio

Sheet OT
A2: TABLA DE ÓRDENES DE TRABAJO
A3: Código | B3: Descripción | C3: Fecha de pedido | D3: Fecha de Entrega | E3: Producto | F3: Detalle 1 | G3: Detalle 2 | H3: Detalle 3 | I3: Detalle 4 | J3: Detalle 5 | K3: TALLAS | P3: SITUACIÓN
K4: XS | L4: S | M4: M | N4: L | O4: XL
A5: OT1 | B5: Prendas Colegio: Americano | C5: 42828 | D5: 42835 | E5: CASACAS | F5: Broche | G5: Cierre | H5: Tela | I5: Bordado | J5: Estampado Interno | K5: 4 | L5: 4 | M5: 8 | N5: 5 | O5: 0 | P5: TERMINADO
F6: Sí | G6: Sí | H6: Franela Perchada 24/1 | I6: Sí | J6: Sí | L6: CANTIDAD | O6: =SUM(K5:O5) -> 21
A7: OT2 | B7: Prendas Colegio: Sophiano College | C7: 42829 | D7: 42839 | E7: CASACAS | F7: Broche | G7: Cierre | H7: Tela | I7: Bordado | J7: Estampado Interno | K7: 2 | L7: 5 | M7: 16 | N7: 4 | O7: 0 | P7: TERMINADO
F8: Sí | G8: No | H8: Franela Perchada 24/1 | I8: Sí | J8: Sí | L8: CANTIDAD | O8: =SUM(K7:O7) -> 27
A9: OT3 | B9: Prendas Colegio: Juan 23 | C9: 42842 | D9: 42852 | E9: POLOS | F9: Estampado Pecho | G9: Estampado Espalda | H9: Tela | I9: Insignia | J9: Cuello | K9: 0 | L9: 3 | M9: 5 | N9: 15 | O9: 4 | P9: TERMINADO
F10: Sí | G10: No | H10: Jersey | I10: Sí | J10: Redondo | L10: CANTIDAD | O10: =SUM(K9:O9) -> 27
A11: OT4 | B11: Prendas Universidad Nacional de Ingeniería | C11: 42835 | D11: 42853 | E11: POLERAS | F11: Bordado | G11: Tela | H11: Estampado Interno | K11: 0 | L11: 4 | M11: 24 | N11: 26 | O11: 0 | P11: TERMINADO
F12: Sí | G12: Franela Perchada 24/1 | H12: Sí | L12: CANTIDAD | O12: =SUM(K11:O11) -> 54
A13: OT5 | B13: Prendas San German | C13: 42844 | D13: 42856 | E13: CASACAS | F13: Broche | G13: Cierre | H13: Tela | I13: Bordado | J13: Estampado Interno | K13: 0 | L13: 1 | M13: 10 | N13: 10 | O13: 0 | P13: TERMINADO
F14: Sí | G14: Sí | H14: Frech Terry 24/1 | I14: Sí | J14: Sí | L14: CANTIDAD | O14: =SUM(K13:O13) -> 21
A15: OT6 | B15: Prendas IEP Fray Luis de León | C15: 42849 | D15: 42859 | E15: POLERAS | F15: Bordado | G15: Tela | H15: Estampado Interno | K15: 0 | L15: 4 | M15: 10 | N15: 3 | O15: 7 | P15: TERMINADO
F16: Sí | G16: Frech Terry 24/1 | H16: Sí | L16: CANTIDAD | O16: =SUM(K15:O15) -> 24
A17: OT7 | B17: Prendas Federico Villareal | C17: 42858 | D17: 42863 | E17: POLOS | F17: Estampado Pecho | G17: Estampado Espalda | H17: Tela | I17: Insignia | J17: Cuello | K17: 0 | L17: 1 | M17: 19 | N17: 6 | O17: 0 | P17: TERMINADO
F18: Sí | G18: No | H18: Algodón Tacto | I18: Sí | J18: V | L18: CANTIDAD | O18: =SUM(K17:O17) -> 26
A19: OT8 | B19: Prendas Saco Oliveros | C19: 42859 | D19: 42871 | E19: POLERAS | F19: Bordado | G19: Tela | H19: Estampado Interno | K19: 0 | L19: 3 | M19: 12 | N19: 12 | O19: 1 | P19: TERMINADO
F20: Sí | G20: Franela Perchada 24/1 | H20: Sí | L20: CANTIDAD | O20: =SUM(K19:O19) -> 28
A21: OT9 | B21: Prendas Colegios Pamer | C21: 42872 | D21: 42880 | E21: POLERAS | F21: Bordado | G21: Tela | H21: Estampado Interno | K21: 0 | L21: 0 | M21: 17 | N21: 0 | O21: 0 | P21: TERMINADO
F22: Sí | G22: Franela Perchada 24/1 | H22: Sí | L22: CANTIDAD | O22: =SUM(K21:O21) -> 17
A23: OT10 | B23: Prendas Colegio Marianistas (0602) | C23: 42875 | D23: 42886 | E23: POLERAS | F23: Bordado | G23: Tela | H23: Estampado Interno | K23: 0 | L23: 6 | M23: 5 | N23: 2 | O23: 1 | P23: TERMINADO
F24: Sí | G24: Frech Terry 24/1 | H24: Sí | L24: CANTIDAD | O24: =SUM(K23:O23) -> 14
A25: OT11 | B25: Prendas Ingenieros UNI | C25: 42880 | D25: 42890 | E25: POLOS | F25: Estampado Pecho | G25: Estampado Espalda | H25: Tela | I25: Insignia | J25: Cuello | K25: 0 | L25: 10 | M25: 16 | N25: 6 | O25: 2 | P25: TERMINADO
F26: Sí | G26: No | H26: Jersey | I26: Sí | J26: Redondo | L26: CANTIDAD | O26: =SUM(K25:O25) -> 34
A27: OT12 | B27: Prendas Colegios Cruz Saco | C27: 42886 | D27: 42894 | E27: POLERAS | F27: Bordado | G27: Tela | H27: Estampado Interno | K27: 0 | L27: 2 | M27: 6 | N27: 12 | O27: 2 | P27: TERMINADO
F28: Sí | G28: Frech Terry 24/1 | H28: Sí | L28: CANTIDAD | O28: =SUM(K27:O27) -> 22
A29: OT13 | B29: Prendas Colegio Hijos de Maria | C29: 42893 | D29: 42903 | E29: CASACAS | F29: Broche | G29: Cierre | H29: Tela | I29: Bordado | J29: Estampado Interno | K29: 0 | L29: 0 | M29: 10 | N29: 7 | O29: 6 | P29: TERMINADO
F30: No | G30: Sí | H30: Frech Terry 24/1 | I30: Sí | J30: Sí | L30: CANTIDAD | O30: =SUM(K29:O29) -> 23
A31: OT14 | B31: Prendas GE San Luis Gonzaga | C31: 42896 | D31: 42906 | E31: CASACAS | F31: Broche | G31: Cierre | H31: Tela | I31: Bordado | J31: Estampado Interno | K31: 0 | L31: 4 | M31: 13 | N31: 10 | O31: 2 | P31: TERMINADO
F32: Sí | G32: No | H32: Franela Perchada 24/1 | I32: Sí | J32: Sí | L32: CANTIDAD | O32: =SUM(K31:O31) -> 29
A33: OT15 | B33: Prendas IEP Nobel Trujillo | C33: 42903 | D33: 42911 | E33: CASACAS | F33: Broche | G33: Cierre | H33: Tela | I33: Bordado | J33: Estampado Interno | K33: 0 | L33: 13 | M33: 16 | N33: 16 | O33: 6 | P33: TERMINADO
F34: Sí | G34: Si | H34: Franela Perchada 24/1 | I34: Sí | J34: Sí | L34: CANTIDAD | O34: =SUM(K33:O33) -> 51
A35: OT16 | B35: Prendas Colegio Adviento College | C35: 42906 | D35: 42915 | E35: POLERAS | F35: Bordado | G35: Tela | H35: Estampado Interno | K35: 0 | L35: 7 | M35: 11 | N35: 7 | O35: 2 | P35: TERMINADO
F36: Sí | G36: Franela Perchada 24/1 | H36: Sí | L36: CANTIDAD | O36: =SUM(K35:O35) -> 27

Sheet Elección de Características
A1: Elección de Características del Producto
A3: POLOS | D3: POLERAS | G3: CASACAS | K3: PRODUCTOS
A4: Característica a Escoger | B4: Tipo | D4: Característica a Escoger | E4: Tipo | G4: Característica a Escoger | H4: Tipo | K4: POLOS
A5: Estampado Pecho | B5: Sí | C5: No | D5: Bordado | E5: Sí | F5: No | G5: Broche | H5: Sí | I5: No | K5: POLERAS
A6: Estampado Espalda | B6: Sí | C6: No | D6: Tela | E6: Frech Terry 24/1 | F6: Franela Perchada 24/1 | G6: Cierre | H6: Sí | I6: No | K6: CASACAS
A7: Tela | B7: Algodón tacto | C7: Jersey | D7: Estampado Interno | E7: Sí | F7: No | G7: Tela | H7: Frech Terry 24/1 | I7: Franela Perchada 24/1
A8: Insignia | B8: Sí | C8: No | G8: Bordado | H8: Sí | I8: No
A9: Cuello | B9: V | C9: Redondo | G9: Estampado Interno | H9: Sí | I9: No

Sheet Modelo_de_Cálculo_Costos
A1: METODOLOGIA DE COSTEO ABC
A3: METODOLOGIA DE COSTEO ABC: SISTEMA DE COSTEO ABC POR ÓRDENES DE TRABAJO
A4: Obtención en el modelo: Costo Integral
A31: PROCESO 1: CALCULO DEL COSTO DE LOS MATERIALES DIRECTOS A CADA ORDEN DE TRABAJO
A32: PROCESO 2: CALCULO DEL COSTO DE LOS SERVICIOS DIRECTOS A CADA ORDEN DE TRABAJO
A33: PROCESO 3: CALCULO DEL COSTO DE LA MANO DE OBRA DIRECTA A CADA ORDEN DE TRABAJO
A34: PROCESO 4: CALCULO DEL COSTO DE LOS COSTOS INDIRECTOS, GASTOS DE VENTAS Y DE ADMINISTRACIÓN A CADA ORDEN DE TRABAJO
A35: PROCESO 4A: CALCULO DEL ELEMENTO DE COSTO A CADA CENTRO DE ACTIVIDAD
A36: PROCESO 4B: CALCULO DEL COSTO DEL ELEMENTO DE COSTO DE CADA CENTRO DE ACTIVIDAD A CADA ACTIVIDAD DEL CENTRO DE ACTIVIDAD
A37: PROCESO 4C: CALCULO DEL COSTO DEL ELEMENTO DE COSTO DE ACTIVIDAD ESTRATÉGICA A ACTIVIDADES DE APOYO Y ACTIVIDADES OPERATIVAS
A38: PROCESO 4D: CALCULO DEL COSTO DEL ELEMENTO DE COSTO DE ACTIVIDAD DE APOYO A ACTIVIDADES OPERATIVAS
A39: PROCESO 4E: CALCULO DEL COSTO DEL ELEMENTO DE COSTO DE ACTIVIDAD OPERATIVA A CADA ORDEN DE TRABAJO
A40: PROCESO 5: CALCULO DEL COSTO DE CADA OBJETO DE COSTO

Sheet Centro de actividades
A1: CENTRO DE ACTIVIDADES
C3: CENTRO DE ACTIVIDAD | D3: TIPO
C4: Gerencia General | D4: Estratégico
C5: Gerencia de Ventas | D5: Estratégico
C6: Gerencia de Marketing | D6: Estratégico
C7: Gerencia de Producción | D7: Estratégico
C8: Logística | D8: Apoyo
C9: Administración | D9: Apoyo
C10: Tesorería y Contabilidad | D10: Apoyo
C11: Calidad | D11: Apoyo
C12: Pre y Post Venta | D12: Operativo
C13: Diseño | D13: Operativo
C14: Corte | D14: Operativo
... C16: Empaquetado y Rotulado | D16: Operativo
B18: CAE1 | C18: ACTIVIDADES DE GERENCIA GENERAL | E18: CAA1 | F18: ACTIVIDADES DE ÁREA ADMINISTRACIÓN | H18: CAO1 | I18: ACTIVIDADES DE ÁREA DE DISEÑO
B19: AE1 | C19: Administrar cuentas bancarias | E19: AA1 | F19: Realizar el pago de planilla | H19: AO1 | I19: Digitalizar firmas y símbolos
B20: AE2 | C20: Aprobar las órdenes de compra | E20: AA2 | F20: Controlar asistencia de trabajadores | H20: AO2 | I20: Unir firmas e imprimir
B21: AE3 | C21: Revisar informes mensuales | H21: AO3 | I21: Diseñar en CorelDraw símbolos pedidos
E22: CAA2 | F22: ACTIVIDADES DE ÁREA DE TESORERÍA Y CONTABILIDAD
B23: CAE2 | C23: ACTIVIDADES DE GERENCIA DE VENTAS | E23: AA3 | F23: Realizar estados financieros | H23: CAO2 | I23: ACTIVIDADES DE ÁREA DE CORTE
B24: AE4 | C24: Realizar el control de ventas | E24: AA4 | F24: Realizar los pagos a los proveedores | H24: AO4 | I24: Tender las telas sobre mesa de corte
E25: AA5 | F25: Realizar el costeo | H25: AO5 | I25: Marcar la tela superficial con tiza de sastre
B26: CAE3 | C26: ACTIVIDADES DE GERENCIA DE MARKETING | H26: AO6 | I26: Cortar con la máquina cada conjunto de telas
B27: AE5 | C27: Realizar visitas a colegios, universidades y otras instituciones | E27: CAA3 | F27: ACTIVIDADES DE ÁREA DE CALIDAD | H27: AO7 | I27: Etiquetar por prenda, talla y cliente con etiqueta de seguimiento
B28: AE6 | C28: Realizar publicaciones en redes sociales | E28: AA6 | F28: Revisar medidas del molde | H28: AO8 | I28: Embolsar para envío a Bordado y/o Estampado (externo)
E29: AA7 | F29: Revisar los bordados de cada prenda (si es que lo lleva)
B30: CAE4 | C30: ACTIVIDADES DE GERENCIA DE PRODUCCIÓN | E30: AA8 | F30: Revisar los estampados de cada prenda (si es que lo lleva) | H30: CAO3 | I30: ACTIVIDADES DE ÁREA DE ACABADO
B31: AE7 | C31: Analizar los indicadores de producción | E31: AA9 | F31: Revisar confección y uniones | H31: AO9 | I31: Limpiar con el piqueteador cada prenda
B32: AE8 | C32: Analizar volúmenes de producción y emitir órdenes de producción
E33: CAA4 | F33: ACTIVIDADES DE GERENCIA DE LOGÍSTICA | H33: CAO4 | I33: ACTIVIDADES DE ÁREA DE EMPAQUETADO Y ROTULADO
E34: AA10 | F34: Realizar la compra de materiales | H34: AO10 | I34: Desetiquetar cada parte de las prendas
E35: AA11 | F35: Trasladar los materiales hacia la planta de producción | H35: AO11 | I35: Doblar la prenda
E36: AA12 | F36: Realizar el traslado del producto en proceso al servicio directo | H36: AO12 | I36: Etiquetar con nombre del cliente cada prenda
H37: AO13 | I37: Embolsar para envío final
B38: COD | C38: ACTIVIDAD
B39: AE1 | C39: Administrar cuentas bancarias | H39: CAA5 | I39: ACTIVIDADES DE ÁREA DE PRE Y POST VENTA
B40: AE2 | C40: Aprobar las órdenes de compra | H40: AO14 | I40: Realizar el contrato
B41: AE3 | C41: Revisar informes mensuales | H41: AO15 | I41: Entregar el pedido
B42: AE4 | C42: Realizar el control de ventas
B43: AE5 | C43: Realizar visitas a colegios, universidades y otras instituciones
B44: AE6 | C44: Realizar publicaciones en redes sociales
B45: AE7 | C45: Analizar los indicadores de producción
B46: AE8 | C46: Analizar volúmenes de producción y emitir órdenes de producción
B47: AA1 | C47: Realizar el pago de planilla
B48: AA2 | C48: Controlar asistencia de trabajadores
B49: AA3 | C49: Realizar estados financieros
B50: AA4 | C50: Realizar los pagos a los proveedores | E50: AE1 | F50: AE2 | G50: AE3 | H50: AE4 | I50: AE5 | J50: AE6 | K50: AE7 | L50: AE8 | M50: AA1 | N50: AA2 | O50: AA3 | P50: AA4 | Q50: AA5 | R50: AA6 | S50: AA7 | T50: AA8 | U50: AA9 | V50: AA10 | W50: AA11 | X50: AA12 | Y50: AO1 | Z50: AO2 | AA50: AO3 | AB50: AO4 | AC50: AO5 | AD50: AO6 | AE50: AO7 | AF50: AO8 | AG50: AO9 | AH50: AO10 | AI50: AO11 | AJ50: AO12 | AK50: AO13 | AL50: AO14 | AM50: AO15
B51: AA5 | C51: Realizar el costeo | E51: Administrar cuentas bancarias | F51: Aprobar las órdenes de compra | G51: Revisar informes mensuales | H51: Realizar el control de ventas | I51: Realizar visitas a colegios, universidades y otras instituciones | J51: Realizar publicaciones en redes sociales | K51: Analizar los indicadores de producción | L51: Analizar volúmenes de producción y emitir órdenes de producción | M51: Realizar el pago de planilla | N51: Controlar asistencia de trabajadores | O51: Realizar estados financieros | P51: Realizar los pagos a los proveedores | Q51: Realizar el costeo | R51: Revisar medidas del molde | S51: Revisar los bordados de cada prenda (si es que lo lleva) | T51: Revisar los estampados de cada prenda (si es que lo lleva) | U51: Revisar confección y uniones | V51: Realizar la compra de materiales | W51: Trasladar los materiales hacia la planta de producción | X51: Realizar el traslado del producto en proceso al servicio directo | Y51: Digitalizar firmas y símbolos | Z51: Unir firmas e imprimir | AA51: Diseñar en CorelDraw símbolos pedidos | AB51: Tender las telas sobre mesa de corte | AC51: Marcar la tela superficial con tiza de sastre | AD51: Cortar con la máquina cada conjunto de telas | AE51: Etiquetar por prenda, talla y cliente con etiqueta de seguimiento | AF51: Embolsar para envío a Bordado y/o Estampado (externo) | AG51: Limpiar con el piqueteador cada prenda | AH51: Desetiquetar cada parte de las prendas | AI51: Doblar la prenda | AJ51: Etiquetar con nombre del cliente cada prenda | AK51: Embolsar para envío final | AL51: Realizar el contrato | AM51: Entregar el pedido
B52: AA6 | C52: Revisar medidas del molde
B53: AA7 | C53: Revisar los bordados de cada prenda (si es que lo lleva)
B54: AA8 | C54: Revisar los estampados de cada prenda (si es que lo lleva)
B55: AA9 | C55: Revisar confección y uniones
B56: AA10 | C56: Realizar la compra de materiales
B57: AA11 | C57: Trasladar los materiales hacia la planta de producción
B58: AA12 | C58: Realizar el traslado del producto en proceso al servicio directo
B59: AO1 | C59: Digitalizar firmas y símbolos
B60: AO2 | C60: Unir firmas e imprimir
B61: AO3 | C61: Diseñar en CorelDraw símbolos pedidos
B62: AO4 | C62: Tender las telas sobre mesa de corte
B63: AO5 | C63: Marcar la tela superficial con tiza de sastre
... B73: AO15 | C73: Entregar el pedido

Sheet Maestro_Servicios_Directos
B1: TABLA MAESTRO DE SERVICIOS DIRECTOS
A2: Código de Servicios Directos | B2: Descripción | C2: cantidad maxima
C3: 15 | D3: 30 | E3: 60
A4: SD01 | B4: Estampado pecho | C4: 0.4 | D4: 0.3 | E4: 0.2
A5: SD02 | B5: Estampado espalda | C5: 0.7 | D5: 0.7 | E5: 0.6
A6: SD03 | B6: Estampado interno | C6: 0.4 | D6: 0.3 | E6: 0.2
A7: SD04 | B7: Bordado | C7: 7 | D7: 7 | E7: 7
A8: SD05 | B8: confeccion polo | C8: 4 | D8: 4 | E8: 3.8
A9: SD06 | B9: confeccion casaca | C9: 8.5 | D9: 8 | E9: 7.5
A10: SD07 | B10: confeccion polera | C10: 8.5 | D10: 8 | E10: 7.5
A13: Código de Servicios Directos | B13: Descripción | C13: Producto
C14: Casaca | D14: Polera | E14: Polo
A15: SD01 | B15: Estampado pecho | E15: X
A16: SD02 | B16: Estampado espalda | E16: X
A17: SD03 | B17: Estampado interno | C17: X | D17: X
A18: SD04 | B18: Bordado | C18: X | D18: X
A19: SD05 | B19: confeccion polo | E19: X
A20: SD06 | B20: confeccion casaca | C20: X
A21: SD07 | B21: confeccion polera | D21: X

Sheet Maestro_Materiales
B1: TABLA MAESTRO DE MATERIALES | D1: PRODUCTO | G1: PRODUCTO
A2: Código de Materiales | B2: Descripción | C2: Tipo | D2: POLOS | E2: POLERAS | F2: CASACAS | G2: POLOS | H2: POLERAS | I2: CASACAS | J2: UCO | K2: UCS | L2: Cto S/. UCO | M2: Descripción | N2: Conversion | O2: Cto S/. UCS
A3: MD01 | B3: Bolsas para empaquetado | C3: Bolsas | D3: X | E3: X | F3: X | G3: 1 | H3: 1 | I3: 1 | J3: ciento | K3: unidad | L3: 15 | M3: 1 ciento = 100 unid | N3: 100 | O3: =L3/N3 -> 0.15
A4: MD02 | B4: Broches | C4: Broche | F4: X | I4: 8 | J4: millar | K4: unidad | L4: 300 | M4: 1millar = 1000 unid | N4: 1000 | O4: =L4/N4 -> 0.3
A5: MD03 | B5: Cierre | C5: Cierre | F5: X | I5: 1 | J5: docena | K5: unidad | L5: 15 | M5: 1docena = 12 unid | N5: 12 | O5: =L5/N5 -> 1.25
A6: MD04 | B6: Etiqueta de la marca | C6: Etiqueta | D6: X | E6: X | F6: X | G6: 1 | H6: 1 | I6: 1 | J6: millar | K6: unidad | L6: 100 | M6: 1millar = 1000 unid | N6: 1000 | O6: =L6/N6 -> 0.1
A7: MD05 | B7: Etiqueta de los nombre | C7: Etiqueta | D7: X | E7: X | F7: X | G7: 1 | H7: 1 | I7: 1 | J7: ciento | K7: unidad | L7: 2 | M7: 1 ciento = 100 unid | N7: 100 | O7: =L7/N7 -> 0.02
A8: MD06 | B8: Etiqueta de los piezas (Etiquetas de Transferencia Térmica) | C8: Etiqueta | D8: X | E8: X | F8: X | G8: 4 | H8: 6 | I8: 6 | J8: Rollo | K8: unidad | L8: 40 | M8: 1rollo = 1500 unid | N8: 1500 | O8: =L8/N8 -> 0.026666667
A9: MD07 | B9: Hilo de costura | C9: Hilo | D9: X | E9: X | F9: X | G9: 0.2 | H9: 0.2 | I9: 0.2 | J9: unidad | K9: unidad | L9: 3 | N9: 1 | O9: =L9/N9 -> 3
A10: MD08 | B10: Hilo pasador | C10: Hilo | E10: X | H10: =5/20 -> 0.25 | J10: unidad | K10: unidad | L10: 2 | N10: 1 | O10: =L10/N10 -> 2
A11: MD09 | B11: Rib | C11: Rib | D11: X | E11: X | F11: X | G11: 0.15 | H11: 0.15 | I11: 0.15 | J11: kg | K11: metro | L11: 32 | M11: 1kg = 1.8mt | N11: 1.8 | O11: =L11/N11 -> 17.777778
A12: MD10 | B12: Franela Perchada 24/1 | C12: Tela | E12: X | F12: X | H12: =34/25 -> 1.36 | I12: =34/25 -> 1.36 | J12: fardos | K12: metro | L12: 550 | M12: 1fardo = 34 mt | N12: 34 | O12: =L12/N12 -> 16.176471
A13: MD11 | B13: Frech Terry 24/1 | C13: Tela | E13: X | F13: X | H13: =34/25 -> 1.36 | I13: =34/25 -> 1.36 | J13: kg | K13: metro | L13: 33 | M13: 1kg = 1.8mt | N13: 1.8 | O13: =L13/N13 -> 18.333333
A14: MD12 | B14: Jersey 30/1 | C14: Tela | D14: X | G14: =20/80 -> 0.25 | J14: fardos | K14: metro | L14: 550 | M14: 1fardo = 20 kg | N14: 20 | O14: =L14/N14 -> 27.5
A15: MD13 | B15: Algodón tacto | C15: Tela | D15: X | G15: 1.5 | J15: unidad | K15: unidad | L15: 4 | N15: 1 | O15: =L15/N15 -> 4
A18: NOTAS IMPORTANTES A CONSIDERAR
A19: * | B19: No se compra "Hilos para Bordados". Esto ya viene incluido en el costo del Servicio Directo de "BORDADO"
A20: * | B20: Los broches y los cierres no se colocan en la empresa. En el Servicio Directo de Confección, se le agrega estos elementos a las casacas | M20: >>> El costo de esta operación ya viene incluido en el costo del servicio directo "Confección para Casaca"
A21: * | B21: Es importante resaltar que no hay un uso permanente de almacén de materiales ya que se realizan compras por cada pedido que se tiene y esta se consume en su totalidad.

Sheet Matriz_Remu_MOD 
A1: Matriz de sueldos de MOD | I1: Considerando 30 días al mes (De lunes a Domingo) y 26 (De lunes a Sábado)
A2: CÓDIGO | B2: DESCRIPCIÓN | C2: PERSONAL | D2: ENCARGADO | E2: Horas Máxima de Dedicación | F2: Remuneración | G2: Cargas | H2: Beneficios | I2: Total (3 meses) | J2: Total (1 mes)
A4: CAO1 | B4: Área de Diseño | C4: Operario D1 | D4: PAVEL | E4: =1*26 -> 26 | F4: =F29 -> 150 | G4: =L16 -> 0 | H4: =L12 -> 0 | I4: =J4*3 -> 450 | J4: =SUM(F4:H4) -> 150
A5: CAO2 | B5: Área de Corte | C5: Operario C1 | D5: GROOVER | E5: =4*26 -> 104 | F5: =F19 -> 1000 | G5: =L24 -> 0 | H5: =L20 -> 0 | I5: =J5*3 -> 3000 | J5: =SUM(F5:H5) -> 1000
A6: CAO3 | B6: Área de acabado | C6: Operario A1 | D6: SERGIO | E6: =2*30 -> 60 | F6: =F13 -> 250 | G6: =L40 -> 0 | H6: =L39 -> 0 | I6: =J6*3 -> 750 | J6: =SUM(F6:H6) -> 250
A7: CAO4 | B7: Área de empaquetado y rotulado | C7: Operario ER1 | D7: SERGIO | E7: =2*30 -> 60 | F7: =F14 -> 250 | G7: =L45 -> 0 | H7: =L44 -> 0 | I7: =J7*3 -> 750 | J7: =SUM(F7:H7) -> 250
H8: TOTAL | I8: =SUM(I4:I7) -> 4950
B9: NOTAS IMPORTANTES A CONSIDERAR | F9: NOTA: Se cambio a periodo de Costeo 3 meses
A10: * | B10: Según dato de los dueños no reciben ningún tipo de beneficio ni hay un cargo adicional. Solo es la remuneración por sus actividades
A11: * | B11: El Sr. Sergio trabaja a medio tiempo de lunes a domingo. Recibe 500 de sueldo. Trabaja al día 4 horas. De las cuales dedica 2 horas al acabado y 2 horas al empaquetado y rotulado
B12: Sueldo | C12: 500 | E12: Horas | F12: Sueldo | H12: >>> | I12: Como trabaja en el área de Acabado y área de Empaquetado se procede a dividir el sueldo entre 2 (Asignará 2 horas a cada uno diariamente)
C13: >>>> MOD | D13: Acabado | E13: 2 | F13: =$C$12/$E$15*E13 -> 250
C14: >>>> MOD | D14: Empaquetado y Rotulado | E14: 2 | F14: =$C$12/$E$15*E14 -> 250
E15: =SUM(E13:E14) -> 4
A17: * | B17: Groover trabaja al día aproximadamente 10 horas. De las cuales dedica 4 horas a corte, 2 horas a la Gerencia General, 1 horas a la Gerencia de Producción, 1 hora al Área de Administración y 1 hora al área Logistica.
B18: Sueldo | C18: 2500 | E18: Horas | F18: Sueldo | H18: >>> | I18: Repartiremos su sueldo proporcional a la cantidad de horas que dedica a cada labor
C19: >>>> MOD | D19: Corte | E19: 4 | F19: =$C$18/$E$25*E19 -> 1000
D20: Gerencia General | E20: 2 | F20: =$C$18/$E$25*E20 -> 500
D21: Gerencia de Producción | E21: 1 | F21: =$C$18/$E$25*E21 -> 250
D22: Administración | E22: 1 | F22: =$C$18/$E$25*E22 -> 250
D23: Contabilidad y Tesorería | E23: 1 | F23: =$C$18/$E$25*E23 -> 250
D24: Logística | E24: 1 | F24: =$C$18/$E$25*E24 -> 250
E25: =SUM(E19:E24) -> 10
A27: * | B27: Pavel trabaja al día aproximadamente 10 horas. De las cuales dedica 1 hora al diseño, 2 horas al área de logística, 1 hora a la Gerencia de Ventas, 2 horas a la Gerencia de Marketing y 4 horas al área de Pre y Post Venta.
B28: Sueldo | C28: 1500 | E28: Horas | F28: Sueldo | H28: >>> | I28: Repartiremos su sueldo proporcional a la cantidad de horas que dedica a cada labor
C29: >>>> MOD | D29: Diseño | E29: 1 | F29: =$C$28/$E$34*E29 -> 150
D30: Logística | E30: 2 | F30: =$C$28/$E$34*E30 -> 300
D31: Gerencia de Ventas | E31: 1 | F31: =$C$28/$E$34*E31 -> 150
D32: Marketing | E32: 2 | F32: =$C$28/$E$34*E32 -> 300
D33: Pre y Post Venta | E33: 4 | F33: =$C$28/$E$34*E33 -> 600
E34: =SUM(E29:E33) -> 10
A36: * | B36: Los sueldos han sido distribuidos de acuerdo a la cantidad de horas que cada encargado le dedica al día. Estas horas que han servido para la distribución no son las HORAS EFECTIVAS de trabajo

Sheet Matriz_Tiemp_Efec_MOD 
A1: Matriz de Tiempos Efectivos por cada tipo de producto
A2: CÓDIGO | B2: DESCRIPCIÓN | C2: PERSONAL | D2: ENCARGADO | E2: UM | F2: CASACAS | G2: POLERAS | H2: POLOS
A4: CAO1 | B4: Área de Diseño | C4: Operario D1 | D4: PAVEL | E4: MinutosH | F4: =K13 -> 4.8 | G4: =K12 -> 4.8 | H4: =K11 -> 4.8
A5: CAO2 | B5: Área de Corte | C5: Operario C1 | D5: GROOVER | E5: MinutosH | F5: =K19 -> 14.4 | G5: =K18 -> 14.4 | H5: =K17 -> 9.6
A6: CAO3 | B6: Área de acabado | C6: Operario A1 | D6: SERGIO | E6: MinutosH | F6: =K25 -> 2.4 | G6: =K24 -> 2.4 | H6: =K23 -> 2.4
A7: CAO4 | B7: Área de empaquetado y rotulado | C7: Operario ER1 | D7: SERGIO | E7: MinutosH | F7: =K31 -> 4.8 | G7: =K30 -> 4.8 | H7: =K29 -> 4.8
A9: NOTAS IMPORTANTES A CONSIDERAR | I9: Cálculo de minutos efectivos por prenda
B10: Cálculo de los tiempos efectivos | I10: minutos | J10: cantidad | K10: min/unidad
A11: * | B11: En el proceso de Diseño, los encargados nos mencionaron que se demoran 2 horas para 25 polos o 25 casacas o 25 poleras | I11: 120 | J11: 25 | K11: =I11/J11 -> 4.8 | L11: polos
I12: 120 | J12: 25 | K12: =I12/J12 -> 4.8 | L12: poleras
I13: 120 | J13: 25 | K13: =I13/J13 -> 4.8 | L13: casacas
I15: Cálculo de minutos efectivos por prenda
I16: minutos | J16: cantidad | K16: min/unidad
A17: * | B17: En el proceso de Corte, los encargados nos mencionaron que se demoraban 4 horas para 25 polos y 6 horas para 25 casacas o 25 poleras | I17: 240 | J17: 25 | K17: =I17/J17 -> 9.6 | L17: polos
I18: 360 | J18: 25 | K18: =I18/J18 -> 14.4 | L18: poleras
I19: 360 | J19: 25 | K19: =I19/J19 -> 14.4 | L19: casacas
I21: Cálculo de minutos efectivos por prenda
A22: * | B22: En el proceso de acabado, que consiste en cortar los hilos, se demora 1 horas para 25 polos o 25 casacas o 25 poleras | I22: minutos | J22: cantidad | K22: min/unidad
I23: 60 | J23: 25 | K23: =I23/J23 -> 2.4 | L23: polos
I24: 60 | J24: 25 | K24: =I24/J24 -> 2.4 | L24: poleras
I25: 60 | J25: 25 | K25: =I25/J25 -> 2.4 | L25: casacas
I27: Cálculo de minutos efectivos por prenda
A28: * | B28: En el proceso de empaquetado y rotulado, se demora 2 horas para 25 polos o 25 casacas o 25 poleras | I28: minutos | J28: cantidad | K28: min/unidad
I29: 120 | J29: 25 | K29: =I29/J29 -> 4.8 | L29: polos
I30: 120 | J30: 25 | K30: =I30/J30 -> 4.8 | L30: poleras
I31: 120 | J31: 25 | K31: =I31/J31 -> 4.8 | L31: casacas

Sheet CMD
A1: CONSUMO DE MATERIALES DIRECTOS POR ORDEN DE TRABAJO
A2: Materiales | B2: Descripción | C2: Unidad Consumo | D2: Cantidad Unitaria de Consumo | G2: OT 1 | H2: OT2 | I2: OT3 | J2: OT4 | K2: OT 5 | L2: OT 6 | M2: OT 7 | N2: OT 8 | O2: OT 9 | P2: OT 10 | Q2: OT 11 | R2: OT 12 | S2: OT 13 | T2: OT 14 | U2: OT 15 | V2: OT 16
G3: CASACAS | H3: CASACAS | I3: POLOS | J3: POLERAS | K3: CASACAS | L3: POLERAS | M3: POLOS | N3: POLERAS | O3: POLERAS | P3: POLERAS | Q3: POLOS | R3: POLERAS | S3: CASACAS | T3: CASACAS | U3: CASACAS | V3: POLERAS
G4: TOTAL | H4: TOTAL | I4: TOTAL | J4: TOTAL | K4: TOTAL | L4: TOTAL | M4: TOTAL | N4: TOTAL | O4: TOTAL | P4: TOTAL | Q4: TOTAL | R4: TOTAL | S4: TOTAL | T4: TOTAL | U4: TOTAL | V4: TOTAL
G5: 21 | H5: =[2]OT!O8 -> 27 | I5: 27 | J5: =[2]OT!O12 -> 54 | K5: 21 | L5: 24 | M5: 26 | N5: 28 | O5: 17 | P5: 14 | Q5: 34 | R5: 22 | S5: 23 | T5: 29 | U5: 51 | V5: 27
D6: POLOS | E6: POLERAS | F6: CASACAS | G6: Terminado | H6: Terminado | I6: Terminado | J6: Terminado | K6: Terminado | L6: Terminado | M6: Terminado | N6: Terminado | O6: Terminado | P6: Terminado | Q6: Terminado | R6: Terminado | S6: Terminado | T6: Terminado | U6: Terminado | V6: Terminado
A7: =[2]Maestro_Materiales!A3 -> MD01 | B7: =[2]Maestro_Materiales!B3 -> Bolsas para empaquetado | C7: =[2]Maestro_Materiales!K3 -> unidad | D7: 1 | E7: 1 | F7: 1 | G7: =HLOOKUP($G$3,$D$6:$F$19,ROW(G2),0)*$G$5 -> 21 | H7: =HLOOKUP($H$3,$D$6:$F$19,ROW(H2),0)*$H$5 -> 27 | I7: =HLOOKUP($I$3,$D$6:$F$19,ROW(I2),0)*$I$5 -> 27 | J7: =HLOOKUP($J$3,$D$6:$F$19,ROW(J2),0)*J$5 -> 54 | K7: =HLOOKUP($J$3,$D$6:$F$19,ROW(K2),0)*K$5 -> 21 | L7: =HLOOKUP($J$3,$D$6:$F$19,ROW(L2),0)*L$5 -> 24 | M7: =HLOOKUP($J$3,$D$6:$F$19,ROW(M2),0)*M$5 -> 26 | N7: =HLOOKUP($J$3,$D$6:$F$19,ROW(N2),0)*N$5 -> 28 | O7: =HLOOKUP($J$3,$D$6:$F$19,ROW(O2),0)*O$5 -> 17 | P7: =HLOOKUP($J$3,$D$6:$F$19,ROW(P2),0)*P$5 -> 14 | Q7: =HLOOKUP($J$3,$D$6:$F$19,ROW(Q2),0)*Q$5 -> 34 | ... V7: =HLOOKUP($J$3,$D$6:$F$19,ROW(V2),0)*V$5 -> 27
A8: =[2]Maestro_Materiales!A4 -> MD02 | B8: =[2]Maestro_Materiales!B4 -> Broches | C8: =[2]Maestro_Materiales!K4 -> unidad | F8: 8 | G8: =HLOOKUP(G$3,$D$6:$F$19,ROW(G3),0)*G$5 -> 168 | H8: =HLOOKUP(H$3,$D$6:$F$19,ROW(H3),0)*H$5 -> 216 | I8: =HLOOKUP(I$3,$D$6:$F$19,ROW(I3),0)*I$5 -> 0 | J8: =HLOOKUP(J$3,$D$6:$F$19,ROW(J3),0)*J$5 -> 0 | K8: =HLOOKUP(K$3,$D$6:$F$19,ROW(K3),0)*K$5 -> 168 | L8: =HLOOKUP(L$3,$D$6:$F$19,ROW(L3),0)*L$5 -> 0 | M8: =HLOOKUP(M$3,$D$6:$F$19,ROW(M3),0)*M$5 -> 0 | N8: =HLOOKUP(N$3,$D$6:$F$19,ROW(N3),0)*N$5 -> 0 | ... V8: =HLOOKUP(V$3,$D$6:$F$19,ROW(V3),0)*V$5 -> 0
A9: =[2]Maestro_Materiales!A5 -> MD03 | B9: =[2]Maestro_Materiales!B5 -> Cierre | C9: =[2]Maestro_Materiales!K5 -> unidad | F9: 1 | G9: =HLOOKUP(G$3,$D$6:$F$19,ROW(G4),0)*G$5 -> 21 | H9: =HLOOKUP(H$3,$D$6:$F$19,ROW(H4),0)*H$5 -> 27 | I9: =HLOOKUP(I$3,$D$6:$F$19,ROW(I4),0)*I$5 -> 0 | J9: =HLOOKUP(J$3,$D$6:$F$19,ROW(J4),0)*J$5 -> 0 | K9: =HLOOKUP(K$3,$D$6:$F$19,ROW(K4),0)*K$5 -> 21 | L9: =HLOOKUP(L$3,$D$6:$F$19,ROW(L4),0)*L$5 -> 0 | M9: =HLOOKUP(M$3,$D$6:$F$19,ROW(M4),0)*M$5 -> 0 | N9: =HLOOKUP(N$3,$D$6:$F$19,ROW(N4),0)*N$5 -> 0 | ... V9: =HLOOKUP(V$3,$D$6:$F$19,ROW(V4),0)*V$5 -> 0
A10: =[2]Maestro_Materiales!A6 -> MD04 | B10: =[2]Maestro_Materiales!B6 -> Etiqueta de la marca | C10: =[2]Maestro_Materiales!K6 -> unidad | D10: 1 | E10: 1 | F10: 1 | G10: =HLOOKUP(G$3,$D$6:$F$19,ROW(G5),0)*G$5 -> 21 | H10: =HLOOKUP(H$3,$D$6:$F$19,ROW(H5),0)*H$5 -> 27 | I10: =HLOOKUP(I$3,$D$6:$F$19,ROW(I5),0)*I$5 -> 27 | J10: =HLOOKUP(J$3,$D$6:$F$19,ROW(J5),0)*J$5 -> 54 | K10: =HLOOKUP(K$3,$D$6:$F$19,ROW(K5),0)*K$5 -> 21 | L10: =HLOOKUP(L$3,$D$6:$F$19,ROW(L5),0)*L$5 -> 24 | M10: =HLOOKUP(M$3,$D$6:$F$19,ROW(M5),0)*M$5 -> 26 | N10: =HLOOKUP(N$3,$D$6:$F$19,ROW(N5),0)*N$5 -> 28 | ... V10: =HLOOKUP(V$3,$D$6:$F$19,ROW(V5),0)*V$5 -> 27
A11: =[2]Maestro_Materiales!A7 -> MD05 | B11: =[2]Maestro_Materiales!B7 -> Etiqueta de los nombre | C11: =[2]Maestro_Materiales!K7 -> unidad | D11: 1 | E11: 1 | F11: 1 | G11: =HLOOKUP(G$3,$D$6:$F$19,ROW(G6),0)*G$5 -> 21 | H11: =HLOOKUP(H$3,$D$6:$F$19,ROW(H6),0)*H$5 -> 27 | I11: =HLOOKUP(I$3,$D$6:$F$19,ROW(I6),0)*I$5 -> 27 | J11: =HLOOKUP(J$3,$D$6:$F$19,ROW(J6),0)*J$5 -> 54 | K11: =HLOOKUP(K$3,$D$6:$F$19,ROW(K6),0)*K$5 -> 21 | L11: =HLOOKUP(L$3,$D$6:$F$19,ROW(L6),0)*L$5 -> 24 | M11: =HLOOKUP(M$3,$D$6:$F$19,ROW(M6),0)*M$5 -> 26 | N11: =HLOOKUP(N$3,$D$6:$F$19,ROW(N6),0)*N$5 -> 28 | ... V11: =HLOOKUP(V$3,$D$6:$F$19,ROW(V6),0)*V$5 -> 27
A12: =[2]Maestro_Materiales!A8 -> MD06 | B12: =[2]Maestro_Materiales!B8 -> Etiqueta de los piezas (Etiquetas de Transferencia Térmica) | C12: =[2]Maestro_Materiales!K8 -> unidad | D12: 4 | E12: 6 | F12: 6 | G12: =HLOOKUP(G$3,$D$6:$F$19,ROW(G7),0)*G$5 -> 126 | H12: =HLOOKUP(H$3,$D$6:$F$19,ROW(H7),0)*H$5 -> 162 | I12: =HLOOKUP(I$3,$D$6:$F$19,ROW(I7),0)*I$5 -> 108 | J12: =HLOOKUP(J$3,$D$6:$F$19,ROW(J7),0)*J$5 -> 324 | K12: =HLOOKUP(K$3,$D$6:$F$19,ROW(K7),0)*K$5 -> 126 | L12: =HLOOKUP(L$3,$D$6:$F$19,ROW(L7),0)*L$5 -> 144 | M12: =HLOOKUP(M$3,$D$6:$F$19,ROW(M7),0)*M$5 -> 104 | N12: =HLOOKUP(N$3,$D$6:$F$19,ROW(N7),0)*N$5 -> 168 | ... V12: =HLOOKUP(V$3,$D$6:$F$19,ROW(V7),0)*V$5 -> 162
A13: =[2]Maestro_Materiales!A9 -> MD07 | B13: =[2]Maestro_Materiales!B9 -> Hilo de costura | C13: =[2]Maestro_Materiales!K9 -> unidad | D13: 0.2 | E13: 0.2 | F13: 0.2 | G13: =HLOOKUP(G$3,$D$6:$F$19,ROW(G8),0)*G$5 -> 4.2 | H13: =HLOOKUP(H$3,$D$6:$F$19,ROW(H8),0)*H$5 -> 5.4 | I13: =HLOOKUP(I$3,$D$6:$F$19,ROW(I8),0)*I$5 -> 5.4 | J13: =HLOOKUP(J$3,$D$6:$F$19,ROW(J8),0)*J$5 -> 10.8 | K13: =HLOOKUP(K$3,$D$6:$F$19,ROW(K8),0)*K$5 -> 4.2 | L13: =HLOOKUP(L$3,$D$6:$F$19,ROW(L8),0)*L$5 -> 4.8 | M13: =HLOOKUP(M$3,$D$6:$F$19,ROW(M8),0)*M$5 -> 5.2 | N13: =HLOOKUP(N$3,$D$6:$F$19,ROW(N8),0)*N$5 -> 5.6 | ... V13: =HLOOKUP(V$3,$D$6:$F$19,ROW(V8),0)*V$5 -> 5.4
A14: =[2]Maestro_Materiales!A10 -> MD08 | B14: =[2]Maestro_Materiales!B10 -> Hilo pasador | C14: =[2]Maestro_Materiales!K10 -> unidad | E14: =5/20 -> 0.25 | G14: =HLOOKUP(G$3,$D$6:$F$19,ROW(G9),0)*G$5 -> 0 | H14: =HLOOKUP(H$3,$D$6:$F$19,ROW(H9),0)*H$5 -> 0 | I14: =HLOOKUP(I$3,$D$6:$F$19,ROW(I9),0)*I$5 -> 0 | J14: =HLOOKUP(J$3,$D$6:$F$19,ROW(J9),0)*J$5 -> 13.5 | K14: =HLOOKUP(K$3,$D$6:$F$19,ROW(K9),0)*K$5 -> 0 | L14: =HLOOKUP(L$3,$D$6:$F$19,ROW(L9),0)*L$5 -> 6 | M14: =HLOOKUP(M$3,$D$6:$F$19,ROW(M9),0)*M$5 -> 0 | N14: =HLOOKUP(N$3,$D$6:$F$19,ROW(N9),0)*N$5 -> 7 | ... V14: =HLOOKUP(V$3,$D$6:$F$19,ROW(V9),0)*V$5 -> 6.75
A15: =[2]Maestro_Materiales!A11 -> MD09 | B15: =[2]Maestro_Materiales!B11 -> Rib | C15: =[2]Maestro_Materiales!K11 -> metro | D15: 0.15 | E15: 0.15 | F15: 0.15 | G15: =HLOOKUP(G$3,$D$6:$F$19,ROW(G10),0)*G$5 -> 3.15 | H15: =HLOOKUP(H$3,$D$6:$F$19,ROW(H10),0)*H$5 -> 4.05 | I15: =HLOOKUP(I$3,$D$6:$F$19,ROW(I10),0)*I$5 -> 4.05 | J15: =HLOOKUP(J$3,$D$6:$F$19,ROW(J10),0)*J$5 -> 8.1 | K15: =HLOOKUP(K$3,$D$6:$F$19,ROW(K10),0)*K$5 -> 3.15 | L15: =HLOOKUP(L$3,$D$6:$F$19,ROW(L10),0)*L$5 -> 3.6 | M15: =HLOOKUP(M$3,$D$6:$F$19,ROW(M10),0)*M$5 -> 3.9 | N15: =HLOOKUP(N$3,$D$6:$F$19,ROW(N10),0)*N$5 -> 4.2 | ... V15: =HLOOKUP(V$3,$D$6:$F$19,ROW(V10),0)*V$5 -> 4.05
A16: =[2]Maestro_Materiales!A12 -> MD10 | B16: =[2]Maestro_Materiales!B12 -> Franela Perchada 24/1 | C16: =[2]Maestro_Materiales!K12 -> metro | E16: =34/25 -> 1.36 | F16: =34/25 -> 1.36 | G16: =HLOOKUP(G$3,$D$6:$F$19,ROW(G11),0)*G$5 -> 28.56 | H16: =HLOOKUP(H$3,$D$6:$F$19,ROW(H11),0)*H$5 -> 36.72 | I16: =HLOOKUP(I$3,$D$6:$F$19,ROW(I11),0)*I$5 -> 0 | J16: =HLOOKUP(J$3,$D$6:$F$19,ROW(J11),0)*J$5 -> 73.44 | K16: =HLOOKUP(K$3,$D$6:$F$19,ROW(K11),0)*K$5 -> 28.56 | L16: =HLOOKUP(L$3,$D$6:$F$19,ROW(L11),0)*L$5 -> 32.64 | M16: =HLOOKUP(M$3,$D$6:$F$19,ROW(M11),0)*M$5 -> 0 | N16: =HLOOKUP(N$3,$D$6:$F$19,ROW(N11),0)*N$5 -> 38.08 | ... V16: =HLOOKUP(V$3,$D$6:$F$19,ROW(V11),0)*V$5 -> 36.72
A17: =[2]Maestro_Materiales!A13 -> MD11 | B17: =[2]Maestro_Materiales!B13 -> Frech Terry 24/1 | C17: =[2]Maestro_Materiales!K13 -> metro | E17: =34/25 -> 1.36 | F17: =34/25 -> 1.36 | G17: =HLOOKUP(G$3,$D$6:$F$19,ROW(G12),0)*G$5 -> 28.56 | H17: =HLOOKUP(H$3,$D$6:$F$19,ROW(H12),0)*H$5 -> 36.72 | I17: =HLOOKUP(I$3,$D$6:$F$19,ROW(I12),0)*I$5 -> 0 | J17: =HLOOKUP(J$3,$D$6:$F$19,ROW(J12),0)*J$5 -> 73.44 | K17: =HLOOKUP(K$3,$D$6:$F$19,ROW(K12),0)*K$5 -> 28.56 | L17: =HLOOKUP(L$3,$D$6:$F$19,ROW(L12),0)*L$5 -> 32.64 | M17: =HLOOKUP(M$3,$D$6:$F$19,ROW(M12),0)*M$5 -> 0 | N17: =HLOOKUP(N$3,$D$6:$F$19,ROW(N12),0)*N$5 -> 38.08 | ... V17: =HLOOKUP(V$3,$D$6:$F$19,ROW(V12),0)*V$5 -> 36.72
A18: =[2]Maestro_Materiales!A14 -> MD12 | B18: =[2]Maestro_Materiales!B14 -> Jersey 30/1 | C18: =[2]Maestro_Materiales!K14 -> metro | D18: =20/80 -> 0.25 | G18: =HLOOKUP(G$3,$D$6:$F$19,ROW(G13),0)*G$5 -> 0 | H18: =HLOOKUP(H$3,$D$6:$F$19,ROW(H13),0)*H$5 -> 0 | I18: =HLOOKUP(I$3,$D$6:$F$19,ROW(I13),0)*I$5 -> 6.75 | J18: =HLOOKUP(J$3,$D$6:$F$19,ROW(J13),0)*J$5 -> 0 | K18: =HLOOKUP(K$3,$D$6:$F$19,ROW(K13),0)*K$5 -> 0 | L18: =HLOOKUP(L$3,$D$6:$F$19,ROW(L13),0)*L$5 -> 0 | M18: =HLOOKUP(M$3,$D$6:$F$19,ROW(M13),0)*M$5 -> 6.5 | N18: =HLOOKUP(N$3,$D$6:$F$19,ROW(N13),0)*N$5 -> 0 | ... V18: =HLOOKUP(V$3,$D$6:$F$19,ROW(V13),0)*V$5 -> 0
A19: =[2]Maestro_Materiales!A15 -> MD13 | B19: =[2]Maestro_Materiales!B15 -> Algodón tacto | C19: =[2]Maestro_Materiales!K15 -> unidad | D19: 1.5 | G19: =HLOOKUP(G$3,$D$6:$F$19,ROW(G14),0)*G$5 -> 0 | H19: =HLOOKUP(H$3,$D$6:$F$19,ROW(H14),0)*H$5 -> 0 | I19: =HLOOKUP(I$3,$D$6:$F$19,ROW(I14),0)*I$5 -> 40.5 | J19: =HLOOKUP(J$3,$D$6:$F$19,ROW(J14),0)*J$5 -> 0 | K19: =HLOOKUP(K$3,$D$6:$F$19,ROW(K14),0)*K$5 -> 0 | L19: =HLOOKUP(L$3,$D$6:$F$19,ROW(L14),0)*L$5 -> 0 | M19: =HLOOKUP(M$3,$D$6:$F$19,ROW(M14),0)*M$5 -> 39 | N19: =HLOOKUP(N$3,$D$6:$F$19,ROW(N14),0)*N$5 -> 0 | ... V19: =HLOOKUP(V$3,$D$6:$F$19,ROW(V14),0)*V$5 -> 0
A22: CALCULO DEL COSTO UNITARIO DE MATERIAL DIRECTO POR ORDEN DE TRABAJO
A23: Materiales | B23: Descripción | C23: Unidad Consumo | D23: Cantidad Unitaria de Consumo | G23: =G2 -> OT 1 | H23: =H2 -> OT2 | I23: =I2 -> OT3 | J23: =J2 -> OT4 | K23: =K2 -> OT 5 | L23: =L2 -> OT 6 | M23: =M2 -> OT 7 | N23: =N2 -> OT 8 | ... V23: =V2 -> OT 16
G24: =G3 -> CASACAS | H24: =H3 -> CASACAS | I24: =I3 -> POLOS | J24: =J3 -> POLERAS | K24: =K3 -> CASACAS | L24: =L3 -> POLERAS | M24: =M3 -> POLOS | N24: =N3 -> POLERAS | ... V24: =V3 -> POLERAS
G25: =G4 -> TOTAL | H25: =H4 -> TOTAL | I25: =I4 -> TOTAL | J25: =J4 -> TOTAL | K25: =K4 -> TOTAL | L25: =L4 -> TOTAL | M25: =M4 -> TOTAL | N25: =N4 -> TOTAL | ... V25: =V4 -> TOTAL
G26: =G5 -> 21 | H26: =H5 -> 27 | I26: =I5 -> 27 | J26: =J5 -> 54 | K26: =K5 -> 21 | L26: =L5 -> 24 | M26: =M5 -> 26 | N26: =N5 -> 28 | ... V26: =V5 -> 27
D27: POLOS | E27: POLERAS | F27: CASACAS | G27: =G6 -> Terminado | H27: =H6 -> Terminado | I27: =I6 -> Terminado | J27: =J6 -> Terminado | K27: =K6 -> Terminado | L27: =L6 -> Terminado | M27: =M6 -> Terminado | N27: =N6 -> Terminado | ... V27: =V6 -> Terminado | W27: Cto S/. UCS
A28: =A7 -> MD01 | B28: =B7 -> Bolsas para empaquetado | C28: =C7 -> unidad | D28: 1 | E28: 1 | F28: 1 | G28: 0.15 | H28: 0.15 | I28: 0.15 | J28: 0.15 | K28: 0.15 | L28: 0.15 | M28: 0.15 | N28: 0.15 | O28: 0.15 | P28: 0.15 | Q28: 0.15 | R28: 0.15 | S28: 0.15 | T28: 0.15 | U28: 0.15 | V28: 0.15 | W28: 0.15
A29: =A8 -> MD02 | B29: =B8 -> Broches | C29: =C8 -> unidad | F29: 8 | G29: 0.3 | H29: 0.3 | I29: 0 | J29: 0 | K29: 0.3 | L29: 0 | M29: 0 | N29: 0 | O29: 0 | P29: 0 | Q29: 0 | R29: 0 | S29: 0 | T29: 0.3 | U29: 0.3 | V29: 0 | W29: 0.3
A30: =A9 -> MD03 | B30: =B9 -> Cierre | C30: =C9 -> unidad | F30: 1 | G30: 1.25 | H30: 0 | I30: 0 | J30: 0 | K30: 1.25 | L30: 0 | M30: 0 | N30: 0 | O30: 0 | P30: 0 | Q30: 0 | R30: 0 | S30: 1.25 | T30: 0 | U30: 1.25 | V30: 0 | W30: 1.25
A31: =A10 -> MD04 | B31: =B10 -> Etiqueta de la marca | C31: =C10 -> unidad | D31: 1 | E31: 1 | F31: 1 | G31: 0.1 | H31: 0.1 | I31: 0.1 | J31: 0.1 | K31: 0.1 | L31: 0.1 | M31: 0.1 | N31: 0.1 | O31: 0.1 | P31: 0.1 | Q31: 0.1 | R31: 0.1 | S31: 0.1 | T31: 0.1 | U31: 0.1 | V31: 0.1 | W31: 0.1
A32: =A11 -> MD05 | B32: =B11 -> Etiqueta de los nombre | C32: =C11 -> unidad | D32: 1 | E32: 1 | F32: 1 | G32: 0.02 | H32: 0.02 | I32: 0.02 | J32: 0.02 | K32: 0.02 | L32: 0.02 | M32: 0.02 | N32: 0.02 | O32: 0.02 | P32: 0.02 | Q32: 0.02 | R32: 0.02 | S32: 0.02 | T32: 0.02 | U32: 0.02 | V32: 0.02 | W32: 0.02
A33: =A12 -> MD06 | B33: =B12 -> Etiqueta de los piezas (Etiquetas de Transferencia Térmica) | C33: =C12 -> unidad | D33: 4 | E33: 6 | F33: 6 | G33: 0.026666667 | H33: 0.026666667 | I33: 0.026666667 | J33: 0.026666667 | K33: 0.026666667 | L33: 0.026666667 | M33: 0.026666667 | N33: 0.026666667 | O33: 0.026666667 | P33: 0.026666667 | Q33: 0.026666667 | R33: 0.026666667 | S33: 0.026666667 | T33: 0.026666667 | U33: 0.026666667 | V33: 0.026666667 | W33: 0.026666667
A34: =A13 -> MD07 | B34: =B13 -> Hilo de costura | C34: =C13 -> unidad | D34: 0.2 | E34: 0.2 | F34: 0.2 | G34: 3 | H34: 3 | I34: 3 | J34: 3 | K34: 3 | L34: 3 | M34: 3 | N34: 3 | O34: 3 | P34: 3 | Q34: 3 | R34: 3 | S34: 3 | T34: 3 | U34: 3 | V34: 3 | W34: 3
A35: =A14 -> MD08 | B35: =B14 -> Hilo pasador | C35: =C14 -> unidad | E35: =5/20 -> 0.25 | G35: 0 | H35: 0 | I35: 0 | J35: 2 | K35: 0 | L35: 0 | M35: 0 | N35: 2 | O35: 0 | P35: 0 | Q35: 0 | R35: 2 | S35: 0 | T35: 0 | U35: 0 | V35: 2 | W35: 2
A36: =A15 -> MD09 | B36: =B15 -> Rib | C36: =C15 -> metro | D36: 0.15 | E36: 0.15 | F36: 0.15 | G36: 17.777778 | H36: 17.777778 | I36: 17.777778 | J36: 17.777778 | K36: 17.777778 | L36: 17.777778 | M36: 17.777778 | N36: 17.777778 | O36: 17.777778 | P36: 17.777778 | Q36: 17.777778 | R36: 17.777778 | S36: 17.777778 | T36: 17.777778 | U36: 17.777778 | V36: 17.777778 | W36: 17.777778
A37: =A16 -> MD10 | B37: =B16 -> Franela Perchada 24/1 | C37: =C16 -> metro | E37: =34/25 -> 1.36 | F37: =34/25 -> 1.36 | G37: 16.176471 | H37: 16.176471 | I37: 0 | J37: 16.176471 | K37: 0 | L37: 0 | M37: 0 | N37: 16.18 | O37: 16.18 | P37: 0 | Q37: 0 | R37: 16.18 | S37: 0 | T37: 16.18 | U37: 16.18 | V37: 16.18 | W37: 16.176471
A38: =A17 -> MD11 | B38: =B17 -> Frech Terry 24/1 | C38: =C17 -> metro | E38: =34/25 -> 1.36 | F38: =34/25 -> 1.36 | G38: 0 | H38: 0 | I38: 0 | J38: 0 | K38: 18.333333 | L38: 18.333333 | M38: 0 | N38: 0 | O38: 0 | P38: 18.33 | Q38: 0 | R38: 0 | S38: 18.33 | T38: 0 | U38: 0 | V38: 0 | W38: 18.333333
A39: =A18 -> MD12 | B39: =B18 -> Jersey 30/1 | C39: =C18 -> metro | D39: =20/80 -> 0.25 | G39: 0 | H39: 0 | I39: 27.5 | J39: 0 | K39: 0 | L39: 0 | M39: 0 | N39: 0 | O39: 0 | P39: 0 | Q39: 27.5 | R39: 0 | S39: 0 | T39: 0 | U39: 0 | V39: 0 | W39: 27.5
A40: =A19 -> MD13 | B40: =B19 -> Algodón tacto | C40: =C19 -> unidad | D40: 1.5 | G40: 0 | H40: 0 | I40: 0 | J40: 0 | K40: 0 | L40: 0 | M40: 4 | N40: 0 | O40: 0 | P40: 0 | Q40: 0 | R40: 0 | S40: 0 | T40: 0 | U40: 0 | V40: 0 | W40: 4
A42: CALCULO DEL COSTO TOTAL DE MATERIAL DIRECTO POR ORDEN DE TRABAJO
A43: Materiales | B43: Descripción | C43: Unidad Consumo | D43: =G23 -> OT 1 | E43: =H23 -> OT2 | F43: =I23 -> OT3 | G43: =J23 -> OT4 | H43: =K23 -> OT 5 | I43: =L23 -> OT 6 | J43: =M23 -> OT 7 | K43: =N23 -> OT 8 | ... S43: =V23 -> OT 16
D44: =G3 -> CASACAS | E44: =H3 -> CASACAS | F44: =I3 -> POLOS | G44: =J3 -> POLERAS | H44: =K3 -> CASACAS | I44: =L3 -> POLERAS | J44: =M3 -> POLOS | K44: =N3 -> POLERAS | ... S44: =V3 -> POLERAS
D45: =G5 -> 21 | E45: =H5 -> 27 | F45: =I5 -> 27 | G45: =J5 -> 54 | H45: =K5 -> 21 | I45: =L5 -> 24 | J45: =M5 -> 26 | K45: =N5 -> 28 | ... S45: =V5 -> 27
D46: =G27 -> Terminado | E46: =H27 -> Terminado | F46: =I27 -> Terminado | G46: =J27 -> Terminado | H46: =K27 -> Terminado | I46: =L27 -> Terminado | J46: =M27 -> Terminado | K46: =N27 -> Terminado | ... S46: =V27 -> Terminado
A47: =A28 -> MD01 | B47: =B28 -> Bolsas para empaquetado | C47: =C28 -> unidad | D47: =G28*G7 -> 3.15 | E47: =H28*H7 -> 4.05 | F47: =I28*I7 -> 4.05 | G47: =J28*J7 -> 8.1 | H47: =K28*K7 -> 3.15 | I47: =L28*L7 -> 3.6 | J47: =M28*M7 -> 3.9 | K47: =N28*N7 -> 4.2 | ... S47: =V28*V7 -> 4.05
A48: =A29 -> MD02 | B48: =B29 -> Broches | C48: =C29 -> unidad | D48: =G29*G8 -> 50.4 | E48: =H29*H8 -> 64.8 | F48: =I29*I8 -> 0 | G48: =J29*J8 -> 0 | H48: =K29*K8 -> 50.4 | I48: =L29*L8 -> 0 | J48: =M29*M8 -> 0 | K48: =N29*N8 -> 0 | ... S48: =V29*V8 -> 0
A49: =A30 -> MD03 | B49: =B30 -> Cierre | C49: =C30 -> unidad | D49: =G30*G9 -> 26.25 | E49: =H30*H9 -> 0 | F49: =I30*I9 -> 0 | G49: =J30*J9 -> 0 | H49: =K30*K9 -> 26.25 | I49: =L30*L9 -> 0 | J49: =M30*M9 -> 0 | K49: =N30*N9 -> 0 | ... S49: =V30*V9 -> 0
A50: =A31 -> MD04 | B50: =B31 -> Etiqueta de la marca | C50: =C31 -> unidad | D50: =G31*G10 -> 2.1 | E50: =H31*H10 -> 2.7 | F50: =I31*I10 -> 2.7 | G50: =J31*J10 -> 5.4 | H50: =K31*K10 -> 2.1 | I50: =L31*L10 -> 2.4 | J50: =M31*M10 -> 2.6 | K50: =N31*N10 -> 2.8 | ... S50: =V31*V10 -> 2.7
A51: =A32 -> MD05 | B51: =B32 -> Etiqueta de los nombre | C51: =C32 -> unidad | D51: =G32*G11 -> 0.42 | E51: =H32*H11 -> 0.54 | F51: =I32*I11 -> 0.54 | G51: =J32*J11 -> 1.08 | H51: =K32*K11 -> 0.42 | I51: =L32*L11 -> 0.48 | J51: =M32*M11 -> 0.52 | K51: =N32*N11 -> 0.56 | ... S51: =V32*V11 -> 0.54
A52: =A33 -> MD06 | B52: =B33 -> Etiqueta de los piezas (Etiquetas de Transferencia Térmica) | C52: =C33 -> unidad | D52: =G33*G12 -> 3.36 | E52: =H33*H12 -> 4.32 | F52: =I33*I12 -> 2.88 | G52: =J33*J12 -> 8.64 | H52: =K33*K12 -> 3.36 | I52: =L33*L12 -> 3.84 | J52: =M33*M12 -> 2.7733333 | K52: =N33*N12 -> 4.48 | ... S52: =V33*V12 -> 4.32
A53: =A34 -> MD07 | B53: =B34 -> Hilo de costura | C53: =C34 -> unidad | D53: =G34*G13 -> 12.6 | E53: =H34*H13 -> 16.2 | F53: =I34*I13 -> 16.2 | G53: =J34*J13 -> 32.4 | H53: =K34*K13 -> 12.6 | I53: =L34*L13 -> 14.4 | J53: =M34*M13 -> 15.6 | K53: =N34*N13 -> 16.8 | ... S53: =V34*V13 -> 16.2
A54: =A35 -> MD08 | B54: =B35 -> Hilo pasador | C54: =C35 -> unidad | D54: =G35*G14 -> 0 | E54: =H35*H14 -> 0 | F54: =I35*I14 -> 0 | G54: =J35*J14 -> 27 | H54: =K35*K14 -> 0 | I54: =L35*L14 -> 0 | J54: =M35*M14 -> 0 | K54: =N35*N14 -> 14 | ... S54: =V35*V14 -> 13.5
A55: =A36 -> MD09 | B55: =B36 -> Rib | C55: =C36 -> metro | D55: =G36*G15 -> 56 | E55: =H36*H15 -> 72 | F55: =I36*I15 -> 72 | G55: =J36*J15 -> 144 | H55: =K36*K15 -> 56 | I55: =L36*L15 -> 64 | J55: =M36*M15 -> 69.333333 | K55: =N36*N15 -> 74.666667 | ... S55: =V36*V15 -> 72
A56: =A37 -> MD10 | B56: =B37 -> Franela Perchada 24/1 | C56: =C37 -> metro | D56: =G37*G16 -> 462 | E56: =H37*H16 -> 594 | F56: =I37*I16 -> 0 | G56: =J37*J16 -> 1188 | H56: =K37*K16 -> 0 | I56: =L37*L16 -> 0 | J56: =M37*M16 -> 0 | K56: =N37*N16 -> 616.1344 | ... S56: =V37*V16 -> 594.1296
A57: =A38 -> MD11 | B57: =B38 -> Frech Terry 24/1 | C57: =C38 -> metro | D57: =G38*G17 -> 0 | E57: =H38*H17 -> 0 | F57: =I38*I17 -> 0 | G57: =J38*J17 -> 0 | H57: =K38*K17 -> 523.6 | I57: =L38*L17 -> 598.4 | J57: =M38*M17 -> 0 | K57: =N38*N17 -> 0 | ... S57: =V38*V17 -> 0
A58: =A39 -> MD12 | B58: =B39 -> Jersey 30/1 | C58: =C39 -> metro | D58: =G39*G18 -> 0 | E58: =H39*H18 -> 0 | F58: =I39*I18 -> 185.625 | G58: =J39*J18 -> 0 | H58: =K39*K18 -> 0 | I58: =L39*L18 -> 0 | J58: =M39*M18 -> 0 | K58: =N39*N18 -> 0 | ... S58: =V39*V18 -> 0
A59: =A40 -> MD13 | B59: =B40 -> Algodón tacto | C59: =C40 -> unidad | D59: =G40*G19 -> 0 | E59: =H40*H19 -> 0 | F59: =I40*I19 -> 0 | G59: =J40*J19 -> 0 | H59: =K40*K19 -> 0 | I59: =L40*L19 -> 0 | J59: =M40*M19 -> 156 | K59: =N40*N19 -> 0 | ... S59: =V40*V19 -> 0
C61: CANTIDAD | D61: =D45 -> 21 | E61: =E45 -> 27 | F61: =F45 -> 27 | G61: =G45 -> 54 | H61: =H45 -> 21 | I61: =I45 -> 24 | J61: =J45 -> 26 | K61: =K45 -> 28 | ... S61: =S45 -> 27
C62: COSTO CMD | D62: =SUM(D47:D59) -> 616.28 | E62: =SUM(E47:E59) -> 758.61 | F62: =SUM(F47:F59) -> 283.995 | G62: =SUM(G47:G59) -> 1414.62 | H62: =SUM(H47:H59) -> 677.88 | I62: =SUM(I47:I59) -> 687.12 | J62: =SUM(J47:J59) -> 250.72667 | K62: =SUM(K47:K59) -> 733.64107 | ... S62: =SUM(S47:S59) -> 707.4396
C63: CuMD | D63: =D62/D61 -> 29.346667 | E63: =E62/E61 -> 28.096667 | F63: =F62/F61 -> 10.518333 | G63: =G62/G61 -> 26.196667 | H63: =H62/H61 -> 32.28 | I63: =I62/I61 -> 28.63 | J63: =J62/J61 -> 9.6433333 | K63: =K62/K61 -> 26.201467 | ... S63: =S62/S61 -> 26.201467
D65: Costo producción terminada | G65: =SUM(D62:S62) -> 10901.052

Sheet CMOD
B1: TIEMPO EFECTIVO EN MINUTOS DE OPERARIO POR ORDEN DE TRABAJO
G2: =[3]CMD!G24 -> CASACAS | H2: =[3]CMD!H24 -> CASACAS | I2: =[3]CMD!I24 -> POLOS | J2: =[3]CMD!J24 -> POLERAS | K2: =[3]CMD!K24 -> CASACA | L2: =[3]CMD!L24 -> POLERAS | M2: =[3]CMD!M24 -> POLOS | N2: =[3]CMD!N24 -> POLERAS | ... V2: =[3]CMD!V24 -> POLERAS
B3: CÓDIGO | C3: DESCRIPCIÓN | D3: PERSONAL | E3: ENCARGADO | F3: UM | G3: OT 1 | H3: OT 2 | I3: OT 3 | J3: OT 4 | K3: OT 5 | L3: OT 6 | M3: OT 7 | N3: OT 8 | O3: OT 9 | P3: OT 10 | Q3: OT 11 | R3: OT 12 | S3: OT 13 | T3: OT 14 | U3: OT 15 | V3: OT 16
G4: TOTAL | H4: TOTAL | I4: TOTAL | J4: TOTAL | K4: TOTAL | L4: TOTAL | M4: TOTAL | N4: TOTAL | O4: TOTAL | P4: TOTAL | Q4: TOTAL | R4: TOTAL | S4: TOTAL | T4: TOTAL | U4: TOTAL | V4: TOTAL
G5: 21 | H5: 27 | I5: 27 | J5: 54 | K5: 21 | L5: 24 | M5: 26 | N5: 28 | O5: 17 | P5: 14 | Q5: 34 | R5: 22 | S5: 23 | T5: 29 | U5: 51 | V5: 27
G6: Terminado | H6: Terminado | I6: Terminado | J6: Terminado | K6: Terminado | L6: Terminado | M6: Terminado | N6: Terminado | O6: Terminado | P6: Terminado | Q6: Terminado | R6: Terminado | S6: Terminado | T6: Terminado | U6: Terminado | V6: Terminado | X6: TOTAL (MinutosHEfectivo)
B7: CAO1 | C7: Área de Diseño | D7: Operario D1 | E7: PAVEL | F7: MinutosH | G7: 100.8 | H7: 129.6 | I7: 129.6 | J7: 259.2 | K7: 100.8 | L7: 115.2 | M7: 124.8 | N7: 134.4 | O7: 81.6 | P7: 67.2 | Q7: 163.2 | R7: 105.6 | S7: 110.4 | T7: 139.2 | U7: 244.8 | V7: 129.6 | X7: =SUM(G7:V7) -> 2136
B8: CAO2 | C8: Área de Corte | D8: Operario C1 | E8: GROOVER | F8: MinutosH | G8: 302.4 | H8: 388.8 | I8: 259.2 | J8: 777.6 | K8: 302.4 | L8: 345.6 | M8: 249.6 | N8: 403.2 | O8: 244.8 | P8: 201.6 | Q8: 326.4 | R8: 316.8 | S8: 331.2 | T8: 417.6 | U8: 489.6 | V8: 388.8 | X8: =SUM(G8:V8) -> 5745.6
B9: CAO3 | C9: Área de acabado | D9: Operario A1 | E9: SERGIO | F9: MinutosH | G9: 50.4 | H9: 64.8 | I9: 64.8 | J9: 129.6 | K9: 50.4 | L9: 57.6 | M9: 62.4 | N9: 67.2 | O9: 40.8 | P9: 33.6 | Q9: 81.6 | R9: 52.8 | S9: 55.2 | T9: 69.6 | U9: 122.4 | V9: 64.8 | X9: =SUM(G9:V9) -> 1068
B10: CAO4 | C10: Área de empaquetado y rotulado | D10: Operario ER1 | E10: SERGIO | F10: MinutosH | G10: 100.8 | H10: 129.6 | I10: 129.6 | J10: 259.2 | K10: 100.8 | L10: 115.2 | M10: 124.8 | N10: 134.4 | O10: 81.6 | P10: 67.2 | Q10: 163.2 | R10: 105.6 | S10: 110.4 | T10: 139.2 | U10: 244.8 | V10: 129.6 | X10: =SUM(G10:V10) -> 2136
B13: COSTO MINUTO DE LOS OPERARIOS
B14: CÓDIGO | C14: DESCRIPCIÓN | D14: PERSONAL | E14: ENCARGADO | F14: UM | G14: OT 1 | H14: OT2 | I14: OT3 | J14: OT4 | K14: OT 5 | L14: OT 6 | M14: OT 7 | N14: OT 8 | O14: OT 9 | P14: OT 10 | Q14: OT 11 | R14: OT 12 | S14: OT 13 | T14: OT 14 | U14: OT 15 | V14: OT 16
G15: =G2 -> CASACAS | H15: =H2 -> CASACAS | I15: =I2 -> POLOS | J15: =J2 -> POLERAS | K15: =K2 -> CASACA | L15: =L2 -> POLERAS | M15: =M2 -> POLOS | N15: =N2 -> POLERAS | ... V15: =V2 -> POLERAS
G16: =G5 -> 21 | H16: =H5 -> 27 | I16: =I5 -> 27 | J16: =J5 -> 54 | K16: =K5 -> 21 | L16: =L5 -> 24 | M16: =M5 -> 26 | N16: =N5 -> 28 | ... V16: =V5 -> 27
G17: Terminado | H17: Terminado | I17: Terminado | J17: Terminado | K17: Terminado | L17: Terminado | M17: Terminado | N17: Terminado | O17: Terminado | P17: Terminado | Q17: Terminado | R17: Terminado | S17: Terminado | T17: Terminado | U17: Terminado | V17: Terminado | X17: Tasa (Soles / MinutosHEfectivo)
B18: =B7 -> CAO1 | C18: Área de Diseño | D18: =D7 -> Operario D1 | E18: =E7 -> PAVEL | F18: MinutosH | G18: ='[3]Matriz_Remu_MOD '!$I4/CMOD!$X7 -> 0.070224719 | H18: ='[3]Matriz_Remu_MOD '!$I4/CMOD!$X7 -> 0.070224719 | I18: ='[3]Matriz_Remu_MOD '!$I4/CMOD!$X7 -> 0.070224719 | J18: ='[3]Matriz_Remu_MOD '!$I4/CMOD!$X7 -> 0.070224719 | K18: ='[3]Matriz_Remu_MOD '!$I4/CMOD!$X7 -> 0.070224719 | L18: ='[3]Matriz_Remu_MOD '!$I4/CMOD!$X7 -> 0.070224719 | M18: ='[3]Matriz_Remu_MOD '!$I4/CMOD!$X7 -> 0.070224719 | N18: ='[3]Matriz_Remu_MOD '!$I4/CMOD!$X7 -> 0.070224719 | ... V18: ='[3]Matriz_Remu_MOD '!$I4/CMOD!$X7 -> 0.070224719 | X18: 0.21067416
B19: =B8 -> CAO2 | C19: Área de Corte | D19: =D8 -> Operario C1 | E19: =E8 -> GROOVER | F19: MinutosH | G19: ='[3]Matriz_Remu_MOD '!$I5/CMOD!$X8 -> 0.17404623 | H19: ='[3]Matriz_Remu_MOD '!$I5/CMOD!$X8 -> 0.17404623 | I19: ='[3]Matriz_Remu_MOD '!$I5/CMOD!$X8 -> 0.17404623 | J19: ='[3]Matriz_Remu_MOD '!$I5/CMOD!$X8 -> 0.17404623 | K19: ='[3]Matriz_Remu_MOD '!$I5/CMOD!$X8 -> 0.17404623 | L19: ='[3]Matriz_Remu_MOD '!$I5/CMOD!$X8 -> 0.17404623 | M19: ='[3]Matriz_Remu_MOD '!$I5/CMOD!$X8 -> 0.17404623 | N19: ='[3]Matriz_Remu_MOD '!$I5/CMOD!$X8 -> 0.17404623 | ... V19: ='[3]Matriz_Remu_MOD '!$I5/CMOD!$X8 -> 0.17404623 | X19: 0.52213868
B20: =B9 -> CAO3 | C20: Área de acabado | D20: =D9 -> Operario A1 | E20: =E9 -> SERGIO | F20: MinutosH | G20: ='[3]Matriz_Remu_MOD '!$I6/CMOD!$X9 -> 0.2340824 | H20: ='[3]Matriz_Remu_MOD '!$I6/CMOD!$X9 -> 0.2340824 | I20: ='[3]Matriz_Remu_MOD '!$I6/CMOD!$X9 -> 0.2340824 | J20: ='[3]Matriz_Remu_MOD '!$I6/CMOD!$X9 -> 0.2340824 | K20: ='[3]Matriz_Remu_MOD '!$I6/CMOD!$X9 -> 0.2340824 | L20: ='[3]Matriz_Remu_MOD '!$I6/CMOD!$X9 -> 0.2340824 | M20: ='[3]Matriz_Remu_MOD '!$I6/CMOD!$X9 -> 0.2340824 | N20: ='[3]Matriz_Remu_MOD '!$I6/CMOD!$X9 -> 0.2340824 | ... V20: ='[3]Matriz_Remu_MOD '!$I6/CMOD!$X9 -> 0.2340824 | X20: 0.70224719
B21: =B10 -> CAO4 | C21: Área de empaquetado y rotulado | D21: =D10 -> Operario ER1 | E21: =E10 -> SERGIO | F21: MinutosH | G21: ='[3]Matriz_Remu_MOD '!$I7/CMOD!$X10 -> 0.1170412 | H21: ='[3]Matriz_Remu_MOD '!$I7/CMOD!$X10 -> 0.1170412 | I21: ='[3]Matriz_Remu_MOD '!$I7/CMOD!$X10 -> 0.1170412 | J21: ='[3]Matriz_Remu_MOD '!$I7/CMOD!$X10 -> 0.1170412 | K21: ='[3]Matriz_Remu_MOD '!$I7/CMOD!$X10 -> 0.1170412 | L21: ='[3]Matriz_Remu_MOD '!$I7/CMOD!$X10 -> 0.1170412 | M21: ='[3]Matriz_Remu_MOD '!$I7/CMOD!$X10 -> 0.1170412 | N21: ='[3]Matriz_Remu_MOD '!$I7/CMOD!$X10 -> 0.1170412 | ... V21: ='[3]Matriz_Remu_MOD '!$I7/CMOD!$X10 -> 0.1170412 | X21: 0.3511236
B24: COSTO MANO DE OBRA DIRECTA POR ORDEN DE TRABAJO
B25: CÓDIGO | C25: DESCRIPCIÓN | D25: PERSONAL | E25: ENCARGADO | F25: UM | G25: OT 1 | H25: OT2 | I25: OT3 | J25: OT4 | K25: OT 5 | L25: OT 6 | M25: OT 7 | N25: OT 8 | O25: OT 9 | P25: OT 10 | Q25: OT 11 | R25: OT 12 | S25: OT 13 | T25: OT 14 | U25: OT 15 | V25: OT 16
G26: =G15 -> CASACAS | H26: =H15 -> CASACAS | I26: =I15 -> POLOS | J26: =J15 -> POLERAS | K26: =K15 -> CASACA | L26: =L15 -> POLERAS | M26: =M15 -> POLOS | N26: =N15 -> POLERAS | ... V26: =V15 -> POLERAS
G27: =G16 -> 21 | H27: =H16 -> 27 | I27: =I16 -> 27 | J27: =J16 -> 54 | K27: =K16 -> 21 | L27: =L16 -> 24 | M27: =M16 -> 26 | N27: =N16 -> 28 | ... V27: =V16 -> 27
G28: Terminado | H28: Terminado | I28: Terminado | J28: Terminado | K28: Terminado | L28: Terminado | M28: Terminado | N28: Terminado | O28: Terminado | P28: Terminado | Q28: Terminado | R28: Terminado | S28: Terminado | T28: Terminado | U28: Terminado | V28: Terminado
B29: =B18 -> CAO1 | C29: =C18 -> Área de Diseño | D29: =D18 -> Operario D1 | E29: =E18 -> PAVEL | F29: =F18 -> MinutosH | G29: =G18*G7 -> 7.0786517 | H29: =H18*H7 -> 9.1011236 | I29: =I18*I7 -> 9.1011236 | J29: =J18*J7 -> 18.202247 | K29: =K18*K7 -> 7.0786517 | L29: =L18*L7 -> 8.0898876 | M29: =M18*M7 -> 8.7640449 | N29: =N18*N7 -> 9.4382022 | ... V29: =V18*V7 -> 9.1011236
B30: =B19 -> CAO2 | C30: =C19 -> Área de Corte | D30: =D19 -> Operario C1 | E30: =E19 -> GROOVER | F30: =F19 -> MinutosH | G30: =G19*G8 -> 52.631579 | H30: =H19*H8 -> 67.669173 | I30: =I19*I8 -> 45.112782 | J30: =J19*J8 -> 135.33835 | K30: =K19*K8 -> 52.631579 | L30: =L19*L8 -> 60.150376 | M30: =M19*M8 -> 43.441938 | N30: =N19*N8 -> 70.175439 | ... V30: =V19*V8 -> 67.669173
B31: =B20 -> CAO3 | C31: =C20 -> Área de acabado | D31: =D20 -> Operario A1 | E31: =E20 -> SERGIO | F31: =F20 -> MinutosH | G31: =G20*G9 -> 11.797753 | H31: =H20*H9 -> 15.168539 | I31: =I20*I9 -> 15.168539 | J31: =J20*J9 -> 30.337079 | K31: =K20*K9 -> 11.797753 | L31: =L20*L9 -> 13.483146 | M31: =M20*M9 -> 14.606742 | N31: =N20*N9 -> 15.730337 | ... V31: =V20*V9 -> 15.168539
B32: =B21 -> CAO4 | C32: =C21 -> Área de empaquetado y rotulado | D32: =D21 -> Operario ER1 | E32: =E21 -> SERGIO | F32: =F21 -> MinutosH | G32: =G21*G10 -> 11.797753 | H32: =H21*H10 -> 15.168539 | I32: =I21*I10 -> 15.168539 | J32: =J21*J10 -> 30.337079 | K32: =K21*K10 -> 11.797753 | L32: =L21*L10 -> 13.483146 | M32: =M21*M10 -> 14.606742 | N32: =N21*N10 -> 15.730337 | ... V32: =V21*V10 -> 15.168539
F33: Costo TOTAL | G33: =SUM(G29:G32) -> 83.305736 | H33: =SUM(H29:H32) -> 107.10738 | I33: =SUM(I29:I32) -> 84.550984 | J33: =SUM(J29:J32) -> 214.21475 | K33: =SUM(K29:K32) -> 83.305736 | L33: =SUM(L29:L32) -> 95.206556 | M33: =SUM(M29:M32) -> 81.419466 | N33: =SUM(N29:N32) -> 111.07432 | ... V33: =SUM(V29:V32) -> 107.10738 | W33: TOTAL PLANILLA
F34: Cantidad de Productos Terminados | G34: =G27 -> 21 | H34: =H27 -> 27 | I34: =I27 -> 27 | J34: =J27 -> 54 | K34: =K27 -> 21 | L34: =L27 -> 24 | M34: =M27 -> 26 | N34: =N27 -> 28 | ... V34: =V27 -> 27 | W34: =SUM(G33:V33) -> 1650
F35: CuMOD | G35: =(G33/G34) -> 3.9669398 | H35: =(H33/H34) -> 3.9669398 | I35: =(I33/I34) -> 3.1315179 | J35: =(J33/J34) -> 3.9669398 | K35: =(K33/K34) -> 3.9669398 | L35: =(L33/L34) -> 3.9669398 | M35: =(M33/M34) -> 3.1315179 | N35: =(N33/N34) -> 3.9669398 | ... V35: =(V33/V34) -> 3.9669398
G37: Costo producción terminada MOD | J37: =SUM(G33:V33) -> 1650

Sheet CSD
A2: CONSUMO DE SERVICIOS DIRECTOS POR ORDEN DE TRABAJO
A3: Servicios Directos | B3: Descripción | C3: OT 1 | D3: OT2 | E3: OT3 | F3: OT4 | G3: OT 5 | H3: OT 6 | I3: OT 7 | J3: OT 8 | K3: OT 9 | L3: OT 10 | M3: OT 11 | N3: OT 12 | O3: OT 13 | P3: OT 14 | Q3: OT 15 | R3: OT 16
C4: 21 | D4: 27 | E4: 27 | F4: 54 | G4: 21 | H4: 24 | I4: 26 | J4: 28 | K4: 17 | L4: 14 | M4: 34 | N4: 22 | O4: 23 | P4: 29 | Q4: 51 | R4: 27
C5: CASACAS | D5: CASACAS | E5: POLOS | F5: POLERAS | G5: CASACAS | H5: POLERAS | I5: POLOS | J5: POLERAS | K5: POLERAS | L5: POLERAS | M5: POLOS | N5: POLERAS | O5: CASACAS | P5: CASACAS | Q5: CASACAS | R5: POLERAS
A6: SD01 | B6: Estampado pecho | E6: 1 | I6: 1 | M6: 1
A7: SD02 | B7: Estampado espalda | E7: 0 | I7: 0 | M7: 0
A8: SD03 | B8: Estampado interno | C8: 1 | D8: 1 | F8: 1 | G8: 1 | H8: 1 | J8: 1 | K8: 1 | L8: 1 | N8: 1 | O8: 1 | P8: 1 | Q8: 1 | R8: 1
A9: SD04 | B9: Bordado | C9: 1 | D9: 1 | F9: 1 | G9: 1 | H9: 1 | J9: 1 | K9: 1 | L9: 1 | N9: 1 | O9: 1 | P9: 1 | Q9: 1 | R9: 1 | S9: * Tanto las poleras como las casacas pueden llevar bordados esto se detalla en el pedido. Mientras que los polos no llevan.
A10: SD05 | B10: confeccion polo | E10: 1 | I10: 1 | M10: 1 | T10: * Se ha separado el servicio directo de "confección" debido a que hay una ligera variación en el costo dependiendo el producto: polo, casaca o polera
A11: SD06 | B11: confeccion casaca | C11: 1 | D11: 1 | G11: 1 | H11: 1 | O11: 1 | P11: 1 | Q11: 1
A12: SD07 | B12: confeccion polera | F12: 1 | J12: 1 | K12: 1 | L12: 1 | N12: 1 | R12: 1
S13: * En la confección del polo, se realiza de manera adicional la insignia.
A14: COSTO SERVICIO DIRECTO POR ORDEN DE TRABAJO
A15: Servicios Directos | B15: Descripción | C15: OT 1 | D15: OT2 | E15: OT3 | F15: OT4 | G15: OT 5 | H15: OT 6 | I15: OT 7 | J15: OT 8 | K15: OT 9 | L15: OT 10 | M15: OT 11 | N15: OT 12 | O15: OT 13 | P15: OT 14 | Q15: OT 15 | R15: OT 16
A17: SD01 | B17: Estampado pecho | C17: 0 | D17: 0 | E17: 8.1 | F17: 0 | G17: 0 | H17: 0 | I17: 7.8 | J17: 0 | K17: 0 | L17: 0 | M17: 6.8 | N17: 0 | O17: 0 | P17: 0 | Q17: 0 | R17: 0
A18: SD02 | B18: Estampado espalda | C18: 0 | D18: 0 | E18: 0 | F18: 0 | G18: 0 | H18: 0 | I18: 0 | J18: 0 | K18: 0 | L18: 0 | M18: 0 | N18: 0 | O18: 0 | P18: 0 | Q18: 0 | R18: 0
A19: SD03 | B19: Estampado interno | C19: 6.3 | D19: 8.1 | E19: 0 | F19: 10.8 | G19: 6.3 | H19: 7.2 | I19: 0 | J19: 8.4 | K19: 5.1 | L19: 5.6 | M19: 0 | N19: 6.6 | O19: 6.9 | P19: 8.7 | Q19: 10.2 | R19: 8.1
A20: SD04 | B20: Bordado | C20: 147 | D20: 189 | E20: 0 | F20: 378 | G20: 147 | H20: 168 | I20: 0 | J20: 196 | K20: 119 | L20: 98 | M20: 0 | N20: 154 | O20: 161 | P20: 203 | Q20: 357 | R20: 189
A21: SD05 | B21: confeccion polo | C21: 0 | D21: 0 | E21: 108 | F21: 0 | G21: 0 | H21: 0 | I21: 104 | J21: 0 | K21: 0 | L21: 0 | M21: 129.2 | N21: 0 | O21: 0 | P21: 0 | Q21: 0 | R21: 0
A22: SD06 | B22: confeccion casaca | C22: 168 | D22: 216 | E22: 0 | F22: 0 | G22: 168 | H22: 192 | I22: 0 | J22: 0 | K22: 0 | L22: 0 | M22: 0 | N22: 0 | O22: 184 | P22: 232 | Q22: 382.5 | R22: 0
A23: SD07 | B23: confeccion polera | C23: 0 | D23: 0 | E23: 0 | F23: 405 | G23: 0 | H23: 0 | I23: 0 | J23: 224 | K23: 136 | L23: 119 | M23: 0 | N23: 176 | O23: 0 | P23: 0 | Q23: 0 | R23: 216
B25: Orden de Trabajo | C25: OT1 | D25: OT2 | E25: OT3 | F25: OT4 | G25: OT5 | H25: OT6 | I25: OT7 | J25: OT8 | K25: OT9 | L25: OT10 | M25: OT11 | N25: OT12 | O25: OT13 | P25: OT14 | Q25: OT15 | R25: OT16
B26: cantidad | C26: 21 | D26: 27 | E26: 27 | F26: 54 | G26: 21 | H26: 24 | I26: 26 | J26: 28 | K26: 17 | L26: 14 | M26: 34 | N26: 22 | O26: 23 | P26: 29 | Q26: 51 | R26: 27
B27: Costo total de SD | C27: 321.3 | D27: 413.1 | E27: 116.1 | F27: 793.8 | G27: 321.3 | H27: 367.2 | I27: 111.8 | J27: 428.4 | K27: 260.1 | L27: 222.6 | M27: 136 | N27: 336.6 | O27: 351.9 | P27: 443.7 | Q27: 749.7 | R27: 413.1
B28: Costo unitario SD | C28: 15.3 | D28: 15.3 | E28: 4.3 | F28: 14.7 | G28: 15.3 | H28: 15.3 | I28: 4.3 | J28: 15.3 | K28: 15.3 | L28: 15.9 | M28: 4 | N28: 15.3 | O28: 15.3 | P28: 15.3 | Q28: 14.7 | R28: 15.3

Sheet Elementos de Costo
A1: ELEMENTOS DE COSTOS
B3: TIPO DE ELEMENTO DE COSTO | C3: CODIGO | D3: ELEMENTO DE COSTO
B4: PERSONAL | C4: EC01 | D4: Sueldo de Groover
C5: EC02 | D5: Sueldo de Pavel
C6: EC03 | D6: Sueldo de Yessica
B7: INSUMOS | C7: EC04 | D7: Tiza para corte
B8: DEPRECIACIÓN MANTENIMIENTO | C8: EC05 | D8: Depreciación Mesa para Corte
C9: EC06 | D9: Depreciación Computadora
C10: EC07 | D10: Depreciación Cortadora
C11: EC08 | D11: Depreciación Etiquetadora
C12: EC09 | D12: Depreciación de molde
B13: SERVICIOS BÁSICOS | C13: EC10 | D13: Energía Eléctrica
C14: EC11 | D14: Agua
C15: EC12 | D15: Teléfono
C16: EC13 | D16: Servicio de internet
B17: TRANSPORTE | C17: EC14 | D17: Transporte de materia prima
C18: EC15 | D18: Transporte de producto en proceso a servicio de terceros
C19: EC16 | D19: Transporte del producto terminado al cliente
C20: EC17 | D20: Transporte para visitar al cliente
B21: BOLSAS | C21: EC18 | D21: Bolsas(empaque por lote)
C22: EC19 | D22: Bolsas (empaque para confección)
C23: EC20 | D23: Bolsas (empaque para bordado)
B24: PUBLICIDAD | C24: EC21 | D24: Volantes
C25: EC22 | D25: Afiches
C26: EC23 | D26: Dominio y Hosting
B27: OTROS COSTOS | C27: EC24 | D27: Piqueteador
C28: EC25 | D28: Alquiler del Local
C29: EC26 | D29: Útiles de escritorio
C30: EC27 | D30: Mantenimiento
C31: EC28 | D31: Impresión de firmas
C32: EC29 | D32: Formato de Contrato

Sheet Auxiliar 1
A1: IDENTIFICACIÓN DE INDUCTORES
D5: CENTRO DE ACTIVIDADES | AD5: CENTRO DE ACTIVIDADES
D6: CAE1 | E6: CAE2 | F6: CAE3 | G6: CAE4 | H6: CAA1 | I6: CAA2 | J6: CAA3 | K6: CAA4 | L6: CAO1 | M6: CAO2 | N6: CAO3 | O6: CAO4 | P6: CAO5 | AD6: CAE1 | AE6: CAE2 | AF6: CAE3 | AG6: CAE4 | AH6: CAA1 | AI6: CAA2 | AJ6: CAA3 | AK6: CAA4 | AL6: CAO1 | AM6: CAO2 | AN6: CAO3 | AO6: CAO4 | AP6: CAO5
A7: ELEMENTOS DE COSTOS | B7: EC01 | C7: Sueldo de Groover (Sin considerar CA Corte) | D7: X | G7: X | H7: X | I7: X | K7: X | S7: I N D U C T O R E S | T7: I01 | U7: Horas diarias dedicadas por Groover a cada C.A. | AD7: X | AG7: X | AH7: X | AI7: X | AK7: X
B8: EC02 | C8: Sueldo de Pavel (Sin considerar CA Diseño) | E8: X | F8: X | K8: X | P8: X | T8: I02 | U8: Horas diarias dedicadas por Pavel a cada C.A. | AE8: X | AF8: X | AK8: X | AP8: X
B9: EC03 | C9: Sueldo de Yessica | J9: X | T9: I03 | U9: Horas diarias dedicadas por Yessica a cada C.A. | AJ9: X
B10: EC04 | C10: Tiza para corte | M10: X | T10: I04 | U10: % Asignación | AM10: X
B11: EC05 | C11: Depreciación Mesa para Corte | M11: X | N11: X | O11: X | T11: I05 | U11: % de uso | AM11: X | AN11: X | AO11: X
B12: EC06 | C12: Depreciación Computadora | D12: X | E12: X | F12: X | G12: X | H12: X | I12: X | L12: X | T12: I06 | U12: % de uso | AD12: X | AE12: X | AF12: X | AG12: X | AH12: X | AI12: X | AL12: X
B13: EC07 | C13: Depreciación Cortadora | M13: X | T13: I07 | U13: % de uso | AM13: X
B14: EC08 | C14: Depreciación Etiquetadora | M14: X | O14: X | T14: I08 | U14: % de uso | AM14: X | AO14: X
B15: EC09 | C15: Depreciación de molde | M15: X | T15: I09 | U15: % Asignación | AM15: X
B16: EC10 | C16: Energía Eléctrica | D16: X | E16: X | F16: X | G16: X | H16: X | I16: X | J16: X | K16: X | L16: X | M16: X | N16: X | O16: X | P16: X | T16: I10 | U16: Proporción de Consumo de Kwh | AD16: X | AE16: X | AF16: X | AG16: X | AH16: X | AI16: X | AJ16: X | AK16: X | AL16: X | AM16: X | AN16: X | AO16: X | AP16: X
B17: EC11 | C17: Agua | D17: X | E17: X | F17: X | G17: X | H17: X | I17: X | J17: X | K17: X | L17: X | M17: X | N17: X | O17: X | P17: X | T17: I11 | U17: N° de personas en el C.A. | AD17: X | AE17: X | AF17: X | AG17: X | AH17: X | AI17: X | AJ17: X | AK17: X | AL17: X | AM17: X | AN17: X | AO17: X | AP17: X
B18: EC12 | C18: Teléfono | D18: X | E18: X | F18: X | G18: X | K18: X | P18: X | T18: I12 | U18: N° de personas en el C.A. | AD18: X | AE18: X | AF18: X | AG18: X | AK18: X | AP18: X
B19: EC13 | C19: Servicio de internet | D19: X | E19: X | F19: X | G19: X | H19: X | I19: X | L19: X | T19: I13 | U19: Flat Parcial | AD19: X | AE19: X | AF19: X | AG19: X | AH19: X | AI19: X | AL19: X
B20: EC14 | C20: Transporte de materia prima | K20: X | T20: I14 | U20: % Asignación | AK20: X
B21: EC15 | C21: Transporte de producto en proceso a servicio de terceros | K21: X | T21: I15 | U21: % Asignación | AK21: X
B22: EC16 | C22: Transporte del producto terminado al cliente | P22: X | T22: I16 | U22: % Asignación | AP22: X
B23: EC17 | C23: Transporte para visitar al cliente | P23: X | T23: I17 | U23: % Asignación | AP23: X
B24: EC18 | C24: Bolsas(empaque por lote) | O24: X | T24: I18 | U24: % de uso | AO24: X
B25: EC19 | C25: Bolsas (empaque para confección) | M25: X | T25: I19 | U25: % de uso | AM25: X
B26: EC20 | C26: Bolsas (empaque para bordado) | M26: X | T26: I20 | U26: % de uso | AM26: X
B27: EC21 | C27: Volantes | F27: X | T27: I21 | U27: % Asignación | AF27: X
B28: EC22 | C28: Afiches | F28: X | T28: I22 | U28: % Asignación | AF28: X
B29: EC23 | C29: Dominio y Hosting | F29: X | T29: I23 | U29: % Asignación | AF29: X
B30: EC24 | C30: Piqueteador | N30: X | T30: I24 | U30: % Asignación | AN30: X
B31: EC25 | C31: Alquiler del Local | D31: X | E31: X | F31: X | G31: X | H31: X | I31: X | J31: X | K31: X | L31: X | M31: X | N31: X | O31: X | P31: X | T31: I25 | U31: % de Importancia | AD31: X | AE31: X | AF31: X | AG31: X | AH31: X | AI31: X | AJ31: X | AK31: X | AL31: X | AM31: X | AN31: X | AO31: X | AP31: X
B32: EC26 | C32: Útiles de escritorio | D32: X | E32: X | F32: X | G32: X | H32: X | I32: X | L32: X | T32: I26 | U32: Flat Parcial | AD32: X | AE32: X | AF32: X | AG32: X | AH32: X | AI32: X | AL32: X
B33: EC27 | C33: Mantenimiento | M33: X | O33: X | T33: I27 | U33: % Asignación | AM33: X | AO33: X
B34: EC28 | C34: Impresión de firmas | L34: X | T34: I28 | U34: % Asignación | AL34: X
B35: EC29 | C35: Formato de Contrato | E35: X | P35: X | T35: I29 | U35: % Asignación | AE35: X | AP35: X
D38: I01 | E38: I02 | F38: I03 | G38: I04 | H38: I05 | I38: I06 | J38: I07 | K38: I08 | L38: I09 | M38: I10 | N38: I11 | O38: I12 | P38: I13 | Q38: I14 | R38: I15 | S38: I16 | T38: I17 | U38: I18 | V38: I19 | W38: I20 | X38: I21 | Y38: I22 | Z38: I23 | AA38: I24 | AB38: I25 | AC38: I26 | AD38: I27 | AE38: I28 | AF38: I29
A39: ELEMENTOS DE COSTOS | B39: EC01 | C39: Sueldo de Groover | D39: x
B40: EC02 | C40: Sueldo de Pavel | E40: x
B41: EC03 | C41: Sueldo de Yessica | F41: x
B42: EC04 | C42: Tiza para corte | G42: x
B43: EC05 | C43: Depreciación Mesa para Corte | H43: x
B44: EC06 | C44: Depreciación Computadora | I44: x
B45: EC07 | C45: Depreciación Cortadora | J45: x
B46: EC08 | C46: Depreciación Etiquetadora | K46: x
B47: EC09 | C47: Depreciación de molde | L47: x
B48: EC10 | C48: Energía Eléctrica | M48: x
B49: EC11 | C49: Agua | N49: x
B50: EC12 | C50: Teléfono | O50: x
B51: EC13 | C51: Servicio de internet | P51: x
B52: EC14 | C52: Transporte de materia prima | Q52: x
B53: EC15 | C53: Transporte de producto en proceso a servicio de terceros | R53: x
B54: EC16 | C54: Transporte del producto terminado al cliente | S54: x
B55: EC17 | C55: Transporte para visitar al cliente | T55: x
B56: EC18 | C56: Bolsas(empaque por lote) | U56: x
B57: EC19 | C57: Bolsas (empaque para confección) | V57: x
B58: EC20 | C58: Bolsas (empaque para bordado) | W58: x
B59: EC21 | C59: Volantes | X59: x
B60: EC22 | C60: Afiches | Y60: x
B61: EC23 | C61: Dominio y Hosting | Z61: x
B62: EC24 | C62: Piqueteador | AA62: x
B63: EC25 | C63: Alquiler del Local | AB63: x
B64: EC26 | C64: Útiles de escritorio | AC64: x
B65: EC27 | C65: Mantenimiento | AD65: x
B66: EC28 | C66: Impresión de firmas | AE66: x
B67: EC29 | C67: Formato de Contrato | AF67: x

Sheet Proceso I
A1: COSTO DE LOS ELEMENTOS DE COSTO POR ACTIVIDAD POR CENTRO DE ACTIVIDAD
C4: ESTRATÉGICO | G4: APOYO | K4: OPERATIVO
A5: ELEMENTO DE COSTO | C5: CAE1 | D5: CAE2 | E5: CAE3 | F5: CAE4 | G5: CAA1 | H5: CAA2 | I5: CAA3 | J5: CAA4 | K5: CAO1 | L5: CAO2 | M5: CAO3 | N5: CAO4 | O5: CAO5 | P5: TOTAL
A6: I01 | B6: =LOOKUP(A6,'Auxiliar 1'!$T$7:$T$35,'Auxiliar 1'!$U$7:$U$35) -> Horas diarias dedicadas por Groover a cada C.A. | C6: 2 | F6: 1 | G6: 1 | H6: 1 | J6: 1 | P6: =SUM(C6:O6) -> 6
A7: I02 | B7: =LOOKUP(A7,'Auxiliar 1'!$T$7:$T$35,'Auxiliar 1'!$U$7:$U$35) -> Horas diarias dedicadas por Pavel a cada C.A. | D7: 1 | E7: 2 | J7: 2 | O7: 4 | P7: =SUM(C7:O7) -> 9
A8: I03 | B8: =LOOKUP(A8,'Auxiliar 1'!$T$7:$T$35,'Auxiliar 1'!$U$7:$U$35) -> Horas diarias dedicadas por Yessica a cada C.A. | I8: 8 | P8: =SUM(C8:O8) -> 8
A9: I04 | B9: =LOOKUP(A9,'Auxiliar 1'!$T$7:$T$35,'Auxiliar 1'!$U$7:$U$35) -> % Asignación | L9: 1 | P9: =SUM(C9:O9) -> 1
A10: I05 | B10: =LOOKUP(A10,'Auxiliar 1'!$T$7:$T$35,'Auxiliar 1'!$U$7:$U$35) -> % de uso | L10: 0.25 | M10: 0.625 | N10: 0.125 | P10: =SUM(C10:O10) -> 1
A11: I06 | B11: =LOOKUP(A11,'Auxiliar 1'!$T$7:$T$35,'Auxiliar 1'!$U$7:$U$35) -> % de uso | C11: 0.1 | D11: 0.1 | E11: 0.2 | F11: 0.1 | G11: 0.1 | H11: 0.1 | K11: 0.3 | P11: =SUM(C11:O11) -> 1
A12: I07 | B12: =LOOKUP(A12,'Auxiliar 1'!$T$7:$T$35,'Auxiliar 1'!$U$7:$U$35) -> % de uso | L12: 1 | P12: =SUM(C12:O12) -> 1
A13: I08 | B13: =LOOKUP(A13,'Auxiliar 1'!$T$7:$T$35,'Auxiliar 1'!$U$7:$U$35) -> % de uso | L13: 0.8 | N13: 0.2 | P13: =SUM(C13:O13) -> 1
A14: I09 | B14: =LOOKUP(A14,'Auxiliar 1'!$T$7:$T$35,'Auxiliar 1'!$U$7:$U$35) -> % Asignación | L14: 1 | P14: =SUM(C14:O14) -> 1
A15: I10 | B15: =LOOKUP(A15,'Auxiliar 1'!$T$7:$T$35,'Auxiliar 1'!$U$7:$U$35) -> Proporción de Consumo de Kwh | C15: 5 | D15: 5 | E15: 10 | F15: 10 | G15: 10 | H15: 10 | I15: 5 | J15: 10 | K15: 20 | L15: 50 | M15: 10 | N15: 10 | O15: 10 | P15: =SUM(C15:O15) -> 165
A16: I11 | B16: =LOOKUP(A16,'Auxiliar 1'!$T$7:$T$35,'Auxiliar 1'!$U$7:$U$35) -> N° de personas en el C.A. | C16: 1 | D16: 1 | E16: 1 | F16: 1 | G16: 1 | H16: 1 | I16: 1 | J16: 2 | K16: 1 | L16: 1 | M16: 1 | N16: 1 | O16: 1 | P16: =SUM(C16:O16) -> 14
A17: I12 | B17: =LOOKUP(A17,'Auxiliar 1'!$T$7:$T$35,'Auxiliar 1'!$U$7:$U$35) -> N° de personas en el C.A. | C17: 1 | D17: 1 | E17: 1 | F17: 1 | J17: 2 | O17: 1 | P17: =SUM(C17:O17) -> 7
A18: I13 | B18: =LOOKUP(A18,'Auxiliar 1'!$T$7:$T$35,'Auxiliar 1'!$U$7:$U$35) -> Flat Parcial | C18: 1 | D18: 1 | E18: 1 | F18: 1 | G18: 1 | H18: 1 | K18: 1 | P18: =SUM(C18:O18) -> 7
A19: I14 | B19: =LOOKUP(A19,'Auxiliar 1'!$T$7:$T$35,'Auxiliar 1'!$U$7:$U$35) -> % Asignación | J19: 1 | P19: =SUM(C19:O19) -> 1
A20: I15 | B20: =LOOKUP(A20,'Auxiliar 1'!$T$7:$T$35,'Auxiliar 1'!$U$7:$U$35) -> % Asignación | J20: 1 | P20: =SUM(C20:O20) -> 1
A21: I16 | B21: =LOOKUP(A21,'Auxiliar 1'!$T$7:$T$35,'Auxiliar 1'!$U$7:$U$35) -> % Asignación | O21: 1 | P21: =SUM(C21:O21) -> 1
A22: I17 | B22: =LOOKUP(A22,'Auxiliar 1'!$T$7:$T$35,'Auxiliar 1'!$U$7:$U$35) -> % Asignación | O22: 1 | P22: =SUM(C22:O22) -> 1
A23: I18 | B23: =LOOKUP(A23,'Auxiliar 1'!$T$7:$T$35,'Auxiliar 1'!$U$7:$U$35) -> % de uso | N23: 1 | P23: =SUM(C23:O23) -> 1
A24: I19 | B24: =LOOKUP(A24,'Auxiliar 1'!$T$7:$T$35,'Auxiliar 1'!$U$7:$U$35) -> % de uso | L24: 1 | P24: =SUM(C24:O24) -> 1
A25: I20 | B25: =LOOKUP(A25,'Auxiliar 1'!$T$7:$T$35,'Auxiliar 1'!$U$7:$U$35) -> % de uso | L25: 1 | P25: =SUM(C25:O25) -> 1
A26: I21 | B26: =LOOKUP(A26,'Auxiliar 1'!$T$7:$T$35,'Auxiliar 1'!$U$7:$U$35) -> % Asignación | E26: 1 | P26: =SUM(C26:O26) -> 1
A27: I22 | B27: =LOOKUP(A27,'Auxiliar 1'!$T$7:$T$35,'Auxiliar 1'!$U$7:$U$35) -> % Asignación | E27: 1 | P27: =SUM(C27:O27) -> 1
A28: I23 | B28: =LOOKUP(A28,'Auxiliar 1'!$T$7:$T$35,'Auxiliar 1'!$U$7:$U$35) -> % Asignación | E28: 1 | P28: =SUM(C28:O28) -> 1
A29: I24 | B29: =LOOKUP(A29,'Auxiliar 1'!$T$7:$T$35,'Auxiliar 1'!$U$7:$U$35) -> % Asignación | M29: 1 | P29: =SUM(C29:O29) -> 1
A30: I25 | B30: =LOOKUP(A30,'Auxiliar 1'!$T$7:$T$35,'Auxiliar 1'!$U$7:$U$35) -> % de Importancia | C30: 0.05 | D30: 0.05 | E30: 0.05 | F30: 0.05 | G30: 0.05 | H30: 0.05 | I30: 0.1 | J30: 0.05 | K30: 0.11 | L30: 0.11 | M30: 0.11 | N30: 0.11 | O30: 0.11 | P30: =SUM(C30:O30) -> 1
A31: I26 | B31: =LOOKUP(A31,'Auxiliar 1'!$T$7:$T$35,'Auxiliar 1'!$U$7:$U$35) -> Flat Parcial | C31: 1 | D31: 1 | E31: 1 | F31: 1 | G31: 1 | H31: 1 | K31: 1 | P31: =SUM(C31:O31) -> 7
A32: I27 | B32: =LOOKUP(A32,'Auxiliar 1'!$T$7:$T$35,'Auxiliar 1'!$U$7:$U$35) -> % Asignación | L32: 0.45 | N32: 0.55 | P32: =SUM(C32:O32) -> 1
A33: I28 | B33: =LOOKUP(A33,'Auxiliar 1'!$T$7:$T$35,'Auxiliar 1'!$U$7:$U$35) -> % Asignación | K33: 1 | P33: =SUM(C33:O33) -> 1
A34: I29 | B34: =LOOKUP(A34,'Auxiliar 1'!$T$7:$T$35,'Auxiliar 1'!$U$7:$U$35) -> % Asignación | D34: 0.5 | O34: 0.5 | P34: =SUM(C34:O34) -> 1
C39: ESTRATÉGICO | G39: APOYO | K39: OPERATIVO | P39: MONTO A REPARTIR
A40: ELEMENTO DE COSTO | C40: CAE1 | D40: CAE2 | E40: CAE3 | F40: CAE4 | G40: CAA1 | H40: CAA2 | I40: CAA3 | J40: CAA4 | K40: CAO1 | L40: CAO2 | M40: CAO3 | N40: CAO4 | O40: CAO5
A41: EC01 | B41: Sueldo de Groover (Sin considerar CA Corte) | C41: =C6/$P6*$P41 -> 1500 | D41: =D6/$P6*$P41 -> 0 | E41: =E6/$P6*$P41 -> 0 | F41: =F6/$P6*$P41 -> 750 | G41: =G6/$P6*$P41 -> 750 | H41: =H6/$P6*$P41 -> 750 | I41: =I6/$P6*$P41 -> 0 | J41: =J6/$P6*$P41 -> 750 | ... O41: =O6/$P6*$P41 -> 0 | P41: 4500
A42: EC02 | B42: Sueldo de Pavel (Sin considerar CA Diseño) | C42: =C7/$P7*$P42 -> 0 | D42: =D7/$P7*$P42 -> 450 | E42: =E7/$P7*$P42 -> 900 | F42: =F7/$P7*$P42 -> 0 | G42: =G7/$P7*$P42 -> 0 | H42: =H7/$P7*$P42 -> 0 | I42: =I7/$P7*$P42 -> 0 | J42: =J7/$P7*$P42 -> 900 | ... O42: =O7/$P7*$P42 -> 1800 | P42: 4050
A43: EC03 | B43: Sueldo de Yessica | C43: =C8/$P8*$P43 -> 0 | D43: =D8/$P8*$P43 -> 0 | E43: =E8/$P8*$P43 -> 0 | F43: =F8/$P8*$P43 -> 0 | G43: =G8/$P8*$P43 -> 0 | H43: =H8/$P8*$P43 -> 0 | I43: =I8/$P8*$P43 -> 3300 | J43: =J8/$P8*$P43 -> 0 | ... O43: =O8/$P8*$P43 -> 0 | P43: 3300
A44: EC04 | B44: Tiza para corte | C44: =C9/$P9*$P44 -> 0 | D44: =D9/$P9*$P44 -> 0 | E44: =E9/$P9*$P44 -> 0 | F44: =F9/$P9*$P44 -> 0 | G44: =G9/$P9*$P44 -> 0 | H44: =H9/$P9*$P44 -> 0 | I44: =I9/$P9*$P44 -> 0 | J44: =J9/$P9*$P44 -> 0 | ... O44: =O9/$P9*$P44 -> 0 | P44: 6
A45: EC05 | B45: Depreciación Mesa para Corte | C45: =C10/$P10*$P45 -> 0 | D45: =D10/$P10*$P45 -> 0 | E45: =E10/$P10*$P45 -> 0 | F45: =F10/$P10*$P45 -> 0 | G45: =G10/$P10*$P45 -> 0 | H45: =H10/$P10*$P45 -> 0 | I45: =I10/$P10*$P45 -> 0 | J45: =J10/$P10*$P45 -> 0 | ... O45: =O10/$P10*$P45 -> 0 | P45: 33.75
A46: EC06 | B46: Depreciación Computadora | C46: =C11/$P11*$P46 -> 28.125 | D46: =D11/$P11*$P46 -> 28.125 | E46: =E11/$P11*$P46 -> 56.25 | F46: =F11/$P11*$P46 -> 28.125 | G46: =G11/$P11*$P46 -> 28.125 | H46: =H11/$P11*$P46 -> 28.125 | I46: =I11/$P11*$P46 -> 0 | J46: =J11/$P11*$P46 -> 0 | ... O46: =O11/$P11*$P46 -> 0 | P46: 281.25
A47: EC07 | B47: Depreciación Cortadora | C47: =C12/$P12*$P47 -> 0 | D47: =D12/$P12*$P47 -> 0 | E47: =E12/$P12*$P47 -> 0 | F47: =F12/$P12*$P47 -> 0 | G47: =G12/$P12*$P47 -> 0 | H47: =H12/$P12*$P47 -> 0 | I47: =I12/$P12*$P47 -> 0 | J47: =J12/$P12*$P47 -> 0 | ... O47: =O12/$P12*$P47 -> 0 | P47: 150.03
A48: EC08 | B48: Depreciación Etiquetadora | C48: =C13/$P13*$P48 -> 0 | D48: =D13/$P13*$P48 -> 0 | E48: =E13/$P13*$P48 -> 0 | F48: =F13/$P13*$P48 -> 0 | G48: =G13/$P13*$P48 -> 0 | H48: =H13/$P13*$P48 -> 0 | I48: =I13/$P13*$P48 -> 0 | J48: =J13/$P13*$P48 -> 0 | ... O48: =O13/$P13*$P48 -> 0 | P48: 29.97
A49: EC09 | B49: Depreciación de molde | C49: =C14/$P14*$P49 -> 0 | D49: =D14/$P14*$P49 -> 0 | E49: =E14/$P14*$P49 -> 0 | F49: =F14/$P14*$P49 -> 0 | G49: =G14/$P14*$P49 -> 0 | H49: =H14/$P14*$P49 -> 0 | I49: =I14/$P14*$P49 -> 0 | J49: =J14/$P14*$P49 -> 0 | ... O49: =O14/$P14*$P49 -> 0 | P49: 150
A50: EC10 | B50: Energía Eléctrica | C50: =C15/$P15*$P50 -> 21.818182 | D50: =D15/$P15*$P50 -> 21.818182 | E50: =E15/$P15*$P50 -> 43.636364 | F50: =F15/$P15*$P50 -> 43.636364 | G50: =G15/$P15*$P50 -> 43.636364 | H50: =H15/$P15*$P50 -> 43.636364 | I50: =I15/$P15*$P50 -> 21.818182 | J50: =J15/$P15*$P50 -> 43.636364 | ... O50: =O15/$P15*$P50 -> 43.636364 | P50: 720
A51: EC11 | B51: Agua | C51: =C16/$P16*$P51 -> 32.142857 | D51: =D16/$P16*$P51 -> 32.142857 | E51: =E16/$P16*$P51 -> 32.142857 | F51: =F16/$P16*$P51 -> 32.142857 | G51: =G16/$P16*$P51 -> 32.142857 | H51: =H16/$P16*$P51 -> 32.142857 | I51: =I16/$P16*$P51 -> 32.142857 | J51: =J16/$P16*$P51 -> 64.285714 | ... O51: =O16/$P16*$P51 -> 32.142857 | P51: 450
A52: EC12 | B52: Teléfono | C52: =C17/$P17*$P52 -> 85.714286 | D52: =D17/$P17*$P52 -> 85.714286 | E52: =E17/$P17*$P52 -> 85.714286 | F52: =F17/$P17*$P52 -> 85.714286 | G52: =G17/$P17*$P52 -> 0 | H52: =H17/$P17*$P52 -> 0 | I52: =I17/$P17*$P52 -> 0 | J52: =J17/$P17*$P52 -> 171.42857 | ... O52: =O17/$P17*$P52 -> 85.714286 | P52: 600
... A69: EC29 | B69: Formato de Contrato | C69: =C34/$P34*$P69 -> 0 | D69: =D34/$P34*$P69 -> 13.2 | E69: =E34/$P34*$P69 -> 0 | F69: =F34/$P34*$P69 -> 0 | G69: =G34/$P34*$P69 -> 0 | H69: =H34/$P34*$P69 -> 0 | I69: =I34/$P34*$P69 -> 0 | J69: =J34/$P34*$P69 -> 0 | ... O69: =O34/$P34*$P69 -> 13.2 | P69: 26.4
B70: TOTAL | C70: =SUM(C41:C69) -> 1818.8718 | D70: =SUM(D41:D69) -> 782.07175 | E70: =SUM(E41:E69) -> 1908.8149 | F70: =SUM(F41:F69) -> 1090.6899 | G70: =SUM(G41:G69) -> 1004.9756 | H70: =SUM(H41:H69) -> 1004.9756 | I70: =SUM(I41:I69) -> 3518.961 | J70: =SUM(J41:J69) -> 2811.8506 | ... O70: =SUM(O41:O69) -> 2476.1935 | P70: =SUM(C70:O70) -> 18695.4

Sheet Auxiliar 2
A1: IDENTIFICACIÓN DE INDUCTORES
D6: CAE1 | G6: CAE2 | H6: CAE3 | J6: CAE4 | L6: CAA1 | N6: CAA2 | Q6: CAA3 | U6: CAA4 | X6: CAO1 | AA6: CAO2 | AF6: CA03 | AG6: CAO4 | AK6: CAO5 | AO6: CAE1 | AT6: CAE2 | AW6: CAE3 | BA6: CAE4
B7: ELEMENTO DE COSTO | D7: AE1 | E7: AE2 | F7: AE3 | G7: AE4 | H7: AE5 | I7: AE6 | J7: AE7 | K7: AE8 | L7: AA1 | M7: AA2 | N7: AA3 | O7: AA4 | P7: AA5 | Q7: AA6 | R7: AA7 | S7: AA8 | T7: AA9 | U7: AA10 | V7: AA11 | W7: AA12 | X7: AO1 | Y7: AO2 | Z7: AO3 | AA7: AO4 | AB7: AO5 | AC7: AO6 | AD7: AO7 | AE7: AO8 | AF7: AO9 | AG7: AO10 | AH7: AO11 | AI7: AO12 | AJ7: AO13 | AK7: AO14 | AL7: AO15 | AO7: AE1 | AP7: AE2 | AQ7: AE3 | AT7: AE4 | AW7: AE5 | AX7: AE6 | BA7: AE7 | BB7: AE8
A8: ELEMENTOS DE COSTOS | B8: EC01 | C8: Sueldo de Groover (Sin considerar CA Corte) | D8: x | E8: x | F8: x | J8: x | K8: x | L8: x | M8: x | N8: X | O8: X | P8: X | U8: x | V8: x | W8: x | AN8: I01 | AO8: x | AP8: x | AQ8: x | AS8: I02 | AT8: x | AV8: I02 | AW8: x | AX8: x | AZ8: I01 | BA8: x | BB8: x
B9: EC02 | C9: Sueldo de Pavel (Sin considerar CA Diseño) | G9: x | H9: x | I9: x | U9: x | V9: x | W9: x | AK9: x | AL9: x | AN9: I06 | AO9: x | AQ9: x | AS9: I06 | AT9: x | AV9: I06 | AX9: x | AZ9: I06 | BA9: x | BB9: x
B10: EC03 | C10: Sueldo de Yessica | Q10: x | R10: x | S10: x | T10: x | AN10: I10 | AO10: x | AP10: x | AQ10: x | AS10: I10 | AT10: x | AV10: I10 | AX10: x | AZ10: I10 | BA10: x | BB10: x
B11: EC04 | C11: Tiza para corte | AB11: x | AN11: I11 | AO11: x | AP11: x | AQ11: x | AS11: I11 | AT11: x | AV11: I11 | AX11: x | AZ11: I11 | BA11: x | BB11: x
B12: EC05 | C12: Depreciación Mesa para Corte | AA12: x | AB12: x | AC12: x | AD12: x | AE12: x | AF12: x | AG12: x | AH12: x | AI12: x | AJ12: x | AN12: I12 | AP12: X | AS12: I12 | AT12: X | AV12: I12 | AW12: X | AX12: X | AZ12: I12 | BB12: X
B13: EC06 | C13: Depreciación Computadora | D13: x | F13: x | G13: x | I13: x | J13: x | K13: x | M13: x | N13: x | P13: x | X13: x | Y13: x | Z13: x | AN13: I13 | AO13: x | AS13: I13 | AT13: x | AV13: I13 | AX13: x | AZ13: I13 | BA13: x
B14: EC07 | C14: Depreciación Cortadora | AC14: x | AN14: I25 | AO14: x | AP14: x | AQ14: x | AS14: I25 | AT14: x | AV14: I21 | AW14: x | AZ14: I25 | BA14: x | BB14: x
B15: EC08 | C15: Depreciación Etiquetadora | AD15: x | AI15: x | AN15: I26 | AP15: x | AQ15: x | AS15: I26 | AT15: x | AV15: I22 | AW15: x | AZ15: I26 | BA15: x | BB15: x
B16: EC09 | C16: Depreciación de molde | AB16: x | AS16: I29 | AT16: x | AV16: I23 | AX16: x
B17: EC10 | C17: Energía Eléctrica | D17: x | E17: x | F17: x | G17: x | I17: x | J17: x | K17: x | L17: x | M17: x | N17: x | O17: x | P17: x | Q17: x | R17: x | S17: x | T17: x | U17: x | X17: x | Y17: x | Z17: x | AA17: x | AB17: x | AC17: x | AD17: x | AE17: x | AF17: x | AG17: x | AH17: x | AI17: x | AJ17: x | AV17: I25 | AX17: x
B18: EC11 | C18: Agua | D18: x | E18: x | F18: x | G18: x | I18: x | J18: x | K18: x | L18: x | M18: x | N18: x | O18: x | P18: x | Q18: x | R18: x | S18: x | T18: x | U18: x | X18: x | Y18: x | Z18: x | AA18: x | AB18: x | AC18: x | AD18: x | AE18: x | AF18: x | AG18: x | AH18: x | AI18: x | AJ18: x | AV18: I26 | AX18: x
B19: EC12 | C19: Teléfono | E19: X | G19: X | H19: X | I19: X | K19: X | U19: X | AK19: x | AL19: x
B20: EC13 | C20: Servicio de internet | D20: x | G20: x | I20: x | J20: x | M20: x | O20: x | X20: x | Y20: x | Z20: x
B21: EC14 | C21: Transporte de materia prima | U21: x | V21: x | AO21: CAA1 | AS21: CAA2 | AX21: CAA3 | BD21: CAA4
B22: EC15 | C22: Transporte de producto en proceso a servicio de terceros | W22: x | AO22: AA1 | AP22: AA2 | AS22: AA3 | AT22: AA4 | AU22: AA5 | AX22: AA6 | AY22: AA7 | AZ22: AA8 | BA22: AA9 | BD22: AA10 | BE22: AA11 | BF22: AA12
B23: EC16 | C23: Transporte del producto terminado al cliente | AL23: x | AN23: I01 | AO23: x | AP23: x | AR23: I01 | AS23: X | AT23: X | AU23: X | AW23: I03 | AX23: x | AY23: x | AZ23: x | BA23: x | BC23: I01 | BD23: x | BE23: x | BF23: x
B24: EC17 | C24: Transporte para visitar al cliente | AK24: x | AN24: I06 | AP24: x | AR24: I06 | AS24: x | AU24: x | AW24: I10 | AX24: x | AY24: x | AZ24: x | BA24: x | BC24: I02 | BD24: x | BE24: x | BF24: x
B25: EC18 | C25: Bolsas(empaque por lote) | AJ25: x | AN25: I10 | AO25: x | AP25: x | AR25: I10 | AS25: x | AT25: x | AU25: x | AW25: I11 | AX25: x | AY25: x | AZ25: x | BA25: x | BC25: I10 | BD25: x
B26: EC19 | C26: Bolsas (empaque para confección) | AE26: x | AN26: I11 | AO26: x | AP26: x | AR26: I11 | AS26: x | AT26: x | AU26: x | AW26: I25 | AX26: x | AY26: x | AZ26: x | BA26: x | BC26: I11 | BD26: x
B27: EC20 | C27: Bolsas (empaque para bordado) | AE27: x | AN27: I13 | AP27: x | AR27: I13 | AT27: x | BC27: I12 | BD27: X
B28: EC21 | C28: Volantes | H28: x | AN28: I25 | AO28: x | AP28: x | AR28: I25 | AS28: x | AT28: x | AU28: x | BC28: I14 | BD28: x | BE28: x
B29: EC22 | C29: Afiches | H29: x | AN29: I26 | AO29: x | AP29: x | AR29: I26 | AS29: x | AU29: x | BC29: I15 | BF29: x
B30: EC23 | C30: Dominio y Hosting | I30: x | BC30: I25 | BD30: x
B31: EC24 | C31: Piqueteador | AF31: x
B32: EC25 | C32: Alquiler del Local | D32: x | E32: x | F32: x | G32: x | I32: x | J32: x | K32: x | L32: x | M32: x | N32: x | O32: x | P32: x | Q32: x | R32: x | S32: x | T32: x | U32: x | X32: x | Y32: x | Z32: x | AA32: x | AB32: x | AC32: x | AD32: x | AE32: x | AF32: x | AG32: x | AH32: x | AI32: x | AJ32: x
B33: EC26 | C33: Útiles de escritorio | E33: x | F33: x | G33: x | I33: x | J33: x | K33: x | L33: x | M33: x | N33: x | P33: x | Y33: x
B34: EC27 | C34: Mantenimiento | AC34: x | AD34: x | AI34: x | AO34: CAO1 | AT34: CAO2 | BA34: CA03 | BD34: CAO4 | BJ34: CAO5
B35: EC28 | C35: Impresión de firmas | Z35: x | AO35: AO1 | AP35: AO2 | AQ35: AO3 | AT35: AO4 | AU35: AO5 | AV35: AO6 | AW35: AO7 | AX35: AO8 | BA35: AO9 | BD35: AO10 | BE35: AO11 | BF35: AO12 | BG35: AO13 | BJ35: AO14 | BK35: AO15
B36: EC29 | C36: Formato de Contrato | G36: x | AK36: x | AN36: I06 | AO36: x | AP36: x | AQ36: x | AS36: I04 | AU36: x | AZ36: I05 | BA36: x | BC36: I05 | BD36: x | BE36: x | BF36: x | BG36: x | BI36: I02 | BJ36: x | BK36: x
AN37: I10 | AO37: x | AP37: x | AQ37: x | AS37: I05 | AT37: x | AU37: x | AV37: x | AW37: x | AX37: x | AZ37: I10 | BA37: x | BC37: I08 | BF37: x | BI37: I12 | BJ37: x | BK37: x
AN38: I11 | AO38: x | AP38: x | AQ38: x | AS38: I07 | AV38: x | AZ38: I11 | BA38: x | BC38: I10 | BD38: x | BE38: x | BF38: x | BG38: x | BI38: I16 | BK38: x
AN39: I13 | AO39: x | AP39: x | AQ39: x | AS39: I08 | AW39: x | AZ39: I24 | BA39: x | BC39: I11 | BD39: x | BE39: x | BF39: x | BG39: x | BI39: I17 | BJ39: x
D40: I01 | E40: I02 | F40: I03 | G40: I04 | H40: I05 | I40: I06 | J40: I07 | K40: I08 | L40: I09 | M40: I10 | N40: I11 | O40: I12 | P40: I13 | Q40: I14 | R40: I15 | S40: I16 | T40: I17 | U40: I18 | V40: I19 | W40: I20 | X40: I21 | Y40: I22 | Z40: I23 | AA40: I24 | AB40: I25 | AC40: I26 | AD40: I27 | AE40: I28 | AF40: I29 | AN40: I25 | AO40: x | AP40: x | AQ40: x | AS40: I09 | AU40: x | AZ40: I25 | BA40: x | BC40: I18 | BG40: x | BI40: I29 | BJ40: x
A41: ELEMENTOS DE COSTOS | B41: EC01 | C41: Sueldo de Groover (Sin considerar CA Corte) | D41: x | AN41: I26 | AP41: x | AS41: I10 | AT41: x | AU41: x | AV41: x | AW41: x | AX41: x | BC41: I25 | BD41: x | BE41: x | BF41: x | BG41: x
B42: EC02 | C42: Sueldo de Pavel (Sin considerar CA Diseño) | E42: x | AN42: I28 | AQ42: x | AS42: I11 | AT42: x | AU42: x | AV42: x | AW42: x | AX42: x | BC42: I27 | BF42: x
B43: EC03 | C43: Sueldo de Yessica | F43: x | AS43: I19 | AX43: x
B44: EC04 | C44: Tiza para corte | G44: x | AS44: I20 | AX44: x
B45: EC05 | C45: Depreciación Mesa para Corte | H45: x | AS45: I25 | AT45: x | AU45: x | AV45: x | AW45: x | AX45: x
B46: EC06 | C46: Depreciación Computadora | I46: x | AS46: I27 | AV46: x | AW46: x
B47: EC07 | C47: Depreciación Cortadora | J47: x
B48: EC08 | C48: Depreciación Etiquetadora | K48: x
B49: EC09 | C49: Depreciación de molde | L49: x
B50: EC10 | C50: Energía Eléctrica | M50: x
B51: EC11 | C51: Agua | N51: x
B52: EC12 | C52: Teléfono | O52: x
B53: EC13 | C53: Servicio de internet | P53: x
B54: EC14 | C54: Transporte de materia prima | Q54: x
B55: EC15 | C55: Transporte de producto en proceso a servicio de terceros | R55: x
B56: EC16 | C56: Transporte del producto terminado al cliente | S56: x
B57: EC17 | C57: Transporte para visitar al cliente | T57: x
B58: EC18 | C58: Bolsas(empaque por lote) | U58: x
B59: EC19 | C59: Bolsas (empaque para confección) | V59: x
B60: EC20 | C60: Bolsas (empaque para bordado) | W60: x
B61: EC21 | C61: Volantes | X61: x
B62: EC22 | C62: Afiches | Y62: x
B63: EC23 | C63: Dominio y Hosting | Z63: x
B64: EC24 | C64: Piqueteador | AA64: x
B65: EC25 | C65: Alquiler del Local | AB65: x
B66: EC26 | C66: Útiles de escritorio | AC66: x
B67: EC27 | C67: Mantenimiento | AD67: x
B68: EC28 | C68: Impresión de firmas | AE68: x
B69: EC29 | C69: Formato de Contrato | AF69: x

Sheet Proceso II
A1: COSTO DE LOS ELEMENTOS DE COSTO POR ACTIVIDAD POR CENTRO DE ACTIVIDAD
B3: CENTRO DE ACTIVIDAD ESTRATÉGICO
A4: CAE1 | B4: GERENCIA GENERAL
C7: CAE1
C8: AE1 | D8: AE2 | E8: AE3 | F8: TOTAL
A9: INDUCTOR | C9: =HLOOKUP(C8,'Centro de actividades'!$E$50:$AM$51,2,0) -> Administrar cuentas bancarias | D9: =HLOOKUP(D8,'Centro de actividades'!$E$50:$AM$51,2,0) -> Aprobar las órdenes de compra | E9: =HLOOKUP(E8,'Centro de actividades'!$E$50:$AM$51,2,0) -> Revisar informes mensuales
A10: I01 | B10: =LOOKUP(A10,'Auxiliar 1'!$T$7:$T$35,'Auxiliar 1'!$U$7:$U$35) -> Horas diarias dedicadas por Groover a cada C.A. | C10: =F10*0.2 -> 0.4 | D10: =F10*0.3 -> 0.6 | E10: =F10*0.5 -> 1 | F10: =VLOOKUP(A10,'Proceso I'!$A$6:$O$34,3,0) -> 2
A11: I06 | B11: =LOOKUP(A11,'Auxiliar 1'!$T$7:$T$35,'Auxiliar 1'!$U$7:$U$35) -> % de uso | C11: =F11/2 -> 0.05 | E11: =F11/2 -> 0.05 | F11: =VLOOKUP(A11,'Proceso I'!$A$6:$O$34,3,0) -> 0.1
A12: I10 | B12: =LOOKUP(A12,'Auxiliar 1'!$T$7:$T$35,'Auxiliar 1'!$U$7:$U$35) -> Proporción de Consumo de Kwh | C12: =$F$12*C10/$F$10 -> 1 | D12: =$F$12*D10/$F$10 -> 1.5 | E12: =$F$12*E10/$F$10 -> 2.5 | F12: =VLOOKUP(A12,'Proceso I'!$A$6:$O$34,3,0) -> 5
A13: I11 | B13: =LOOKUP(A13,'Auxiliar 1'!$T$7:$T$35,'Auxiliar 1'!$U$7:$U$35) -> N° de personas en el C.A. | C13: =$F$13*C10/$F$10 -> 0.2 | D13: =$F$13*D10/$F$10 -> 0.3 | E13: =$F$13*E10/$F$10 -> 0.5 | F13: =VLOOKUP(A13,'Proceso I'!$A$6:$O$34,3,0) -> 1
A14: I12 | B14: =LOOKUP(A14,'Auxiliar 1'!$T$7:$T$35,'Auxiliar 1'!$U$7:$U$35) -> N° de personas en el C.A. | D14: 1 | F14: =VLOOKUP(A14,'Proceso I'!$A$6:$O$34,3,0) -> 1
A15: I13 | B15: =LOOKUP(A15,'Auxiliar 1'!$T$7:$T$35,'Auxiliar 1'!$U$7:$U$35) -> Flat Parcial | C15: =F15 -> 1 | F15: =VLOOKUP(A15,'Proceso I'!$A$6:$O$34,3,0) -> 1
A16: I25 | B16: =LOOKUP(A16,'Auxiliar 1'!$T$7:$T$35,'Auxiliar 1'!$U$7:$U$35) -> % de Importancia | C16: =C10*$F$16/$F$10 -> 0.01 | D16: =D10*$F$16/$F$10 -> 0.015 | E16: =E10*$F$16/$F$10 -> 0.025 | F16: =VLOOKUP(A16,'Proceso I'!$A$6:$O$34,3,0) -> 0.05
A17: I26 | B17: =LOOKUP(A17,'Auxiliar 1'!$T$7:$T$35,'Auxiliar 1'!$U$7:$U$35) -> Flat Parcial | D17: =F17*0.5 -> 0.5 | E17: =F17*0.5 -> 0.5 | F17: =VLOOKUP(A17,'Proceso I'!$A$6:$O$34,3,0) -> 1
C20: CAE1
C21: AE1 | D21: AE2 | E21: AE3 | F21: TOTAL | I21: º
A22: ELEMENTO DE COSTO | C22: =HLOOKUP(C21,'Centro de actividades'!$E$50:$AM$51,2,0) -> Administrar cuentas bancarias | D22: =HLOOKUP(D21,'Centro de actividades'!$E$50:$AM$51,2,0) -> Aprobar las órdenes de compra | E22: =HLOOKUP(E21,'Centro de actividades'!$E$50:$AM$51,2,0) -> Revisar informes mensuales
A23: =LOOKUP(A10,'Auxiliar 1'!$T$7:$T$35,'Auxiliar 1'!$B$7:$B$35) -> EC01 | B23: =LOOKUP(A23,'Auxiliar 1'!$B$7:$B$35,'Auxiliar 1'!$C$7:$C$35) -> Sueldo de Groover (Sin considerar CA Corte) | C23: =C10*$F23/$F10 -> 300 | D23: =D10*$F23/$F10 -> 450 | E23: =E10*$F23/$F10 -> 750 | F23: =VLOOKUP(A23,'Proceso I'!$A$41:$O$69,3,0) -> 1500
A24: =LOOKUP(A11,'Auxiliar 1'!$T$7:$T$35,'Auxiliar 1'!$B$7:$B$35) -> EC06 | B24: =LOOKUP(A24,'Auxiliar 1'!$B$7:$B$35,'Auxiliar 1'!$C$7:$C$35) -> Depreciación Computadora | C24: =C11*$F24/$F11 -> 14.0625 | D24: =D11*$F24/$F11 -> 0 | E24: =E11*$F24/$F11 -> 14.0625 | F24: =VLOOKUP(A24,'Proceso I'!$A$41:$O$69,3,0) -> 28.125
A25: =LOOKUP(A12,'Auxiliar 1'!$T$7:$T$35,'Auxiliar 1'!$B$7:$B$35) -> EC10 | B25: =LOOKUP(A25,'Auxiliar 1'!$B$7:$B$35,'Auxiliar 1'!$C$7:$C$35) -> Energía Eléctrica | C25: =C12*$F25/$F12 -> 4.3636364 | D25: =D12*$F25/$F12 -> 6.5454545 | E25: =E12*$F25/$F12 -> 10.909091 | F25: =VLOOKUP(A25,'Proceso I'!$A$41:$O$69,3,0) -> 21.818182
A26: =LOOKUP(A13,'Auxiliar 1'!$T$7:$T$35,'Auxiliar 1'!$B$7:$B$35) -> EC11 | B26: =LOOKUP(A26,'Auxiliar 1'!$B$7:$B$35,'Auxiliar 1'!$C$7:$C$35) -> Agua | C26: =C13*$F26/$F13 -> 6.4285714 | D26: =D13*$F26/$F13 -> 9.6428571 | E26: =E13*$F26/$F13 -> 16.071429 | F26: =VLOOKUP(A26,'Proceso I'!$A$41:$O$69,3,0) -> 32.142857
A27: =LOOKUP(A14,'Auxiliar 1'!$T$7:$T$35,'Auxiliar 1'!$B$7:$B$35) -> EC12 | B27: =LOOKUP(A27,'Auxiliar 1'!$B$7:$B$35,'Auxiliar 1'!$C$7:$C$35) -> Teléfono | C27: =C14*$F27/$F14 -> 0 | D27: =D14*$F27/$F14 -> 85.714286 | E27: =E14*$F27/$F14 -> 0 | F27: =VLOOKUP(A27,'Proceso I'!$A$41:$O$69,3,0) -> 85.714286
A28: =LOOKUP(A15,'Auxiliar 1'!$T$7:$T$35,'Auxiliar 1'!$B$7:$B$35) -> EC13 | B28: =LOOKUP(A28,'Auxiliar 1'!$B$7:$B$35,'Auxiliar 1'!$C$7:$C$35) -> Servicio de internet | C28: =C15*$F28/$F15 -> 64.285714 | D28: =D15*$F28/$F15 -> 0 | E28: =E15*$F28/$F15 -> 0 | F28: =VLOOKUP(A28,'Proceso I'!$A$41:$O$69,3,0) -> 64.285714
A29: =LOOKUP(A16,'Auxiliar 1'!$T$7:$T$35,'Auxiliar 1'!$B$7:$B$35) -> EC25 | B29: =LOOKUP(A29,'Auxiliar 1'!$B$7:$B$35,'Auxiliar 1'!$C$7:$C$35) -> Alquiler del Local | C29: =C16*$F29/$F16 -> 16.5 | D29: =D16*$F29/$F16 -> 24.75 | E29: =E16*$F29/$F16 -> 41.25 | F29: =VLOOKUP(A29,'Proceso I'!$A$41:$O$69,3,0) -> 82.5
A30: =LOOKUP(A17,'Auxiliar 1'!$T$7:$T$35,'Auxiliar 1'!$B$7:$B$35) -> EC26 | B30: =LOOKUP(A30,'Auxiliar 1'!$B$7:$B$35,'Auxiliar 1'!$C$7:$C$35) -> Útiles de escritorio | C30: =C17*$F30/$F17 -> 0 | D30: =D17*$F30/$F17 -> 2.1428571 | E30: =E17*$F30/$F17 -> 2.1428571 | F30: =VLOOKUP(A30,'Proceso I'!$A$41:$O$69,3,0) -> 4.2857143
B31: total | C31: =SUM(C23:C30) -> 405.64042 | D31: =SUM(D23:D30) -> 578.79545 | E31: =SUM(E23:E30) -> 834.43588 | F31: =SUM(F23:F30) -> 1818.8718
A33: CAE2 | B33: CENTRO DE ACTIVIDAD GERENCIA DE VENTAS
C36: CAE2
C37: AE4 | D37: TOTAL
A38: INDUCTOR | C38: =HLOOKUP(C37,'Centro de actividades'!$E$50:$AM$51,2,0) -> Realizar el control de ventas
A39: I02 | B39: =LOOKUP(A39,'Auxiliar 1'!$T$7:$T$35,'Auxiliar 1'!$U$7:$U$35) -> Horas diarias dedicadas por Pavel a cada C.A. | C39: =D39 -> 1 | D39: =VLOOKUP(A39,'Proceso I'!$A$6:$O$34,4,0) -> 1
A40: I06 | B40: =LOOKUP(A40,'Auxiliar 1'!$T$7:$T$35,'Auxiliar 1'!$U$7:$U$35) -> % de uso | C40: =D40 -> 0.1 | D40: =VLOOKUP(A40,'Proceso I'!$A$6:$O$34,4,0) -> 0.1
A41: I10 | B41: =LOOKUP(A41,'Auxiliar 1'!$T$7:$T$35,'Auxiliar 1'!$U$7:$U$35) -> Proporción de Consumo de Kwh | C41: =D41 -> 5 | D41: =VLOOKUP(A41,'Proceso I'!$A$6:$O$34,4,0) -> 5
A42: I11 | B42: =LOOKUP(A42,'Auxiliar 1'!$T$7:$T$35,'Auxiliar 1'!$U$7:$U$35) -> N° de personas en el C.A. | C42: =D42 -> 1 | D42: =VLOOKUP(A42,'Proceso I'!$A$6:$O$34,4,0) -> 1
A43: I12 | B43: =LOOKUP(A43,'Auxiliar 1'!$T$7:$T$35,'Auxiliar 1'!$U$7:$U$35) -> N° de personas en el C.A. | C43: =D43 -> 1 | D43: =VLOOKUP(A43,'Proceso I'!$A$6:$O$34,4,0) -> 1
A44: I13 | B44: =LOOKUP(A44,'Auxiliar 1'!$T$7:$T$35,'Auxiliar 1'!$U$7:$U$35) -> Flat Parcial | C44: =D44 -> 1 | D44: =VLOOKUP(A44,'Proceso I'!$A$6:$O$34,4,0) -> 1
A45: I25 | B45: =LOOKUP(A45,'Auxiliar 1'!$T$7:$T$35,'Auxiliar 1'!$U$7:$U$35) -> % de Importancia | C45: =D45 -> 0.05 | D45: =VLOOKUP(A45,'Proceso I'!$A$6:$O$34,4,0) -> 0.05
A46: I26 | B46: =LOOKUP(A46,'Auxiliar 1'!$T$7:$T$35,'Auxiliar 1'!$U$7:$U$35) -> Flat Parcial | C46: =D46 -> 1 | D46: =VLOOKUP(A46,'Proceso I'!$A$6:$O$34,4,0) -> 1
A47: I29 | B47: =LOOKUP(A47,'Auxiliar 1'!$T$7:$T$35,'Auxiliar 1'!$U$7:$U$35) -> % Asignación | C47: =D47 -> 0.5 | D47: =VLOOKUP(A47,'Proceso I'!$A$6:$O$34,4,0) -> 0.5
C50: CAE2
C51: AE4 | D51: TOTAL
A52: ELEMENTO DE COSTO | C52: =HLOOKUP(C51,'Centro de actividades'!$E$50:$AM$51,2,0) -> Realizar el control de ventas
A53: =LOOKUP(A39,'Auxiliar 1'!$T$7:$T$35,'Auxiliar 1'!$B$7:$B$35) -> EC02 | B53: =LOOKUP(A53,'Auxiliar 1'!$B$7:$B$35,'Auxiliar 1'!$C$7:$C$35) -> Sueldo de Pavel (Sin considerar CA Diseño) | C53: =C39*$D53/$D39 -> 450 | D53: =VLOOKUP(A53,'Proceso I'!$A$41:$O$69,4,0) -> 450
A54: =LOOKUP(A40,'Auxiliar 1'!$T$7:$T$35,'Auxiliar 1'!$B$7:$B$35) -> EC06 | B54: =LOOKUP(A54,'Auxiliar 1'!$B$7:$B$35,'Auxiliar 1'!$C$7:$C$35) -> Depreciación Computadora | C54: =C40*$D54/$D40 -> 28.125 | D54: =VLOOKUP(A54,'Proceso I'!$A$41:$O$69,4,0) -> 28.125
A55: =LOOKUP(A41,'Auxiliar 1'!$T$7:$T$35,'Auxiliar 1'!$B$7:$B$35) -> EC10 | B55: =LOOKUP(A55,'Auxiliar 1'!$B$7:$B$35,'Auxiliar 1'!$C$7:$C$35) -> Energía Eléctrica | C55: =C41*$D55/$D41 -> 21.818182 | D55: =VLOOKUP(A55,'Proceso I'!$A$41:$O$69,4,0) -> 21.818182
A56: =LOOKUP(A42,'Auxiliar 1'!$T$7:$T$35,'Auxiliar 1'!$B$7:$B$35) -> EC11 | B56: =LOOKUP(A56,'Auxiliar 1'!$B$7:$B$35,'Auxiliar 1'!$C$7:$C$35) -> Agua | C56: =C42*$D56/$D42 -> 32.142857 | D56: =VLOOKUP(A56,'Proceso I'!$A$41:$O$69,4,0) -> 32.142857
A57: =LOOKUP(A43,'Auxiliar 1'!$T$7:$T$35,'Auxiliar 1'!$B$7:$B$35) -> EC12 | B57: =LOOKUP(A57,'Auxiliar 1'!$B$7:$B$35,'Auxiliar 1'!$C$7:$C$35) -> Teléfono | C57: =C43*$D57/$D43 -> 85.714286 | D57: =VLOOKUP(A57,'Proceso I'!$A$41:$O$69,4,0) -> 85.714286
A58: =LOOKUP(A44,'Auxiliar 1'!$T$7:$T$35,'Auxiliar 1'!$B$7:$B$35) -> EC13 | B58: =LOOKUP(A58,'Auxiliar 1'!$B$7:$B$35,'Auxiliar 1'!$C$7:$C$35) -> Servicio de internet | C58: =C44*$D58/$D44 -> 64.285714 | D58: =VLOOKUP(A58,'Proceso I'!$A$41:$O$69,4,0) -> 64.285714
A59: =LOOKUP(A45,'Auxiliar 1'!$T$7:$T$35,'Auxiliar 1'!$B$7:$B$35) -> EC25 | B59: =LOOKUP(A59,'Auxiliar 1'!$B$7:$B$35,'Auxiliar 1'!$C$7:$C$35) -> Alquiler del Local | C59: =C45*$D59/$D45 -> 82.5 | D59: =VLOOKUP(A59,'Proceso I'!$A$41:$O$69,4,0) -> 82.5
A60: =LOOKUP(A46,'Auxiliar 1'!$T$7:$T$35,'Auxiliar 1'!$B$7:$B$35) -> EC26 | B60: =LOOKUP(A60,'Auxiliar 1'!$B$7:$B$35,'Auxiliar 1'!$C$7:$C$35) -> Útiles de escritorio | C60: =C46*$D60/$D46 -> 4.2857143 | D60: =VLOOKUP(A60,'Proceso I'!$A$41:$O$69,4,0) -> 4.2857143
A61: =LOOKUP(A47,'Auxiliar 1'!$T$7:$T$35,'Auxiliar 1'!$B$7:$B$35) -> EC29 | B61: =LOOKUP(A61,'Auxiliar 1'!$B$7:$B$35,'Auxiliar 1'!$C$7:$C$35) -> Formato de Contrato | C61: =C47*$D61/$D47 -> 13.2 | D61: =VLOOKUP(A61,'Proceso I'!$A$41:$O$69,4,0) -> 13.2
B62: total | C62: =SUM(C53:C61) -> 782.07175 | D62: =SUM(D53:D61) -> 782.07175
A64: CAE3 | B64: GERENCIA DE MARKETING
C67: CAE3
C68: AE5 | D68: AE6 | E68: TOTAL
A69: INDUCTOR | C69: =HLOOKUP(C68,'Centro de actividades'!$E$50:$AM$51,2,0) -> Realizar visitas a colegios, universidades y otras instituciones | D69: =HLOOKUP(D68,'Centro de actividades'!$E$50:$AM$51,2,0) -> Realizar publicaciones en redes sociales
A70: I02 | B70: =LOOKUP(A70,'Auxiliar 1'!$T$7:$T$35,'Auxiliar 1'!$U$7:$U$35) -> Horas diarias dedicadas por Pavel a cada C.A. | C70: 1 | D70: 1 | E70: =VLOOKUP(A70,'Proceso I'!$A$6:$O$34,5,0) -> 2
A71: I06 | B71: =LOOKUP(A71,'Auxiliar 1'!$T$7:$T$35,'Auxiliar 1'!$U$7:$U$35) -> % de uso | D71: 0.2 | E71: =VLOOKUP(A71,'Proceso I'!$A$6:$O$34,5,0) -> 0.2
A72: I10 | B72: =LOOKUP(A72,'Auxiliar 1'!$T$7:$T$35,'Auxiliar 1'!$U$7:$U$35) -> Proporción de Consumo de Kwh | D72: =E72 -> 10 | E72: =VLOOKUP(A72,'Proceso I'!$A$6:$O$34,5,0) -> 10
A73: I11 | B73: =LOOKUP(A73,'Auxiliar 1'!$T$7:$T$35,'Auxiliar 1'!$U$7:$U$35) -> N° de personas en el C.A. | D73: =E73 -> 1 | E73: =VLOOKUP(A73,'Proceso I'!$A$6:$O$34,5,0) -> 1
A74: I12 | B74: =LOOKUP(A74,'Auxiliar 1'!$T$7:$T$35,'Auxiliar 1'!$U$7:$U$35) -> N° de personas en el C.A. | C74: =$E74/2 -> 0.5 | D74: =$E74/2 -> 0.5 | E74: =VLOOKUP(A74,'Proceso I'!$A$6:$O$34,5,0) -> 1
A75: I13 | B75: =LOOKUP(A75,'Auxiliar 1'!$T$7:$T$35,'Auxiliar 1'!$U$7:$U$35) -> Flat Parcial | D75: =E75 -> 1 | E75: =VLOOKUP(A75,'Proceso I'!$A$6:$O$34,5,0) -> 1
A76: I21 | B76: =LOOKUP(A76,'Auxiliar 1'!$T$7:$T$35,'Auxiliar 1'!$U$7:$U$35) -> % Asignación | C76: =E76 -> 1 | E76: =VLOOKUP(A76,'Proceso I'!$A$6:$O$34,5,0) -> 1
A77: I22 | B77: =LOOKUP(A77,'Auxiliar 1'!$T$7:$T$35,'Auxiliar 1'!$U$7:$U$35) -> % Asignación | C77: =E77 -> 1 | E77: =VLOOKUP(A77,'Proceso I'!$A$6:$O$34,5,0) -> 1
A78: I23 | B78: =LOOKUP(A78,'Auxiliar 1'!$T$7:$T$35,'Auxiliar 1'!$U$7:$U$35) -> % Asignación | D78: =E78 -> 1 | E78: =VLOOKUP(A78,'Proceso I'!$A$6:$O$34,5,0) -> 1
A79: I25 | B79: =LOOKUP(A79,'Auxiliar 1'!$T$7:$T$35,'Auxiliar 1'!$U$7:$U$35) -> % de Importancia | D79: =E79 -> 0.05 | E79: =VLOOKUP(A79,'Proceso I'!$A$6:$O$34,5,0) -> 0.05
A80: I26 | B80: =LOOKUP(A80,'Auxiliar 1'!$T$7:$T$35,'Auxiliar 1'!$U$7:$U$35) -> Flat Parcial | D80: =E80 -> 1 | E80: =VLOOKUP(A80,'Proceso I'!$A$6:$O$34,5,0) -> 1
C83: CAE3
C84: AE5 | D84: AE6 | E84: TOTAL
A85: ELEMENTO DE COSTO | C85: =HLOOKUP(C84,'Centro de actividades'!$E$50:$AM$51,2,0) -> Realizar visitas a colegios, universidades y otras instituciones | D85: =HLOOKUP(D84,'Centro de actividades'!$E$50:$AM$51,2,0) -> Realizar publicaciones en redes sociales
A86: =LOOKUP(A70,'Auxiliar 1'!$T$7:$T$35,'Auxiliar 1'!$B$7:$B$35) -> EC02 | B86: =LOOKUP(A86,'Auxiliar 1'!$B$7:$B$35,'Auxiliar 1'!$C$7:$C$35) -> Sueldo de Pavel (Sin considerar CA Diseño) | C86: =C70*$E86/$E70 -> 450 | D86: =D70*$E86/$E70 -> 450 | E86: =VLOOKUP(A86,'Proceso I'!$A$41:$O$69,5,0) -> 900
A87: =LOOKUP(A71,'Auxiliar 1'!$T$7:$T$35,'Auxiliar 1'!$B$7:$B$35) -> EC06 | B87: =LOOKUP(A87,'Auxiliar 1'!$B$7:$B$35,'Auxiliar 1'!$C$7:$C$35) -> Depreciación Computadora | C87: =C71*$E87/$E71 -> 0 | D87: =D71*$E87/$E71 -> 56.25 | E87: =VLOOKUP(A87,'Proceso I'!$A$41:$O$69,5,0) -> 56.25
A88: =LOOKUP(A72,'Auxiliar 1'!$T$7:$T$35,'Auxiliar 1'!$B$7:$B$35) -> EC10 | B88: =LOOKUP(A88,'Auxiliar 1'!$B$7:$B$35,'Auxiliar 1'!$C$7:$C$35) -> Energía Eléctrica | C88: =C72*$E88/$E72 -> 0 | D88: =D72*$E88/$E72 -> 43.636364 | E88: =VLOOKUP(A88,'Proceso I'!$A$41:$O$69,5,0) -> 43.636364
A89: =LOOKUP(A73,'Auxiliar 1'!$T$7:$T$35,'Auxiliar 1'!$B$7:$B$35) -> EC11 | B89: =LOOKUP(A89,'Auxiliar 1'!$B$7:$B$35,'Auxiliar 1'!$C$7:$C$35) -> Agua | C89: =C73*$E89/$E73 -> 0 | D89: =D73*$E89/$E73 -> 32.142857 | E89: =VLOOKUP(A89,'Proceso I'!$A$41:$O$69,5,0) -> 32.142857
A90: =LOOKUP(A74,'Auxiliar 1'!$T$7:$T$35,'Auxiliar 1'!$B$7:$B$35) -> EC12 | B90: =LOOKUP(A90,'Auxiliar 1'!$B$7:$B$35,'Auxiliar 1'!$C$7:$C$35) -> Teléfono | C90: =C74*$E90/$E74 -> 42.857143 | D90: =D74*$E90/$E74 -> 42.857143 | E90: =VLOOKUP(A90,'Proceso I'!$A$41:$O$69,5,0) -> 85.714286
A91: =LOOKUP(A75,'Auxiliar 1'!$T$7:$T$35,'Auxiliar 1'!$B$7:$B$35) -> EC13 | B91: =LOOKUP(A91,'Auxiliar 1'!$B$7:$B$35,'Auxiliar 1'!$C$7:$C$35) -> Servicio de internet | C91: =C75*$E91/$E75 -> 0 | D91: =D75*$E91/$E75 -> 64.285714 | E91: =VLOOKUP(A91,'Proceso I'!$A$41:$O$69,5,0) -> 64.285714
A92: =LOOKUP(A76,'Auxiliar 1'!$T$7:$T$35,'Auxiliar 1'!$B$7:$B$35) -> EC21 | B92: =LOOKUP(A92,'Auxiliar 1'!$B$7:$B$35,'Auxiliar 1'!$C$7:$C$35) -> Volantes | C92: =C76*$E92/$E76 -> 60 | D92: =D76*$E92/$E76 -> 0 | E92: =VLOOKUP(A92,'Proceso I'!$A$41:$O$69,5,0) -> 60
A93: =LOOKUP(A77,'Auxiliar 1'!$T$7:$T$35,'Auxiliar 1'!$B$7:$B$35) -> EC22 | B93: =LOOKUP(A93,'Auxiliar 1'!$B$7:$B$35,'Auxiliar 1'!$C$7:$C$35) -> Afiches | C93: =C77*$E93/$E77 -> 280 | D93: =D77*$E93/$E77 -> 0 | E93: =VLOOKUP(A93,'Proceso I'!$A$41:$O$69,5,0) -> 280
A94: =LOOKUP(A78,'Auxiliar 1'!$T$7:$T$35,'Auxiliar 1'!$B$7:$B$35) -> EC23 | B94: =LOOKUP(A94,'Auxiliar 1'!$B$7:$B$35,'Auxiliar 1'!$C$7:$C$35) -> Dominio y Hosting | C94: =C78*$E94/$E78 -> 0 | D94: =D78*$E94/$E78 -> 300 | E94: =VLOOKUP(A94,'Proceso I'!$A$41:$O$69,5,0) -> 300
A95: =LOOKUP(A79,'Auxiliar 1'!$T$7:$T$35,'Auxiliar 1'!$B$7:$B$35) -> EC25 | B95: =LOOKUP(A95,'Auxiliar 1'!$B$7:$B$35,'Auxiliar 1'!$C$7:$C$35) -> Alquiler del Local | C95: =C79*$E95/$E79 -> 0 | D95: =D79*$E95/$E79 -> 82.5 | E95: =VLOOKUP(A95,'Proceso I'!$A$41:$O$69,5,0) -> 82.5
A96: =LOOKUP(A80,'Auxiliar 1'!$T$7:$T$35,'Auxiliar 1'!$B$7:$B$35) -> EC26 | B96: =LOOKUP(A96,'Auxiliar 1'!$B$7:$B$35,'Auxiliar 1'!$C$7:$C$35) -> Útiles de escritorio | C96: =C80*$E96/$E80 -> 0 | D96: =D80*$E96/$E80 -> 4.2857143 | E96: =VLOOKUP(A96,'Proceso I'!$A$41:$O$69,5,0) -> 4.2857143
B97: total | C97: =SUM(C86:C96) -> 832.85714 | D97: =SUM(D86:D96) -> 1075.9578 | E97: =SUM(E86:E96) -> 1908.8149
A99: CAE4 | B99: GERENCIA DE PRODUCCION
C101: CAE4
C102: AE7 | D102: AE8 | E102: TOTAL
A103: INDUCTOR | C103: =HLOOKUP(C102,'Centro de actividades'!$E$50:$AM$51,2,0) -> Analizar los indicadores de producción | D103: =HLOOKUP(D102,'Centro de actividades'!$E$50:$AM$51,2,0) -> Analizar volúmenes de producción y emitir órdenes de producción
A104: I01 | B104: =LOOKUP(A104,'Auxiliar 1'!$T$7:$T$35,'Auxiliar 1'!$U$7:$U$35) -> Horas diarias dedicadas por Groover a cada C.A. | C104: =$E104/2 -> 0.5 | D104: =$E104/2 -> 0.5 | E104: =VLOOKUP(A104,'Proceso I'!$A$6:$O$34,6,0) -> 1
A105: I06 | B105: =LOOKUP(A105,'Auxiliar 1'!$T$7:$T$35,'Auxiliar 1'!$U$7:$U$35) -> % de uso | C105: =$E105/2 -> 0.05 | D105: =$E105/2 -> 0.05 | E105: =VLOOKUP(A105,'Proceso I'!$A$6:$O$34,6,0) -> 0.1
A106: I10 | B106: =LOOKUP(A106,'Auxiliar 1'!$T$7:$T$35,'Auxiliar 1'!$U$7:$U$35) -> Proporción de Consumo de Kwh | C106: 5 | D106: 5 | E106: =VLOOKUP(A106,'Proceso I'!$A$6:$O$34,6,0) -> 10
A107: I11 | B107: =LOOKUP(A107,'Auxiliar 1'!$T$7:$T$35,'Auxiliar 1'!$U$7:$U$35) -> N° de personas en el C.A. | C107: =$E107/2 -> 0.5 | D107: =$E107/2 -> 0.5 | E107: =VLOOKUP(A107,'Proceso I'!$A$6:$O$34,6,0) -> 1
A108: I12 | B108: =LOOKUP(A108,'Auxiliar 1'!$T$7:$T$35,'Auxiliar 1'!$U$7:$U$35) -> N° de personas en el C.A. | D108: =E108 -> 1 | E108: =VLOOKUP(A108,'Proceso I'!$A$6:$O$34,6,0) -> 1
A109: I13 | B109: =LOOKUP(A109,'Auxiliar 1'!$T$7:$T$35,'Auxiliar 1'!$U$7:$U$35) -> Flat Parcial | C109: =E109 -> 1 | E109: =VLOOKUP(A109,'Proceso I'!$A$6:$O$34,6,0) -> 1
A110: I25 | B110: =LOOKUP(A110,'Auxiliar 1'!$T$7:$T$35,'Auxiliar 1'!$U$7:$U$35) -> % de Importancia | C110: 0.02 | D110: 0.03 | E110: =VLOOKUP(A110,'Proceso I'!$A$6:$O$34,6,0) -> 0.05
A111: I26 | B111: =LOOKUP(A111,'Auxiliar 1'!$T$7:$T$35,'Auxiliar 1'!$U$7:$U$35) -> Flat Parcial | C111: =$E111/2 -> 0.5 | D111: =$E111/2 -> 0.5 | E111: =VLOOKUP(A111,'Proceso I'!$A$6:$O$34,6,0) -> 1
C114: CAE4
C115: AE7 | D115: AE8 | E115: TOTAL
A116: ELEMENTO DE COSTO | C116: =HLOOKUP(C115,'Centro de actividades'!$E$50:$AM$51,2,0) -> Analizar los indicadores de producción | D116: =HLOOKUP(D115,'Centro de actividades'!$E$50:$AM$51,2,0) -> Analizar volúmenes de producción y emitir órdenes de producción
A117: =LOOKUP(A104,'Auxiliar 1'!$T$7:$T$35,'Auxiliar 1'!$B$7:$B$35) -> EC01 | B117: =LOOKUP(A117,'Auxiliar 1'!$B$7:$B$35,'Auxiliar 1'!$C$7:$C$35) -> Sueldo de Groover (Sin considerar CA Corte) | C117: =C104*$E117/$E104 -> 375 | D117: =D104*$E117/$E104 -> 375 | E117: =VLOOKUP(A117,'Proceso I'!$A$41:$O$69,6,0) -> 750
A118: =LOOKUP(A105,'Auxiliar 1'!$T$7:$T$35,'Auxiliar 1'!$B$7:$B$35) -> EC06 | B118: =LOOKUP(A118,'Auxiliar 1'!$B$7:$B$35,'Auxiliar 1'!$C$7:$C$35) -> Depreciación Computadora | C118: =C105*$E118/$E105 -> 14.0625 | D118: =D105*$E118/$E105 -> 14.0625 | E118: =VLOOKUP(A118,'Proceso I'!$A$41:$O$69,6,0) -> 28.125
A119: =LOOKUP(A106,'Auxiliar 1'!$T$7:$T$35,'Auxiliar 1'!$B$7:$B$35) -> EC10 | B119: =LOOKUP(A119,'Auxiliar 1'!$B$7:$B$35,'Auxiliar 1'!$C$7:$C$35) -> Energía Eléctrica | C119: =C106*$E119/$E106 -> 21.818182 | D119: =D106*$E119/$E106 -> 21.818182 | E119: =VLOOKUP(A119,'Proceso I'!$A$41:$O$69,6,0) -> 43.636364
...

Sheet Proceso III
A1: COSTO DE LAS ACTIVIDADES ESTRATÉGICAS A LOS CENTRO DE ACTIVIDAD DE APOYO Y OPERATIVO
A3: CAE1 | B3: GERENCIA GENERAL
C4: APOYO | G4: OPERATIVO | L4: total
A5: CAE1 | B5: INDUCTOR | C5: CAA1 | D5: CAA2 | E5: CAA3 | F5: CAA4 | G5: CAO1 | H5: CAO2 | I5: CAO3 | J5: CAO4 | K5: CAO5
A6: I01 | B6: nivel de actividad | C6: 1 | D6: 3 | F6: 3 | L6: =SUM(C6:K6) -> 7
A7: I02 | B7: % de asignacion | D7: 0.5 | F7: 0.5 | L7: =SUM(C7:K7) -> 1
A8: I03 | B8: flat total | C8: 1 | D8: 1 | E8: 1 | F8: 1 | G8: 1 | H8: 1 | I8: 1 | J8: 1 | K8: 1 | L8: =SUM(C8:K8) -> 9
C12: APOYO | G12: OPERATIVO | L12: TOTAL
A13: CAE1 | B13: ACTIVIDADES DE GERENCIA GENERAL | C13: CAA1 | D13: CAA2 | E13: CAA3 | F13: CAA4 | G13: CAO1 | H13: CAO2 | I13: CAO3 | J13: CAO4 | K13: CAO5
A14: AE1 | B14: Administrar cuentas bancarias | C14: =$L14/$L6*C6 -> 57.948632 | D14: =$L14/$L6*D6 -> 173.8459 | E14: =$L14/$L6*E6 -> 0 | F14: =$L14/$L6*F6 -> 173.8459 | G14: =$L14/$L6*G6 -> 0 | H14: =$L14/$L6*H6 -> 0 | I14: =$L14/$L6*I6 -> 0 | J14: =$L14/$L6*J6 -> 0 | K14: =$L14/$L6*K6 -> 0 | L14: 405.64042
A15: AE2 | B15: Aprobar las órdenes de compra | C15: =$L15/$L7*C7 -> 0 | D15: =$L15/$L7*D7 -> 289.39773 | E15: =$L15/$L7*E7 -> 0 | F15: =$L15/$L7*F7 -> 289.39773 | G15: =$L15/$L7*G7 -> 0 | H15: =$L15/$L7*H7 -> 0 | I15: =$L15/$L7*I7 -> 0 | J15: =$L15/$L7*J7 -> 0 | K15: =$L15/$L7*K7 -> 0 | L15: 578.79545
A16: AE3 | B16: Revisar informes mensuales | C16: =$L16/$L8*C8 -> 92.715097 | D16: =$L16/$L8*D8 -> 92.715097 | E16: =$L16/$L8*E8 -> 92.715097 | F16: =$L16/$L8*F8 -> 92.715097 | G16: =$L16/$L8*G8 -> 92.715097 | H16: =$L16/$L8*H8 -> 92.715097 | I16: =$L16/$L8*I8 -> 92.715097 | J16: =$L16/$L8*J8 -> 92.715097 | K16: =$L16/$L8*K8 -> 92.715097 | L16: 834.43588
B17: TOTAL | C17: =SUM(C16) -> 92.715097 | D17: =SUM(D16) -> 92.715097 | E17: =SUM(E16) -> 92.715097 | F17: =SUM(F16) -> 92.715097 | G17: =SUM(G16) -> 92.715097 | H17: =SUM(H16) -> 92.715097 | I17: =SUM(I16) -> 92.715097 | J17: =SUM(J16) -> 92.715097 | K17: =SUM(K16) -> 92.715097 | L17: =SUM(L14:L16) -> 1818.8718
A19: CAE2 | B19: GERENCIA DE VENTAS
C21: APOYO | G21: OPERATIVO | L21: TOTAL
A22: CAE2 | B22: INDUCTOR | C22: CAA1 | D22: CAA2 | E22: CAA3 | F22: CAA4 | G22: CAO1 | H22: CAO2 | I22: CAO3 | J22: CAO4 | K22: CAO5
A23: I04 | B23: # de horas dedicadas | D23: 5 | K23: 10 | L23: =SUM(C23:K23) -> 15
C26: APOYO | G26: OPERATIVO | L26: TOTAL
A27: CAE2 | B27: ACTIVIDADES DE GERENCIA DE VENTAS | C27: CAA1 | D27: CAA2 | E27: CAA3 | F27: CAA4 | G27: CAO1 | H27: CAO2 | I27: CAO3 | J27: CAO4 | K27: CAO5
A28: AE4 | B28: Realizar el control de ventas | C28: =$L28/$L23*C23 -> 0 | D28: =$L28/$L23*D23 -> 260.69058 | E28: =$L28/$L23*E23 -> 0 | F28: =$L28/$L23*F23 -> 0 | G28: =$L28/$L23*G23 -> 0 | H28: =$L28/$L23*H23 -> 0 | I28: =$L28/$L23*I23 -> 0 | J28: =$L28/$L23*J23 -> 0 | K28: =$L28/$L23*K23 -> 521.38117 | L28: 782.07175
B29: TOTAL | C29: =SUM(C28) -> 0 | D29: =SUM(D28) -> 260.69058 | E29: =SUM(E28) -> 0 | F29: =SUM(F28) -> 0 | G29: =SUM(G28) -> 0 | H29: =SUM(H28) -> 0 | I29: =SUM(I28) -> 0 | J29: =SUM(J28) -> 0 | K29: =SUM(K28) -> 521.38117
A31: CAE3 | B31: GERENCIA DE MARKETING
C33: APOYO | G33: OPERATIVO | L33: TOTAL
A34: CAE3 | B34: INDUCTOR | C34: CAA1 | D34: CAA2 | E34: CAA3 | F34: CAA4 | G34: CAO1 | H34: CAO2 | I34: CAO3 | J34: CAO4 | K34: CAO5
A35: I05 | B35: % de asignacion | K35: 1 | L35: 1
A36: I06 | B36: % de asignacion | K36: 1 | L36: 1
C39: APOYO | G39: OPERATIVO | L39: TOTAL
A40: CAE3 | B40: ACTIVIDADES DE GERENCIA DE MARKETING | C40: CAA1 | D40: CAA2 | E40: CAA3 | F40: CAA4 | G40: CAO1 | H40: CAO2 | I40: CAO3 | J40: CAO4 | K40: CAO5
A41: AE5 | B41: Realizar visitas a colegios, universidades y otras instituciones | C41: =$L41/$L35*C35 -> 0 | D41: =$L41/$L35*D35 -> 0 | E41: =$L41/$L35*E35 -> 0 | F41: =$L41/$L35*F35 -> 0 | G41: =$L41/$L35*G35 -> 0 | H41: =$L41/$L35*H35 -> 0 | I41: =$L41/$L35*I35 -> 0 | J41: =$L41/$L35*J35 -> 0 | K41: =$L41/$L35*K35 -> 832.85714 | L41: 832.85714
A42: AE6 | B42: Realizar publicaciones en redes sociales | C42: =$L42/$L36*C36 -> 0 | D42: =$L42/$L36*D36 -> 0 | E42: =$L42/$L36*E36 -> 0 | F42: =$L42/$L36*F36 -> 0 | G42: =$L42/$L36*G36 -> 0 | H42: =$L42/$L36*H36 -> 0 | I42: =$L42/$L36*I36 -> 0 | J42: =$L42/$L36*J36 -> 0 | K42: =$L42/$L36*K36 -> 1075.9578 | L42: 1075.9578
B43: TOTAL | C43: =SUM(C41:C42) -> 0 | D43: =SUM(D41:D42) -> 0 | E43: =SUM(E41:E42) -> 0 | F43: =SUM(F41:F42) -> 0 | G43: =SUM(G41:G42) -> 0 | H43: =SUM(H41:H42) -> 0 | I43: =SUM(I41:I42) -> 0 | J43: =SUM(J41:J42) -> 0 | ... L43: =SUM(L41:L42) -> 1908.8149
A45: CAE4 | B45: GERENCIA DE PRODUCCION
C47: APOYO | G47: OPERATIVO
A48: CAE4 | B48: INDUCTOR | C48: CAA1 | D48: CAA2 | E48: CAA3 | F48: CAA4 | G48: CAO1 | H48: CAO2 | I48: CAO3 | J48: CAO4 | K48: CAO5
A49: I07 | B49: % de dedicacion | E49: 0.4 | G49: 0.15 | H49: 0.15 | I49: 0.15 | J49: 0.15 | L49: 1
A50: I08 | B50: % porcentaje de dedicacion | G50: 0.25 | H50: 0.25 | I50: 0.25 | J50: 0.25 | L50: 1
C53: APOYO | G53: OPERATIVO | L53: TOTAL
A54: CAE4 | B54: ACTIVIDADES DE GERENCIA DE PRODUCCIÓN | C54: CAA1 | D54: CAA2 | E54: CAA3 | F54: CAA4 | G54: CAO1 | H54: CAO2 | I54: CAO3 | J54: CAO4 | K54: CAO5
A55: AE7 | B55: Analizar los indicadores de producción | C55: =$L55/$L49*C49 -> 0 | D55: =$L55/$L49*D49 -> 0 | E55: =$L55/$L49*E49 -> 210.55227 | F55: =$L55/$L49*F49 -> 0 | G55: =$L55/$L49*G49 -> 78.957102 | H55: =$L55/$L49*H49 -> 78.957102 | I55: =$L55/$L49*I49 -> 78.957102 | J55: =$L55/$L49*J49 -> 78.957102 | K55: =$L55/$L49*K49 -> 0 | L55: 526.38068
A56: AE8 | B56: Analizar volúmenes de producción y emitir órdenes de producción | C56: =$L56/$L50*C50 -> 0 | D56: =$L56/$L50*D50 -> 0 | E56: =$L56/$L50*E50 -> 0 | F56: =$L56/$L50*F50 -> 0 | G56: =$L56/$L50*G50 -> 141.07731 | H56: =$L56/$L50*H50 -> 141.07731 | I56: =$L56/$L50*I50 -> 141.07731 | J56: =$L56/$L50*J50 -> 141.07731 | K56: =$L56/$L50*K50 -> 0 | L56: 564.30925
B57: TOTAL | C57: =SUM(C55:C56) -> 0 | D57: =SUM(D55:D56) -> 0 | E57: =SUM(E55:E56) -> 210.55227 | F57: =SUM(F55:F56) -> 0 | G57: =SUM(G55:G56) -> 220.03442 | H57: =SUM(H55:H56) -> 220.03442 | I57: =SUM(I55:I56) -> 220.03442 | J57: =SUM(J55:J56) -> 220.03442 | ... L57: =SUM(L55:L56) -> 1090.6899
B59: CENTRO DE ACTIVIDADES DE APOYO
A61: CAA1 | B61: ACTIVIDADES DE ÁREA ADMINISTRACIÓN | C61: IMPORTANCIA (%) | D61: COSTO
A62: AA1 | B62: Realizar el pago de planilla | C62: 0.3 | D62: =D$64/C$64*C62 -> 27.814529
A63: AA2 | B63: Controlar asistencia de trabajadores | C63: 0.7 | D63: =D$64/C$64*C63 -> 64.900568
B64: TOTAL | C64: =SUM(C62:C63) -> 1 | D64: =C17+C29+C43+C57 -> 92.715097
A67: CAA2 | B67: ACTIVIDADES DE ÁREA DE TESORERÍA Y CONTABILIDAD | C67: IMPORTANCIA (%) | D67: COSTO
A68: AA3 | B68: Realizar estados financieros | C68: 0.3 | D68: =D$71/C$71*C68 -> 106.0217
A69: AA4 | B69: Realizar los pagos a los proveedores | C69: 0.3 | D69: =D$71/C$71*C69 -> 106.0217
A70: AA5 | B70: Realizar el costeo | C70: 0.4 | D70: =D$71/C$71*C70 -> 141.36227
B71: TOTAL | C71: =SUM(C68:C70) -> 1 | D71: =D57+D43+D29+D17 -> 353.40568
A74: CAA3 | B74: ACTIVIDADES DE ÁREA DE CALIDAD | C74: IMPORTANCIA (%) | D74: COSTO
A75: AA6 | B75: Revisar medidas del molde | C75: 0.25 | D75: =D$79/C$79*C75 -> 75.816843
A76: AA7 | B76: Revisar los bordados de cada prenda (si es que lo lleva) | C76: 0.25 | D76: =D$79/C$79*C76 -> 75.816843
A77: AA8 | B77: Revisar los estampados de cada prenda (si es que lo lleva) | C77: 0.25 | D77: =D$79/C$79*C77 -> 75.816843
A78: AA9 | B78: Revisar confección y uniones | C78: 0.25 | D78: =D$79/C$79*C78 -> 75.816843
B79: TOTAL | C79: =SUM(C75:C78) -> 1 | D79: =E57+E43+E29+E17 -> 303.26737
A82: CAA4 | B82: ACTIVIDADES DE ÁREA LOGÍSTICA | C82: IMPORTANCIA (%) | D82: COSTO
A83: AA10 | B83: Realizar la compra de materiales | C83: =1/3 -> 0.33333333 | D83: =D$86/C$86*C83 -> 30.905032
A84: AA11 | B84: Trasladar los materiales hacia la planta de producción | C84: =1/3 -> 0.33333333 | D84: =D$86/C$86*C84 -> 30.905032
A85: AA12 | B85: Realizar el traslado del producto en proceso al servicio directo | C85: =1/3 -> 0.33333333 | D85: =D$86/C$86*C85 -> 30.905032
B86: TOTAL | C86: =SUM(C83:C85) -> 1 | D86: =F57+F43+F29+F17 -> 92.715097
B88: CENTRO DE ACTIVIDADES OPERATIVAS
A90: CAO1 | B90: ACTIVIDADES DE ÁREA DE DISEÑO | C90: IMPORTANCIA | D90: COSTO
A91: AO1 | B91: Digitalizar firmas y símbolos | C91: 0.35 | D91: =D$94/C$94*C91 -> 109.46233
A92: AO2 | B92: Unir firmas e imprimir | C92: 0.15 | D92: =D$94/C$94*C92 -> 46.912427
A93: AO3 | B93: Diseñar en CorelDraw símbolos pedidos | C93: 0.5 | D93: =D$94/C$94*C93 -> 156.37476
B94: TOTAL | C94: =SUM(C91:C93) -> 1 | D94: =G17+G29+G43+G57 -> 312.74951
A97: CAO2 | B97: ACTIVIDADES DE ÁREA DE CORTE | C97: IMPORTANCIA | D97: COSTO
A98: AO4 | B98: Tender las telas sobre mesa de corte | C98: 0.1 | D98: =D$103/C$103*C98 -> 31.274951
A99: AO5 | B99: Marcar la tela superficial con tiza de sastre | C99: 0.35 | D99: =D$103/C$103*C99 -> 109.46233
A100: AO6 | B100: Cortar con la máquina cada conjunto de telas | C100: 0.35 | D100: =D$103/C$103*C100 -> 109.46233
A101: AO7 | B101: Etiquetar por prenda, talla y cliente con etiqueta de seguimiento | C101: 0.1 | D101: =D$103/C$103*C101 -> 31.274951
A102: AO8 | B102: Embolsar para envío a Bordado y/o Estampado (externo) | C102: 0.1 | D102: =D$103/C$103*C102 -> 31.274951
B103: TOTAL | C103: =SUM(C98:C102) -> 1 | D103: =H17+H29+H43+H57 -> 312.74951
A106: CAO3 | B106: ACTIVIDADES DE ÁREA DE ACABADO | C106: IMPORTANCIA | D106: COSTO
A107: AO9 | B107: Limpiar con el piqueteador cada prenda | C107: 1 | D107: =I57+I43+I29+I17 -> 312.74951
B108: TOTAL | C108: =C107 -> 1 | D108: =D107 -> 312.74951
A111: CAO4 | B111: ACTIVIDADES DE ÁREA DE EMPAQUETADO Y ROTULADO | C111: IMPORTANCIA | D111: COSTO
A112: AO10 | B112: Desetiquetar cada parte de las prendas | C112: 0.3 | D112: =D$116/C$116*C112 -> 93.824854
A113: AO11 | B113: Doblar la prenda | C113: 0.2 | D113: =D$116/C$116*C113 -> 62.549903
A114: AO12 | B114: Etiquetar con nombre del cliente cada prenda | C114: 0.3 | D114: =D$116/C$116*C114 -> 93.824854
A115: AO13 | B115: Embolsar para envío final | C115: 0.2 | D115: =D$116/C$116*C115 -> 62.549903
B116: TOTAL | C116: =SUM(C112:C115) -> 1 | D116: =J17+J29+J43+J57 -> 312.74951
A119: CAA5 | B119: ACTIVIDADES DE ÁREA DE PRE Y POST VENTA | C119: IMPORTANCIA | D119: COSTO
A120: AO14 | B120: Realizar el contrato | C120: 0.5 | D120: =D$122/C$122*C120 -> 1261.4556
A121: AO15 | B121: Entregar el pedido | C121: 0.5 | D121: =D$122/C$122*C121 -> 1261.4556
B122: TOTAL | C122: =SUM(C120:C121) -> 1 | D122: =K17+K29+K43+K57 -> 2522.9112

Sheet Proceso IV
A1: COSTO DE LA ACTIVIDADES DE APOYO A LOS CENTROS DE ACTIVIDAD OPERATIVOS
B3: CENTROS DE ACTIVIDAD DE APOYO
A4: CAA1 | B4: AREA ADMINISTRATIVA
C6: OPERATIVO | H6: TOTAL
A7: CAA1 | B7: INDUCTORES | C7: CAO1 | D7: CAO2 | E7: CAO3 | F7: CAO4 | G7: CAO5
A8: I01 | B8: # De Trabajadores | C8: 1 | D8: 1 | E8: 1 | F8: 1 | G8: 1 | H8: =SUM(C8:G8) -> 5
A9: I02 | B9: # De Trabajadores | C9: 1 | D9: 1 | E9: 1 | F9: 1 | G9: 1 | H9: =SUM(C9:G9) -> 5
C12: OPERATIVO | H12: PROCESO II | I12: PROCESO III | J12: TOTAL
A13: CAA1 | B13: ACTIVIDADES DE ÁREA ADMINISTRACIÓN | C13: CAO1 | D13: CAO2 | E13: CAO3 | F13: CAO4 | G13: CAO5
A14: AA1 | B14: Realizar el pago de planilla | C14: =C8*$J14/$H8 -> 28.37849 | D14: =D8*$J14/$H8 -> 28.37849 | E14: =E8*$J14/$H8 -> 28.37849 | F14: =F8*$J14/$H8 -> 28.37849 | G14: =G8*$J14/$H8 -> 28.37849 | H14: ='Proceso II'!C152 -> 114.07792 | I14: ='Proceso III'!D62 -> 27.814529 | J14: =SUM(H14:I14) -> 141.89245
A15: AA2 | B15: Controlar asistencia de trabajadores | C15: =C9*$J15/$H9 -> 191.15966 | D15: =D9*$J15/$H9 -> 191.15966 | E15: =E9*$J15/$H9 -> 191.15966 | F15: =F9*$J15/$H9 -> 191.15966 | G15: =G9*$J15/$H9 -> 191.15966 | H15: ='Proceso II'!D152 -> 890.89773 | I15: ='Proceso III'!D63 -> 64.900568 | J15: =SUM(H15:I15) -> 955.7983
B16: TOTAL | C16: =SUM(C14:C15) -> 219.53815 | D16: =SUM(D14:D15) -> 219.53815 | E16: =SUM(E14:E15) -> 219.53815 | F16: =SUM(F14:F15) -> 219.53815 | G16: =SUM(G14:G15) -> 219.53815 | H16: =SUM(H14:H15) -> 1004.9756 | I16: =SUM(I14:I15) -> 92.715097 | J16: =SUM(J14:J15) -> 1097.6907
A18: CAA2 | B18: TESORERIA Y CONTABILIDAD
C20: OPERATIVO | H20: TOTAL
A21: CAA2 | B21: INDUCTORES | C21: CAO1 | D21: CAO2 | E21: CAO3 | F21: CAO4 | G21: CAO5
A22: I03 | B22: % de asignacion | C22: 0.1 | D22: 0.2 | E22: 0.15 | F22: 0.15 | G22: 0.4 | H22: =SUM(C22:G22) -> 1
A23: I04 | B23: flat total | C23: 1 | D23: 1 | E23: 1 | F23: 1 | G23: 1 | H23: =SUM(C23:G23) -> 5
A24: I05 | B24: flat total | C24: 1 | D24: 1 | E24: 1 | F24: 1 | G24: 1 | H24: =SUM(C24:G24) -> 5
C26: OPERATIVO | H26: PROCESO II | I26: PROCESO III | J26: TOTAL
A27: CAA2 | B27: ACTIVIDADES DE ÁREA DE TESORERÍA Y CONTABILIDAD | C27: CAO1 | D27: CAO2 | E27: CAO3 | F27: CAO4 | G27: CAO5
A28: AA3 | B28: Realizar estados financieros | C28: =C22*$J28/$H22 -> 21.211748 | D28: =D22*$J28/$H22 -> 42.423497 | E28: =E22*$J28/$H22 -> 31.817623 | F28: =F22*$J28/$H22 -> 31.817623 | G28: =G22*$J28/$H22 -> 84.846994 | H28: ='Proceso II'!C179 -> 106.09578 | I28: ='Proceso III'!D68 -> 106.0217 | J28: =SUM(H28:I28) -> 212.11748
A29: AA4 | B29: Realizar los pagos a los proveedores | C29: =C23*$J29/$H23 -> 90.422523 | D29: =D23*$J29/$H23 -> 90.422523 | E29: =E23*$J29/$H23 -> 90.422523 | F29: =F23*$J29/$H23 -> 90.422523 | G29: =G23*$J29/$H23 -> 90.422523 | H29: ='Proceso II'!D179 -> 346.09091 | I29: ='Proceso III'!D69 -> 106.0217 | J29: =SUM(H29:I29) -> 452.11261
A30: AA5 | B30: Realizar el costeo | C30: =C24*$J30/$H24 -> 138.83025 | D30: =D24*$J30/$H24 -> 138.83025 | E30: =E24*$J30/$H24 -> 138.83025 | F30: =F24*$J30/$H24 -> 138.83025 | G30: =G24*$J30/$H24 -> 138.83025 | H30: ='Proceso II'!E179 -> 552.78896 | I30: ='Proceso III'!D70 -> 141.36227 | J30: =SUM(H30:I30) -> 694.15123
B31: TOTAL | C31: =SUM(C28:C30) -> 250.46452 | D31: =SUM(D28:D30) -> 271.67627 | E31: =SUM(E28:E30) -> 261.07039 | F31: =SUM(F28:F30) -> 261.07039 | G31: =SUM(G28:G30) -> 314.09976 | H31: =SUM(H28:H30) -> 1004.9756 | I31: =SUM(I28:I30) -> 353.40568 | J31: =SUM(H31:I31) -> 1358.3813
A33: CAA3 | B33: CALIDAD
C35: OPERATIVO | H35: TOTAL
A36: CAA3 | B36: INDUCTORES | C36: CAO1 | D36: CAO2 | E36: CAO3 | F36: CAO4 | G36: CAO5
A37: I06 | B37: % de uso | D37: 1 | H37: =SUM(C37:G37) -> 1
A38: I07 | B38: % de asignacion | E38: 0.4 | F38: 0.3 | G38: 0.3 | H38: =SUM(C38:G38) -> 1
A39: I08 | B39: % de asignacion | E39: 0.4 | F39: 0.3 | G39: 0.3 | H39: =SUM(C39:G39) -> 1
A40: I09 | B40: % de asignacion | E40: 0.5 | F40: 0.2 | G40: 0.3 | H40: =SUM(C40:G40) -> 1
C43: OPERATIVO | H43: PROCESO II | I43: PROCESO III | J43: TOTAL
A44: CAA3 | B44: ACTIVIDADES DE ÁREA DE CALIDAD | C44: CAO1 | D44: CAO2 | E44: CAO3 | F44: CAO4 | G44: CAO5
A45: AA6 | B45: Revisar medidas del molde | C45: =C37*$J45/$H37 -> 0 | D45: =D37*$J45/$H37 -> 946.21619 | E45: =E37*$J45/$H37 -> 0 | F45: =F37*$J45/$H37 -> 0 | G45: =G37*$J45/$H37 -> 0 | H45: ='Proceso II'!C200 -> 870.39935 | I45: ='Proceso III'!D75 -> 75.816843 | J45: =SUM(H45:I45) -> 946.21619
A46: AA7 | B46: Revisar los bordados de cada prenda (si es que lo lleva) | C46: =C38*$J46/$H38 -> 0 | D46: =D38*$J46/$H38 -> 0 | E46: =E38*$J46/$H38 -> 385.08648 | F46: =F38*$J46/$H38 -> 288.81486 | G46: =G38*$J46/$H38 -> 288.81486 | H46: ='Proceso II'!D200 -> 886.89935 | I46: ='Proceso III'!D76 -> 75.816843 | J46: =SUM(H46:I46) -> 962.71619
A47: AA8 | B47: Revisar los estampados de cada prenda (si es que lo lleva) | C47: =C39*$J47/$H39 -> 0 | D47: =D39*$J47/$H39 -> 0 | E47: =E39*$J47/$H39 -> 378.48648 | F47: =F39*$J47/$H39 -> 283.86486 | G47: =G39*$J47/$H39 -> 283.86486 | H47: ='Proceso II'!E200 -> 870.39935 | I47: ='Proceso III'!D77 -> 75.816843 | J47: =SUM(H47:I47) -> 946.21619
A48: AA9 | B48: Revisar confección y uniones | C48: =C40*$J48/$H40 -> 0 | D48: =D40*$J48/$H40 -> 0 | E48: =E40*$J48/$H40 -> 483.53991 | F48: =F40*$J48/$H40 -> 193.41597 | G48: =G40*$J48/$H40 -> 290.12395 | H48: ='Proceso II'!F200 -> 891.26299 | I48: ='Proceso III'!D78 -> 75.816843 | J48: =SUM(H48:I48) -> 967.07983
B49: TOTAL | C49: =SUM(C45:C48) -> 0 | D49: =SUM(D45:D48) -> 946.21619 | E49: =SUM(E45:E48) -> 1247.1129 | F49: =SUM(F45:F48) -> 766.09568 | G49: =SUM(G45:G48) -> 862.80366 | H49: =SUM(H45:H48) -> 3518.961 | I49: =SUM(I45:I48) -> 303.26737 | J49: =SUM(J45:J48) -> 3822.2284
A51: CAA4 | B51: LOGISTICA
C53: OPERATIVO | H53: TOTAL
A54: CAA4 | B54: INDUCTORES | C54: CAO1 | D54: CAO2 | E54: CAO3 | F54: CAO4 | G54: CAO5
A55: I10 | B55: % de asignacion | C55: 0.05 | D55: 0.5 | E55: 0.2 | F55: 0.25 | H55: =SUM(C55:G55) -> 1
A56: I11 | B56: % de asignacion | C56: 0.05 | D56: 0.5 | E56: 0.2 | F56: 0.25 | H56: =SUM(C56:G56) -> 1
A57: I12 | B57: % de asignacion | E57: 0.5 | F57: 0.2 | G57: 0.3 | H57: =SUM(C57:G57) -> 1
C60: OPERATIVO | H60: PROCESO II | I60: PROCESO III | J60: TOTAL
A61: CAA4 | B61: ACTIVIDADES DE ÁREA LOGÍSTICA | C61: CAO1 | D61: CAO2 | E61: CAO3 | F61: CAO4 | G61: CAO5
A62: AA10 | B62: Realizar la compra de materiales | C62: =C55*$J62/$H55 -> 48.262784 | D62: =D55*$J62/$H55 -> 482.62784 | E62: =E55*$J62/$H55 -> 193.05114 | F62: =F55*$J62/$H55 -> 241.31392 | G62: =G55*$J62/$H55 -> 0 | H62: ='Proceso II'!C229 -> 934.35065 | I62: ='Proceso III'!D83 -> 30.905032 | J62: =SUM(H62:I62) -> 965.25568
A63: AA11 | B63: Trasladar los materiales hacia la planta de producción | C63: =C56*$J63/$H56 -> 30.170252 | D63: =D56*$J63/$H56 -> 301.70252 | E63: =E56*$J63/$H56 -> 120.68101 | F63: =F56*$J63/$H56 -> 150.85126 | G63: =G56*$J63/$H56 -> 0 | H63: ='Proceso II'!D229 -> 572.5 | I63: ='Proceso III'!D84 -> 30.905032 | J63: =SUM(H63:I63) -> 603.40503
A64: AA12 | B64: Realizar el traslado del producto en proceso al servicio directo | C64: =C57*$J64/$H57 -> 0 | D64: =D57*$J64/$H57 -> 0 | E64: =E57*$J64/$H57 -> 667.95252 | F64: =F57*$J64/$H57 -> 267.18101 | G64: =G57*$J64/$H57 -> 400.77151 | H64: ='Proceso II'!E229 -> 1305 | I64: ='Proceso III'!D85 -> 30.905032 | J64: =SUM(H64:I64) -> 1335.905
B65: TOTAL | C65: =SUM(C62:C64) -> 78.433036 | D65: =SUM(D62:D64) -> 784.33036 | E65: =SUM(E62:E64) -> 981.68466 | F65: =SUM(F62:F64) -> 659.34619 | G65: =SUM(G62:G64) -> 400.77151 | H65: =SUM(H62:H64) -> 2811.8506 | I65: =SUM(I62:I64) -> 92.715097 | J65: =SUM(J62:J64) -> 2904.5657
A69: CAO1 | B69: DISEÑO
A71: CAO1 | B71: ACTIVIDADES DE ÁREA DE DISEÑO | C71: IMPORTANCIA | D71: COSTO
A72: AO1 | B72: Digitalizar firmas y símbolos | C72: 0.35 | D72: =D$75/C$75*C72 -> 191.9525
A73: AO2 | B73: Unir firmas e imprimir | C73: 0.15 | D73: =D$75/C$75*C73 -> 82.265355
A74: AO3 | B74: Diseñar en CorelDraw símbolos pedidos | C74: 0.5 | D74: =D$75/C$75*C74 -> 274.21785
B75: TOTAL | C75: =SUM(C72:C74) -> 1 | D75: =C65+C49+C31+C16 -> 548.4357
A78: CAO2 | B78: ACTIVIDADES DE ÁREA DE CORTE | C78: IMPORTANCIA | D78: COSTO
A79: AO4 | B79: Tender las telas sobre mesa de corte | C79: 0.1 | D79: =D$84/C$84*C79 -> 222.1761
A80: AO5 | B80: Marcar la tela superficial con tiza de sastre | C80: 0.35 | D80: =D$103/C$103*C80 -> 629.02458
A81: AO6 | B81: Cortar con la máquina cada conjunto de telas | C81: 0.35 | D81: =D$103/C$103*C81 -> 629.02458
A82: AO7 | B82: Etiquetar por prenda, talla y cliente con etiqueta de seguimiento | C82: 0.1 | D82: =D$103/C$103*C82 -> 179.72131
A83: AO8 | B83: Embolsar para envío a Bordado y/o Estampado (externo) | C83: 0.1 | D83: =D$103/C$103*C83 -> 179.72131
B84: TOTAL | C84: =SUM(C79:C83) -> 1 | D84: =D65+D49+D31+D16 -> 2221.761
A87: CAO3 | B87: ACTIVIDADES DE ÁREA DE ACABADO | C87: IMPORTANCIA | D87: COSTO
A88: AO9 | B88: Limpiar con el piqueteador cada prenda | C88: 1 | D88: =D89 -> 2709.4061
B89: TOTAL | C89: =C88 -> 1 | D89: =E65+E49+E31+E16 -> 2709.4061
A92: CAO4 | B92: ACTIVIDADES DE ÁREA DE EMPAQUETADO Y ROTULADO | C92: IMPORTANCIA | D92: COSTO
A93: AO10 | B93: Desetiquetar cada parte de las prendas | C93: 0.3 | D93: =D$97/C$97*C93 -> 571.81512
A94: AO11 | B94: Doblar la prenda | C94: 0.2 | D94: =D$97/C$97*C94 -> 381.21008
A95: AO12 | B95: Etiquetar con nombre del cliente cada prenda | C95: 0.3 | D95: =D$97/C$97*C95 -> 571.81512
A96: AO13 | B96: Embolsar para envío final | C96: 0.2 | D96: =D$97/C$97*C96 -> 381.21008
B97: TOTAL | C97: =SUM(C93:C96) -> 1 | D97: =F65+F49+F31+F16 -> 1906.0504
A100: CAA5 | B100: ACTIVIDADES DE ÁREA DE PRE Y POST VENTA | C100: IMPORTANCIA | D100: COSTO
A101: AO14 | B101: Realizar el contrato | C101: 0.5 | D101: =D$103/C$103*C101 -> 898.60654
A102: AO15 | B102: Entregar el pedido | C102: 0.5 | D102: =D$103/C$103*C102 -> 898.60654
B103: TOTAL | C103: =SUM(C101:C102) -> 1 | D103: =G65+G49+G31+G16 -> 1797.2131

Sheet Proceso V
A1: COSTO DE LAS ACTIVIDADES OPERATIVAS A LOS OBJETOS DE COSTO
D4: OT 1 | E4: OT2 | F4: OT3 | G4: OT4 | H4: OT 5 | I4: OT 6 | J4: OT 7 | K4: OT 8 | L4: OT 9 | M4: OT 10 | N4: OT 11 | O4: OT 12 | P4: OT 13 | Q4: OT 14 | R4: OT 15 | S4: OT 16
B5: INDUCTORES | T5: TOTAL
A6: CAO1 | B6: I01 | C6: # de firmas por pedido | D6: 21 | E6: 27 | F6: 27 | G6: 54 | H6: 21 | I6: 24 | J6: 26 | K6: 28 | L6: 17 | M6: 14 | N6: 34 | O6: 22 | P6: 23 | Q6: 29 | R6: 51 | S6: 27 | T6: =SUM(D6:S6) -> 445
B7: I02 | C7: # de firmas por pedido | D7: =D6 -> 21 | E7: =E6 -> 27 | F7: =F6 -> 27 | G7: =G6 -> 54 | H7: =H6 -> 21 | I7: =I6 -> 24 | J7: =J6 -> 26 | K7: =K6 -> 28 | ... S7: =S6 -> 27 | T7: =SUM(D7:S7) -> 445
B8: I03 | C8: # diseños por prenda | D8: 1 | E8: 1 | F8: 1 | G8: 1 | H8: 1 | I8: 1 | J8: 1 | K8: 1 | L8: 1 | M8: 1 | N8: 1 | O8: 1 | P8: 1 | Q8: 1 | R8: 1 | S8: 1 | T8: =SUM(D8:S8) -> 16
A9: CAO2 | B9: I04 | C9: # de prendas por pedido | D9: =D7 -> 21 | E9: =E7 -> 27 | F9: =F7 -> 27 | G9: =G7 -> 54 | H9: =H7 -> 21 | I9: =I7 -> 24 | J9: =J7 -> 26 | K9: =K7 -> 28 | ... S9: =S7 -> 27 | T9: =SUM(D9:S9) -> 445
B10: I05 | C10: flat total | D10: 1 | E10: 1 | F10: 1 | G10: 1 | H10: 1 | I10: 1 | J10: 1 | K10: 1 | L10: 1 | M10: 1 | N10: 1 | O10: 1 | P10: 1 | Q10: 1 | R10: 1 | S10: 1 | T10: =SUM(D10:S10) -> 16
B11: I06 | C11: flat total | D11: =D10 -> 1 | E11: =E10 -> 1 | F11: =F10 -> 1 | G11: =G10 -> 1 | H11: =H10 -> 1 | I11: =I10 -> 1 | J11: =J10 -> 1 | K11: =K10 -> 1 | ... S11: =S10 -> 1 | T11: =SUM(D11:S11) -> 16
B12: I07 | C12: # de partes por prenda | D12: 5 | E12: 5 | F12: 4 | G12: 5 | H12: 5 | I12: 5 | J12: 4 | K12: 5 | L12: 5 | M12: 5 | N12: 4 | O12: 5 | P12: 5 | Q12: 5 | R12: 5 | S12: 5 | T12: =SUM(D12:S12) -> 77
B13: I08 | C13: # prendras por pedido | D13: =D9 -> 21 | E13: =E9 -> 27 | F13: =F9 -> 27 | G13: =G9 -> 54 | H13: =H9 -> 21 | I13: =I9 -> 24 | J13: =J9 -> 26 | K13: =K9 -> 28 | ... S13: =S9 -> 27 | T13: =SUM(D13:S13) -> 445
A14: CA03 | B14: I09 | C14: # prendras por pedido | D14: =D13 -> 21 | E14: =E13 -> 27 | F14: =F13 -> 27 | G14: =G13 -> 54 | H14: =H13 -> 21 | I14: =I13 -> 24 | J14: =J13 -> 26 | K14: =K13 -> 28 | ... S14: =S13 -> 27 | T14: =SUM(D14:S14) -> 445
A15: CAO4 | B15: I10 | C15: # de partes por prenda | D15: 5 | E15: 5 | F15: 4 | G15: 5 | H15: 5 | I15: 5 | J15: 4 | K15: 5 | L15: 5 | M15: 5 | N15: 4 | O15: 5 | P15: 5 | Q15: 5 | R15: 5 | S15: 5 | T15: =SUM(D15:S15) -> 77
B16: I11 | C16: # prendras por pedido x dificultad | D16: 42 | E16: 54 | F16: 27 | G16: 108 | H16: 42 | I16: 48 | J16: 26 | K16: 56 | L16: 24 | M16: 28 | N16: 34 | O16: 22 | P16: 23 | Q16: 29 | R16: 51 | S16: 27 | T16: =SUM(D16:S16) -> 641
B17: I12 | C17: # de prendas por pedido | D17: 21 | E17: 27 | F17: 27 | G17: 54 | H17: 21 | I17: 24 | J17: 26 | K17: 28 | L17: 17 | M17: 14 | N17: 34 | O17: 22 | P17: 23 | Q17: 29 | R17: 51 | S17: 27 | T17: =SUM(D17:S17) -> 445
B18: I13 | C18: # de bolsas a utilizar por pedido | D18: =ROUNDUP(D17/15,0) -> 2 | E18: =ROUNDUP(E17/15,0) -> 2 | F18: =ROUNDUP(F17/15,0) -> 2 | G18: =ROUNDUP(G17/15,0) -> 4 | H18: =ROUNDUP(H17/15,0) -> 2 | I18: =ROUNDUP(I17/15,0) -> 2 | J18: =ROUNDUP(J17/15,0) -> 2 | K18: =ROUNDUP(K17/15,0) -> 2 | ... S18: =ROUNDUP(S17/15,0) -> 2 | T18: =SUM(D18:S18) -> 36
A19: CAO5 | B19: I14 | C19: flat total | D19: 1 | E19: 1 | F19: 1 | G19: 1 | H19: 1 | I19: 1 | J19: 1 | K19: 1 | L19: 1 | M19: 1 | N19: 1 | O19: 1 | P19: 1 | Q19: 1 | R19: 1 | S19: 1 | T19: =SUM(D19:S19) -> 16
B20: I15 | C20: relacion de distancia | D20: 6 | E20: 3 | F20: 3 | G20: 6 | H20: 4 | I20: 6 | J20: 6 | K20: 6 | L20: 4 | M20: 4 | N20: 4 | O20: 6 | P20: 3 | Q20: 5 | R20: 3 | S20: 7 | T20: =SUM(D20:S20) -> 76
D24: OT 1 | E24: OT2 | F24: OT3 | G24: OT4 | H24: OT 5 | I24: OT 6 | J24: OT 7 | K24: OT 8 | L24: OT 9 | M24: OT 10 | N24: OT 11 | O24: OT 12 | P24: OT 13 | Q24: OT 14 | R24: OT 15 | S24: OT 16
B25: CENTRO DE ACTIVIDADES OPERATIVAS | T25: PROCESO II | U25: PROCESO III | V25: PROCESO IV | W25: TOTAL
A26: CAO1 | B26: AO1 | C26: Digitalizar firmas y símbolos | D26: =D6*$W26/$T6 -> 19.712611 | E26: =E6*$W26/$T6 -> 25.344786 | F26: =F6*$W26/$T6 -> 25.344786 | G26: =G6*$W26/$T6 -> 50.689571 | H26: =H6*$W26/$T6 -> 19.712611 | I26: =I6*$W26/$T6 -> 22.528698 | J26: =J6*$W26/$T6 -> 24.40609 | K26: =K6*$W26/$T6 -> 26.283481 | ... S26: =S6*$W26/$T6 -> 25.344786 | T26: ='Proceso II'!C255 -> 116.30479 | U26: ='Proceso III'!D91 -> 109.46233 | V26: ='Proceso IV'!D72 -> 191.9525 | W26: =SUM(T26:V26) -> 417.71961
B27: AO2 | C27: Unir firmas e imprimir | D27: =D7*$W27/$T7 -> 11.786818 | E27: =E7*$W27/$T7 -> 15.15448 | F27: =F7*$W27/$T7 -> 15.15448 | G27: =G7*$W27/$T7 -> 30.308961 | H27: =H7*$W27/$T7 -> 11.786818 | I27: =I7*$W27/$T7 -> 13.470649 | J27: =J7*$W27/$T7 -> 14.593203 | K27: =K7*$W27/$T7 -> 15.715757 | ... S27: =S7*$W27/$T7 -> 15.15448 | T27: ='Proceso II'!D255 -> 120.5905 | U27: ='Proceso III'!D92 -> 46.912427 | V27: ='Proceso IV'!D73 -> 82.265355 | W27: =SUM(T27:V27) -> 249.76829
B28: AO3 | C28: Diseñar en CorelDraw símbolos pedidos | D28: =D8*$W28/$T8 -> 45.472458 | E28: =E8*$W28/$T8 -> 45.472458 | F28: =F8*$W28/$T8 -> 45.472458 | G28: =G8*$W28/$T8 -> 45.472458 | H28: =H8*$W28/$T8 -> 45.472458 | I28: =I8*$W28/$T8 -> 45.472458 | J28: =J8*$W28/$T8 -> 45.472458 | K28: =K8*$W28/$T8 -> 45.472458 | ... S28: =S8*$W28/$T8 -> 45.472458 | T28: ='Proceso II'!E255 -> 296.96672 | U28: ='Proceso III'!D93 -> 156.37476 | V28: ='Proceso IV'!D74 -> 274.21785 | W28: =SUM(T28:V28) -> 727.55933
A29: CAO2 | B29: AO4 | C29: Tender las telas sobre mesa de corte | D29: =D9*$W29/$T9 -> 15.138995 | E29: =E9*$W29/$T9 -> 19.464422 | F29: =F9*$W29/$T9 -> 19.464422 | G29: =G9*$W29/$T9 -> 38.928844 | H29: =H9*$W29/$T9 -> 15.138995 | I29: =I9*$W29/$T9 -> 17.301708 | J29: =J9*$W29/$T9 -> 18.743517 | K29: =K9*$W29/$T9 -> 20.185326 | ... S29: =S9*$W29/$T9 -> 19.464422 | T29: ='Proceso II'!C290 -> 67.351461 | U29: ='Proceso III'!D98 -> 31.274951 | V29: ='Proceso IV'!D79 -> 222.1761 | W29: =SUM(T29:V29) -> 320.80251
B30: AO5 | C30: Marcar la tela superficial con tiza de sastre | D30: =D10*$W30/$T10 -> 60.114898 | E30: =E10*$W30/$T10 -> 60.114898 | F30: =F10*$W30/$T10 -> 60.114898 | G30: =G10*$W30/$T10 -> 60.114898 | H30: =H10*$W30/$T10 -> 60.114898 | I30: =I10*$W30/$T10 -> 60.114898 | J30: =J10*$W30/$T10 -> 60.114898 | K30: =K10*$W30/$T10 -> 60.114898 | ... S30: =S10*$W30/$T10 -> 60.114898 | T30: ='Proceso II'!D290 -> 223.35146 | U30: ='Proceso III'!D99 -> 109.46233 | V30: ='Proceso IV'!D80 -> 629.02458 | W30: =SUM(T30:V30) -> 961.83837
B31: AO6 | C31: Cortar con la máquina cada conjunto de telas | D31: =D11*$W31/$T11 -> 66.660584 | E31: =E11*$W31/$T11 -> 66.660584 | F31: =F11*$W31/$T11 -> 66.660584 | G31: =G11*$W31/$T11 -> 66.660584 | H31: =H11*$W31/$T11 -> 66.660584 | I31: =I11*$W31/$T11 -> 66.660584 | J31: =J11*$W31/$T11 -> 66.660584 | K31: =K11*$W31/$T11 -> 66.660584 | ... S31: =S11*$W31/$T11 -> 66.660584 | T31: ='Proceso II'!E290 -> 328.08244 | U31: ='Proceso III'!D100 -> 109.46233 | V31: ='Proceso IV'!D81 -> 629.02458 | W31: =SUM(T31:V31) -> 1066.5693
B32: AO7 | C32: Etiquetar por prenda, talla y cliente con etiqueta de seguimiento | D32: =D12*$W32/$T12 -> 25.241927 | E32: =E12*$W32/$T12 -> 25.241927 | F32: =F12*$W32/$T12 -> 20.193541 | G32: =G12*$W32/$T12 -> 25.241927 | H32: =H12*$W32/$T12 -> 25.241927 | I32: =I12*$W32/$T12 -> 25.241927 | J32: =J12*$W32/$T12 -> 20.193541 | K32: =K12*$W32/$T12 -> 25.241927 | ... S32: =S12*$W32/$T12 -> 25.241927 | T32: ='Proceso II'!F290 -> 177.72941 | U32: ='Proceso III'!D101 -> 31.274951 | V32: ='Proceso IV'!D82 -> 179.72131 | W32: =SUM(T32:V32) -> 388.72567
B33: AO8 | C33: Embolsar para envío a Bordado y/o Estampado (externo) | D33: =D13*$W33/$T13 -> 18.864591 | E33: =E13*$W33/$T13 -> 24.254474 | F33: =F13*$W33/$T13 -> 24.254474 | G33: =G13*$W33/$T13 -> 48.508949 | H33: =H13*$W33/$T13 -> 18.864591 | I33: =I13*$W33/$T13 -> 21.559533 | J33: =J13*$W33/$T13 -> 23.35616 | K33: =K13*$W33/$T13 -> 25.152788 | ... S33: =S13*$W33/$T13 -> 24.254474 | T33: ='Proceso II'!G290 -> 188.75341 | U33: ='Proceso III'!D102 -> 31.274951 | V33: ='Proceso IV'!D83 -> 179.72131 | W33: =SUM(T33:V33) -> 399.74967
A34: CA03 | B34: AO9 | C34: Limpiar con el piqueteador cada prenda | D34: =D14*$W34/$T14 -> 156.13281 | E34: =E14*$W34/$T14 -> 200.74218 | F34: =F14*$W34/$T14 -> 200.74218 | G34: =G14*$W34/$T14 -> 401.48436 | H34: =H14*$W34/$T14 -> 156.13281 | I34: =I14*$W34/$T14 -> 178.4375 | J34: =J14*$W34/$T14 -> 193.30729 | K34: =K14*$W34/$T14 -> 208.17708 | ... S34: =S14*$W34/$T14 -> 200.74218 | T34: ='Proceso II'!C313 -> 286.37297 | U34: ='Proceso III'!D107 -> 312.74951 | V34: ='Proceso IV'!D88 -> 2709.4061 | W34: =SUM(T34:V34) -> 3308.5286
A35: CAO4 | B35: AO10 | C35: Desetiquetar cada parte de las prendas | D35: =D15*$W35/$T15 -> 47.727428 | E35: =E15*$W35/$T15 -> 47.727428 | F35: =F15*$W35/$T15 -> 38.181943 | G35: =G15*$W35/$T15 -> 47.727428 | H35: =H15*$W35/$T15 -> 47.727428 | I35: =I15*$W35/$T15 -> 47.727428 | J35: =J15*$W35/$T15 -> 38.181943 | K35: =K15*$W35/$T15 -> 47.727428 | ... S35: =S15*$W35/$T15 -> 47.727428 | T35: ='Proceso II'!C340 -> 69.362419 | U35: ='Proceso III'!D112 -> 93.824854 | V35: ='Proceso IV'!D93 -> 571.81512 | W35: =SUM(T35:V35) -> 735.0024
B36: AO11 | C36: Doblar la prenda | D36: =D16*$W36/$T16 -> 33.098526 | E36: =E16*$W36/$T16 -> 42.555248 | F36: =F16*$W36/$T16 -> 21.277624 | G36: =G16*$W36/$T16 -> 85.110495 | H36: =H16*$W36/$T16 -> 33.098526 | I36: =I16*$W36/$T16 -> 37.826887 | J36: =J16*$W36/$T16 -> 20.489564 | K36: =K16*$W36/$T16 -> 44.131368 | ... S36: =S16*$W36/$T16 -> 21.277624 | T36: ='Proceso II'!D340 -> 61.386567 | U36: ='Proceso III'!D113 -> 62.549903 | V36: ='Proceso IV'!D94 -> 381.21008 | W36: =SUM(T36:V36) -> 505.14655
B37: AO12 | C37: Etiquetar con nombre del cliente cada prenda | D37: =D17*$W37/$T17 -> 42.754886 | E37: =E17*$W37/$T17 -> 54.970568 | F37: =F17*$W37/$T17 -> 54.970568 | G37: =G17*$W37/$T17 -> 109.94114 | H37: =H17*$W37/$T17 -> 42.754886 | I37: =I17*$W37/$T17 -> 48.862727 | J37: =J17*$W37/$T17 -> 52.934621 | K37: =K17*$W37/$T17 -> 57.006515 | ... S37: =S17*$W37/$T17 -> 54.970568 | T37: ='Proceso II'!E340 -> 240.35642 | U37: ='Proceso III'!D114 -> 93.824854 | V37: ='Proceso IV'!D95 -> 571.81512 | W37: =SUM(T37:V37) -> 905.9964
B38: AO13 | C38: Embolsar para envío final | D38: =D18*$W38/$T18 -> 30.285919 | E38: =E18*$W38/$T18 -> 30.285919 | F38: =F18*$W38/$T18 -> 30.285919 | G38: =G18*$W38/$T18 -> 60.571839 | H38: =H18*$W38/$T18 -> 30.285919 | I38: =I18*$W38/$T18 -> 30.285919 | J38: =J18*$W38/$T18 -> 30.285919 | K38: =K18*$W38/$T18 -> 30.285919 | ... S38: =S18*$W38/$T18 -> 30.285919 | T38: ='Proceso II'!F340 -> 101.38657 | U38: ='Proceso III'!D115 -> 62.549903 | V38: ='Proceso IV'!D96 -> 381.21008 | W38: =SUM(T38:V38) -> 545.14655
A39: CAO5 | B39: AO14 | C39: Realizar el contrato | D39: =D19*$W39/$T19 -> 176.63246 | E39: =E19*$W39/$T19 -> 176.63246 | F39: =F19*$W39/$T19 -> 176.63246 | G39: =G19*$W39/$T19 -> 176.63246 | H39: =H19*$W39/$T19 -> 176.63246 | I39: =I19*$W39/$T19 -> 176.63246 | J39: =J19*$W39/$T19 -> 176.63246 | K39: =K19*$W39/$T19 -> 176.63246 | ... S39: =S19*$W39/$T19 -> 176.63246 | T39: ='Proceso II'!C363 -> 666.05714 | U39: ='Proceso III'!D120 -> 1261.4556 | V39: ='Proceso IV'!D101 -> 898.60654 | W39: =SUM(T39:V39) -> 2826.1193
B40: AO15 | C40: Entregar el pedido | D40: =D20*$W40/$T20 -> 293.12521 | E40: =E20*$W40/$T20 -> 146.5626 | F40: =F20*$W40/$T20 -> 146.5626 | G40: =G20*$W40/$T20 -> 293.12521 | H40: =H20*$W40/$T20 -> 195.4168 | I40: =I20*$W40/$T20 -> 293.12521 | J40: =J20*$W40/$T20 -> 293.12521 | K40: =K20*$W40/$T20 -> 293.12521 | ... S40: =S20*$W40/$T20 -> 341.97941 | T40: ='Proceso II'!D363 -> 1552.8571 | U40: ='Proceso III'!D121 -> 1261.4556 | V40: ='Proceso IV'!D102 -> 898.60654 | W40: =SUM(T40:V40) -> 3712.9193
C41: TOTAL | D41: =SUM(D26:D40) -> 1042.7501 | E41: =SUM(E26:E40) -> 981.18443 | F41: =SUM(F26:F40) -> 945.31294 | G41: =SUM(G26:G40) -> 1540.5191 | H41: =SUM(H26:H40) -> 945.04171 | I41: =SUM(I26:I40) -> 1085.2486 | J41: =SUM(J26:J40) -> 1078.4974 | K41: =SUM(K26:K40) -> 1141.9132 | ... W41: =SUM(W26:W40) -> 17071.592
A50: CÁLCULO DEL COSTO UNITARIO DE LOS OBJETOS DE COSTO
D53: OT 1 | E53: OT2 | F53: OT3 | G53: OT4 | H53: OT 5 | I53: OT 6 | J53: OT 7 | K53: OT 8 | L53: OT 9 | M53: OT 10 | N53: OT 11 | O53: OT 12 | P53: OT 13 | Q53: OT 14 | R53: OT 15 | S53: OT 16
C55: Costo Total | D55: =D41+CSD!C27+CMOD!G33+CMD!D62 -> 2063.6358 | E55: =E41+CSD!D27+CMOD!H33+CMD!E62 -> 2260.0018 | F55: =F41+CSD!E27+CMOD!I33+CMD!F62 -> 1429.9589 | G55: =G41+CSD!F27+CMOD!J33+CMD!G62 -> 3963.1539 | H55: =H41+CSD!G27+CMOD!K33+CMD!H62 -> 2027.5274 | I55: =I41+CSD!H27+CMOD!L33+CMD!I62 -> 2234.7751 | J55: =J41+CSD!I27+CMOD!M33+CMD!J62 -> 1522.4436 | K55: =K41+CSD!J27+CMOD!N33+CMD!K62 -> 2415.0286 | ... S55: =S41+CSD!R27+CMOD!V33+CMD!S62 -> 2382.9706
C56: Produccion Mensual (paquetes) | D56: 21 | E56: 27 | F56: 27 | G56: 54 | H56: 21 | I56: 24 | J56: 26 | K56: 28 | L56: 17 | M56: 14 | N56: 34 | O56: 22 | P56: 23 | Q56: 29 | R56: 51 | S56: 27
C57: COSTO UNITARIO | D57: =D55/D56 -> 98.268374 | E57: =E55/E56 -> 83.703771 | F57: =F55/F56 -> 52.961442 | G57: =G55/G56 -> 73.391738 | H57: =H55/H56 -> 96.548926 | I57: =I55/I56 -> 93.11563 | J57: =J55/J56 -> 58.555522 | K57: =K55/K56 -> 86.25102 | ... S57: =S55/S56 -> 88.25817
C60: Nota: Lo que se ha hallado es el Costo Integral de cada producto

Sheet Precio_de_venta
A1: PRECIO DE VENTA
B3: Precio de Base
A4: Tela | B4: Franela Perchada 24/1 | C4: Frech Terry 24/1
A5: CASACAS | B5: 95 | C5: 100
B6: Si lleva se adiciona
A7: Broche | B7: 4 | C7: 4
A8: Cierre | B8: 3 | C8: 3
A9: Bordado | B9: 10 | C9: 10
A10: Estampado Interno | B10: 2 | C10: 2
B12: Precio de Base
A13: Tela | B13: Jersey 30/1 | C13: Algodón tacto
A14: POLOS | B14: 55 | C14: 50
B15: Si lleva se adiciona
A16: Estampado Pecho | B16: 2 | C16: 2
A17: Estampado Espalda | B17: 2 | C17: 2
A18: Insignia | B18: 2 | C18: 2
B20: Precio de Base
A21: Tela | B21: Franela Perchada 24/1 | C21: Frech Terry 24/1
A22: POLERAS | B22: 90 | C22: 95
B23: Si lleva se adiciona
A24: Bordado | B24: 4 | C24: 4
A25: Estampado Interno | B25: 2 | C25: 2

Sheet Valor_de_venta_por_OT
A1: Valor de Venta por OT
A4: Detalles OT1 | B4: CASACA | C4: 21
A5: Broche | B5: Cierre | C5: Tela | D5: Bordado | E5: Estampado Interno
A6: Sí | B6: Sí | C6: Franela Perchada 24/1 | D6: Sí | E6: Sí
B8: PRECIO | D8: Venta
B9: =Precio_de_venta!B5+Precio_de_venta!B7+Precio_de_venta!B8+Precio_de_venta!B9+Precio_de_venta!B10 -> 114 | C9: =1.18*B9 -> 134.52 | D9: =C9*C4 -> 2824.92
B10: sin IGV | C10: con IGV
A12: Detalles OT2 | B12: CASACA | C12: 27
A13: Broche | B13: Cierre | C13: Tela | D13: Bordado | E13: Estampado Interno
A14: Sí | B14: NO | C14: Franela Perchada 24/1 | D14: Sí | E14: Sí
B16: PRECIO | D16: Venta
B17: =Precio_de_venta!B5+Precio_de_venta!B7+Precio_de_venta!B9+Precio_de_venta!B10 -> 111 | C17: =1.18*B17 -> 130.98 | D17: =C17*C12 -> 3536.46
B18: sin IGV | C18: con IGV
A20: Detalles OT3 | B20: POLOS | C20: 27
A21: Estampado pecho | B21: estampado espalda | C21: Tela | D21: Bordado | E21: Estampado Interno
A22: Sí | B22: No | C22: Jersey | D22: Sí | E22: Sí
B24: PRECIO | D24: Venta
B25: =Precio_de_venta!B14+Precio_de_venta!B16+Precio_de_venta!B18 -> 59 | C25: =1.18*B25 -> 69.62 | D25: =C25*C20 -> 1879.74
B26: sin IGV | C26: con IGV
A28: Detalles OT4 | B28: POLERAS | C28: 54
A29: Bordado | B29: Tela | C29: Estampado Interno
A30: Sí | B30: Franela Perchada 24/1 | C30: Sí
B32: PRECIO | D32: Venta
B33: =Precio_de_venta!B22+Precio_de_venta!B24+Precio_de_venta!B25 -> 96 | C33: =1.18*B33 -> 113.28 | D33: =C33*C28 -> 6117.12
B34: sin IGV | C34: con IGV
A36: Detalles OT5 | B36: CASACA | C36: 21
A37: Broche | B37: Cierre | C37: Tela | D37: Bordado | E37: Estampado Interno
A38: Sí | B38: Sí | C38: Frech Terry 24/1 | D38: Sí | E38: Sí
B40: PRECIO | D40: Venta
B41: =Precio_de_venta!C5+Precio_de_venta!C7+Precio_de_venta!C8+Precio_de_venta!C9+Precio_de_venta!C10 -> 119 | C41: =1.18*B41 -> 140.42 | D41: =C41*C36 -> 2948.82
B42: sin IGV | C42: con IGV
A44: Detalles OT6 | B44: POLERA | C44: 24
A45: Bordado | B45: Tela | C45: Estampado Interno
A46: Sí | B46: Frech Terry 24/1 | C46: Sí
B48: PRECIO | D48: Venta
B49: =Precio_de_venta!C22+Precio_de_venta!C24+Precio_de_venta!C25 -> 101 | C49: =1.18*B49 -> 119.18 | D49: =C49*C44 -> 2860.32
B50: sin IGV | C50: con IGV
A52: Detalles OT7 | B52: POLOS | C52: 26
A53: Estampado Pecho | B53: Estampado Espalda | C53: Tela | D53: Insignia | E53: Cuello
A54: Sí | B54: No | C54: Algodón Tacto | D54: Sí | E54: V
B56: PRECIO | D56: Venta
B57: =Precio_de_venta!C14+Precio_de_venta!C16+Precio_de_venta!C18 -> 54 | C57: =1.18*B57 -> 63.72 | D57: =C57*C52 -> 1656.72
B58: sin IGV | C58: con IGV
A60: Detalles OT8 | B60: POLERAS | C60: 28
A61: Bordado | B61: Tela | C61: Estampado Interno
A62: Sí | B62: Franela Perchada 24/1 | C62: Sí
B64: PRECIO | D64: Venta
B65: =Precio_de_venta!B22+Precio_de_venta!B24+Precio_de_venta!B25 -> 96 | C65: =1.18*B65 -> 113.28 | D65: =C65*C60 -> 3171.84
B66: sin IGV | C66: con IGV
A68: Detalles OT9 | B68: POLERAS | C68: 17
A69: Bordado | B69: Tela | C69: Estampado Interno
A70: Sí | B70: Franela Perchada 24/1 | C70: Sí
B72: PRECIO | D72: Venta
B73: =Precio_de_venta!B22+Precio_de_venta!B24+Precio_de_venta!B25 -> 96 | C73: =1.18*B73 -> 113.28 | D73: =C73*C68 -> 1925.76
B74: sin IGV | C74: con IGV
A76: Detalles OT10 | B76: POLERAS | C76: 14
A77: Bordado | B77: Tela | C77: Estampado Interno
A78: Sí | B78: Frech Terry 24/1 | C78: Sí
B80: PRECIO | D80: Venta
B81: =Precio_de_venta!C22+Precio_de_venta!C24+Precio_de_venta!C25 -> 101 | C81: =1.18*B81 -> 119.18 | D81: =C81*C76 -> 1668.52
B82: sin IGV | C82: con IGV
A84: Detalles OT11 | B84: POLOS | C84: 34
A85: Estampado Pecho | B85: Estampado Espalda | C85: Tela | D85: Insignia | E85: Cuello
A86: Sí | B86: No | C86: Jersey | D86: Sí | E86: Redondo
B88: PRECIO | D88: Venta
B89: =Precio_de_venta!B14+Precio_de_venta!B16+Precio_de_venta!B18 -> 59 | C89: =1.18*B89 -> 69.62 | D89: =C89*C84 -> 2367.08
B90: sin IGV | C90: con IGV
A92: Detalles OT12 | B92: POLERA | C92: 22
A93: Bordado | B93: Tela | C93: Estampado Interno
A94: Sí | B94: Frech Terry 24/1 | C94: Sí
B96: PRECIO | D96: Venta
B97: =Precio_de_venta!C22+Precio_de_venta!C24+Precio_de_venta!C25 -> 101 | C97: =1.18*B97 -> 119.18 | D97: =C97*C92 -> 2621.96
B98: sin IGV | C98: con IGV
A100: Detalles OT13 | B100: CASACAS | C100: 23
A101: Broche | B101: Cierre | C101: Tela | D101: Bordado | E101: Estampado Interno
A102: No | B102: Sí | C102: Frech Terry 24/1 | D102: Sí | E102: Sí
B104: PRECIO | D104: Venta
B105: =Precio_de_venta!C5+Precio_de_venta!B8+Precio_de_venta!B9+Precio_de_venta!B10 -> 115 | C105: =1.18*B105 -> 135.7 | D105: =C105*C100 -> 3121.1
B106: sin IGV | C106: con IGV
A108: Detalles OT14 | B108: CASACAS | C108: 29
A109: Broche | B109: Cierre | C109: Tela | D109: Bordado | E109: Estampado Interno
A110: Sí | B110: No | C110: Franela Perchada 24/1 | D110: Sí | E110: Sí
B112: PRECIO | D112: Venta
B113: =Precio_de_venta!B5+Precio_de_venta!B7+Precio_de_venta!B9+Precio_de_venta!B10 -> 111 | C113: =1.18*B113 -> 130.98 | D113: =C113*C108 -> 3798.42
B114: sin IGV | C114: con IGV
A116: Detalles OT15 | B116: CASACA | C116: 51
A117: Broche | B117: Cierre | C117: Tela | D117: Bordado | E117: Estampado Interno
A118: Sí | B118: Si | C118: Franela Perchada 24/1 | D118: Sí | E118: Sí
B120: PRECIO | D120: Venta
B121: =Precio_de_venta!B5+Precio_de_venta!B7+Precio_de_venta!B8+Precio_de_venta!B9+Precio_de_venta!B10 -> 114 | C121: =1.18*B121 -> 134.52 | D121: =C121*C116 -> 6860.52
B122: sin IGV | C122: con IGV
A124: Detalles OT16 | B124: POLERA | C124: 27
A125: Bordado | B125: Tela | C125: Estampado Interno
A126: Sí | B126: Franela Perchada 24/1 | C126: Sí
B128: PRECIO | D128: Venta
B129: =Precio_de_venta!B22+Precio_de_venta!B24+Precio_de_venta!B25 -> 96 | C129: =1.18*B129 -> 113.28 | D129: =C129*C124 -> 3058.56
B130: sin IGV | C130: con IGV

Sheet Análisis_de_Rentabilidad
A1: ANÁLISIS DE RENTABILIDAD POR ORDEN DE TRABAJO | E1: ANÁLISIS DE RENTABILIDAD POR ORDEN DE TRABAJO
A2: OT1 | C2: 21 | H2: CASACAS | I2: CASACAS | J2: POLOS | K2: POLERAS | L2: CASACAS | M2: POLERAS | N2: POLOS | O2: POLERAS | P2: POLERAS | Q2: POLERAS | R2: POLOS | S2: POLERAS | T2: CASACAS | U2: CASACAS | V2: CASACAS | W2: POLERAS
A3: CASACAS | H3: OT1 | I3: OT2 | J3: OT3 | K3: OT4 | L3: OT5 | M3: OT6 | N3: OT7 | O3: OT8 | P3: OT9 | Q3: OT10 | R3: OT11 | S3: OT12 | T3: OT13 | U3: OT14 | V3: OT15 | W3: OT16 | X3: TOTAL
A4: ESTADO DE LA ORDEN | C4: TERMINADA Y VENDIDA | E4: Ventas | H4: =C5*C2 -> 2394 | I4: =C12*C9 -> 2997 | J4: =C19*C16 -> 1593 | K4: =C26*C23 -> 5184 | L4: =C33*C30 -> 2499 | M4: =C40*C37 -> 2424 | N4: =C47*C44 -> 1404 | O4: =C54*C51 -> 2688 | P4: =C61*C58 -> 1632 | Q4: =C68*C65 -> 1414 | R4: =C75*C72 -> 2006 | S4: =C82*C79 -> 2222 | T4: =C89*C86 -> 2645 | U4: =C96*C93 -> 3219 | V4: =C103*C100 -> 5814 | W4: =C110*C107 -> 2592 | X4: =SUM(H4:W4) -> 42727
A5: VENTA | C5: =Valor_de_venta_por_OT!B9 -> 114 | E5: Costo de Ventas | H5: =C6*C2 -> 2063.6358 | I5: =C13*C9 -> 2260.0018 | J5: =C20*C16 -> 1429.9589 | K5: =C34*C30 -> 2027.5274 | L5: =C34*C30 -> 2027.5274 | M5: =C41*C37 -> 2234.7751 | N5: =C48*C44 -> 1522.4436 | O5: =C55*C51 -> 2415.0286 | P5: =C62*C58 -> 1644.9594 | Q5: =C69*C65 -> 1509.6294 | R5: =C76*C72 -> 1703.0517 | S5: =C83*C79 -> 2039.8839 | T5: =C90*C86 -> 2036.6698 | U5: =C97*C93 -> 2458.0552 | V5: =C104*C100 -> 3717.5992 | W5: =C111*C107 -> 2382.9706 | X5: =SUM(H5:W5) -> 33473.718
A6: COSTO DE VENTA | C6: ='Proceso V'!D57 -> 98.268374 | E6: Margen Neto | H6: =H4-H5 -> 330.36415 | I6: =I4-I5 -> 736.99819 | J6: =J4-J5 -> 163.04108 | K6: =K4-K5 -> 3156.4726 | L6: =L4-L5 -> 471.47255 | M6: =M4-M5 -> 189.22487 | N6: =N4-N5 -> -118.44358 | O6: =O4-O5 -> 272.97143 | ... X6: =X4-X5 -> 9253.2821
A7: MARGEN NETO | C7: =(C5-C6)/C6 -> 0.1600884
A9: OT2 | C9: 27 | H9: Monto | I9: % | K9: RENTABILIDAD POR PRODUCTO
A10: CASACAS | E10: Valor de Venta | H10: =SUM(H4:W4) -> 42727 | I10: =100% -> 1 | K10: CASACAS | L10: POLOS | M10: POLERAS
A11: ESTADO DE LA ORDEN | C11: TERMINADA Y VENDIDA | E11: Costo de Ventas | H11: =SUM(H5:W5) -> 33473.718 | I11: =H11/H10 -> 0.78343244 | K11: =SUMIF($H$2:$W$2,K10,$H$6:$W$6) -> 5004.5107 | L11: =SUMIF($H$2:$W$2,L10,$H$6:$W$6) -> 347.5458 | M11: =SUMIF($H$2:$W$2,M10,$H$6:$W$6) -> 3901.2256 | N11: =SUM(K11:M11) -> 9253.2821
A12: VENTA | C12: =Valor_de_venta_por_OT!B17 -> 111 | E12: Margen Neto | H12: =H10-H11 -> 9253.2821 | I12: =H12/H10 -> 0.21656756 | K12: =K11/$N$11 -> 0.54083628 | L12: =L11/$N$11 -> 0.037559192 | M12: =M11/$N$11 -> 0.42160452 | N12: =SUM(K12:M12) -> 1
A13: COSTO DE VENTA | C13: ='Proceso V'!E57 -> 83.703771
A14: MARGEN NETO | C14: =(C12-C13)/C13 -> 0.32610513
A16: OT3 | C16: 27
A17: POLOS
A18: ESTADO DE LA ORDEN | C18: TERMINADA Y VENDIDA
A19: VENTA | C19: =Valor_de_venta_por_OT!B25 -> 59
A20: COSTO DE VENTA | C20: ='Proceso V'!F57 -> 52.961442
A21: MARGEN NETO | C21: =(C19-C20)/C20 -> 0.11401801
A23: OT4 | C23: 54
A24: POLERAS
A25: ESTADO DE LA ORDEN | C25: TERMINADA Y VENDIDA
A26: VENTA | C26: =Valor_de_venta_por_OT!B33 -> 96
A27: COSTO DE VENTA | C27: ='Proceso V'!G57 -> 73.391738
A28: MARGEN NETO | C28: =(C26-C27)/C27 -> 0.30804914
A30: OT5 | C30: 21
A31: CASACAS
A32: ESTADO DE LA ORDEN | C32: TERMINADA Y VENDIDA
A33: VENTA | C33: =Valor_de_venta_por_OT!B41 -> 119
A34: COSTO DE VENTA | C34: ='Proceso V'!H57 -> 96.548926
A35: MARGEN NETO | C35: =(C33-C34)/C34 -> 0.23253572
A37: OT6 | C37: 24
A38: POLERAS
A39: ESTADO DE LA ORDEN | C39: TERMINADA Y VENDIDA
A40: VENTA | C40: =Valor_de_venta_por_OT!B49 -> 101
A41: COSTO DE VENTA | C41: ='Proceso V'!I57 -> 93.11563
A42: MARGEN NETO | C42: =(C40-C41)/C41 -> 0.084672891
A44: OT7 | C44: 26
A45: POLOS
A46: ESTADO DE LA ORDEN | C46: TERMINADA Y VENDIDA
A47: VENTA | C47: =Valor_de_venta_por_OT!B57 -> 54
A48: COSTO DE VENTA | C48: ='Proceso V'!J57 -> 58.555522
A49: MARGEN NETO | C49: =(C47-C48)/C48 -> -0.077798338
A51: OT8 | C51: 28
A52: POLERAS
A53: ESTADO DE LA ORDEN | C53: TERMINADA Y VENDIDA
A54: VENTA | C54: =Valor_de_venta_por_OT!B65 -> 96
A55: COSTO DE VENTA | C55: ='Proceso V'!K57 -> 86.25102
A56: MARGEN NETO | C56: =(C54-C55)/C55 -> 0.11303031
A58: OT9 | C58: 17
A59: POLERAS
A60: ESTADO DE LA ORDEN | C60: TERMINADA Y VENDIDA
A61: VENTA | C61: =Valor_de_venta_por_OT!B73 -> 96
A62: COSTO DE VENTA | C62: ='Proceso V'!L57 -> 96.762318
A63: MARGEN NETO | C63: =(C61-C62)/C62 -> -0.0078782506
A65: OT10 | C65: 14
A66: POLERAS
A67: ESTADO DE LA ORDEN | C67: TERMINADA Y VENDIDA
A68: VENTA | C68: =Valor_de_venta_por_OT!B81 -> 101
A69: COSTO DE VENTA | C69: ='Proceso V'!M57 -> 107.83067
A70: MARGEN NETO | C70: =(C68-C69)/C69 -> -0.063346252
A72: OT11 | C72: 34
A73: POLOS
A74: ESTADO DE LA ORDEN | C74: TERMINADA Y VENDIDA
A75: VENTA | C75: =Valor_de_venta_por_OT!B89 -> 59
A76: COSTO DE VENTA | C76: ='Proceso V'!N57 -> 50.089756
A77: MARGEN NETO | C77: =(C75-C76)/C76 -> 0.17788556
A79: OT12 | C79: 22
A80: POLERAS
A81: ESTADO DE LA ORDEN | C81: TERMINADA Y VENDIDA
A82: VENTA | C82: =Valor_de_venta_por_OT!B97 -> 101
A83: COSTO DE VENTA | C83: ='Proceso V'!O57 -> 92.721995
A84: MARGEN NETO | C84: =(C82-C83)/C83 -> 0.089277687
A86: OT13 | C86: 23
A87: CASACAS
A88: ESTADO DE LA ORDEN | C88: TERMINADA Y VENDIDA
A89: VENTA | C89: =Valor_de_venta_por_OT!B105 -> 115
A90: COSTO DE VENTA | C90: ='Proceso V'!P57 -> 88.55086
A91: MARGEN NETO | C91: =(C89-C90)/C90 -> 0.29868868
A93: OT14 | C93: 29
A94: CASACAS
A95: ESTADO DE LA ORDEN | C95: TERMINADA Y VENDIDA
A96: VENTA | C96: =Valor_de_venta_por_OT!B113 -> 111
A97: COSTO DE VENTA | C97: ='Proceso V'!Q57 -> 84.760524
A98: MARGEN NETO | C98: =(C96-C97)/C97 -> 0.3095719
A100: OT15 | C100: 51
A101: CASACAS
A102: ESTADO DE LA ORDEN | C102: TERMINADA Y VENDIDA
A103: VENTA | C103: =Valor_de_venta_por_OT!B121 -> 114
A104: COSTO DE VENTA | C104: ='Proceso V'!R57 -> 72.894102
A105: MARGEN NETO | C105: =(C103-C104)/C104 -> 0.56391254
A107: OT16 | C107: 27
A108: POLERAS
A109: ESTADO DE LA ORDEN | C109: TERMINADA Y VENDIDA
A110: VENTA | C110: =Valor_de_venta_por_OT!B129 -> 96
A111: COSTO DE VENTA | C111: ='Proceso V'!S57 -> 88.25817
A112: MARGEN NETO | C112: =(C110-C111)/C111 -> 0.087717999

Sheet Comparación de Costos
A1: Comparación de Costos
A4: Costo Integral (Modelo III ABC) VS Costo de Venta (Costeo Tradicional)
C9: OT1 | D9: OT2 | E9: OT3 | F9: OT4
C10: CASACAS | D10: CASACAS | E10: POLOS | F10: POLERAS
A11: N° Prendas | B11: Número de Prendas | C11: 21 | D11: 27 | E11: 27 | F11: 54
A12: COSTO UNITARIO (Tradicional) | C12: 83.848594 | D12: 78.91437 | E12: 51.525885 | F12: 75.422463
A13: COSTO UNITARIO (ABC) | C13: =Análisis_de_Rentabilidad!C6 -> 98.268374 | D13: =Análisis_de_Rentabilidad!C13 -> 83.703771 | E13: =Análisis_de_Rentabilidad!C20 -> 52.961442 | F13: =Análisis_de_Rentabilidad!C27 -> 73.391738
A15: Tradicional | D15: ABC
A16: - Se consideró un periodo de costeo de 1 mes | D16: - Se consideró un periodo de costeo de 3 meses
A17: - Solo se trabajó con la información proporcionada por lo que se tuvo pocos elementos de costos para distribuir los indirectos a los productos | D17: - Al desagregarse en actividades, se encontraron mayor cantidad de elementos de costos lo que influye en el precio
D18: - Al utilizar el Modelo de Costo ABC, se desagrega el proceso de reparto de elementos de costos. Por esto es que el cálculo es más representativo y real. Además esto es
A22: NOTA: Se concluye que los costos de ventas por el costeo ABC es más preciso. Es mayor el costo en algunos casos debido a que se les ha asignado todos los gastos de venta y los gastos de administración. De tal manera que el costo unitario es más real y es una prueba "más ácida"ya que muestra a partir de que valor de venta se obtiene una utilidad neta
