Workbook

Sheet NOTAS
A1: DISEÑO DE UN PROTOTIPO DE SISTEMA DE COSTOS EN UNA EMPRESA:
A3: OBJETIVO: VALORIZAR LOS INVENTARIOS PARA CALCULAR EL COSTO DE VENTAS Y GENERAR INFORMACION PARA LA TOMA DE DECISIONES
A4: EL TRATAMIENTO DE LA INFORMACION PARA LA CONTABILIDAD ES DE ACUERDO A LAS EXIGENCIAS DE LAS NORMAS CONTABLES Y TRIBUTARIAS
A5: EJEMPLO: METODO PROMEDIO PARA VALORIZACION DE INVENTARIOS
A6: EL TRATAMIENTO DE LA INFORMACION PARA LA TOMA DE DECISIONES ES DE ACUERDO A LAS NECESIDADES, SEA CON INFORMACION HISTORICA
A7: O SEA DE ACUERDO CON INFORMACION PROYECTADA (CALCULO DE COSTOS PARA DETERMINAR VALORES DE VENTA A SOLICITUD DE UN CLIENTE)
A9: SISTEMA DE COSTEO: EVALUAR SI ADOPTA UN SISTEMA DE COSTEO TRADICIONAL O UN SISTEMA DE COSTEO ABC (SE RECOMIENDA COSTEO ABC)
A10: SUGERENCIA ES DEFINIR UN SISTEMA DE COSTEO POR ORDENES DE TRABAJO O LOTES DE PRODUCCION, PORQUE EL OBJETO DE COSTEO Y EL CONTROL
A11: DE LOS COSTOS SERÍAN LAS ORDENES DE TRABAJO O LOS LOTES DE PRODUCCION
A13: DESARROLLAR UN MODELO DE COSTEO
A15: DEFINIR UN PERIODO PARA EL COSTEO: SE SUGIERE UN MES CUYO PERIODO YA FINALIZO
A16: TENIENDO EN CUENTA QUE LA CONTABILIDAD FINANCIERA TENGA UN PERIODO CERRADO Y VALIDADO
A18: DEFINIR LA ESTRUCTURA DE HOJAS EXCEL PARA EL PROTOTIPO | H18: HOJAS DE CALCULO:
H19: MAESTROS: CC, EC, MATERIALES, PERSONAL. SERVICIOS DIRECTOS, COSTOS INDIRECTOS
H20: MODELO DE COSTEO
H21: HOJAS DE PROCESOS DE CALCULO
H22: HOJAS DE RESULTADOS
H23: HOJAS DE COSTOS DE LOS OBJETOS DE COSTOS
H24: HOJA DE RESUMEN DE COSTOS
H25: HOJA DE DASHBOARD DE COSTOS

Sheet Modelo
A1: MODELO DE COSTEO TRADICIONAL
A2: SISTEMA DE COSTEO POR ORDENES DE PRODUCCION
A3: PERIODO DE COSTEO: MES
A4: EMPRESA: ENVASE SAC
D35: PROCESOS DE COSTEO:
D36: P1: COSTEO DEL MATERIAL DIRECTO A LAS OT
D37: P2: COSTEO DEL PERSONAL DIRECTO A LAS OT
D38: P3: COSTEO DEL SERVICIO DIRECTO A LAS OT
D39: P4: COSTEO DE LOS INDIRECTOS
D40: P4A: COSTEO DEL COSTO INDIRECTO A TODOS LOS CENTROS DE COSTOS
D41: P4B: COSTEO DEL COSTO INDIRECTO DE LOS CENTROS DE COSTOS DE APOYO A LOS PRODUCTIVOS (METODO DIRECTO)
D42: P4C: COSTEO DEL COSTO INDIRECTO DE LOS CC PRODUCTIVOS A LOS OBJETOS DE COSTOS
D43: P5: CALCULO DEL GASTO ADMINISTRATIVO EN LOS OBJETOS DE COSTOS
D44: P6: CALCULO DEL GASTO DE VENTAS A LOS OBJETOS DE COSTOS
