Workbook

Sheet Caso
A1: CASO: PLANETA SAC | L1: S/ | M1: % | Q1: S/ | R1: %
A2: La empresa Planeta SAC se constituye con fecha 01 de enero 2020, siendo el aporte de los accionistas los siguientes: | K2: Mateo Quispe | L2: 600000 | M2: =L2/$L$5 -> 0.60913706 | P2: Socio 1 | Q2: 10000 | R2: =Q2/$Q$4 -> 0.5
A3: El señor Mateo Quispe aporto S/ 600,000 en efectivo; la señora Martha Morales dio mobiliario valorizado en S/ 150,000 | K3: Martha Morales | L3: =150000+35000 -> 185000 | M3: =L3/$L$5 -> 0.18781726 | P3: Socio 2 | Q3: 10000 | R3: =Q3/$Q$4 -> 0.5
A4: y una patente en S/ 35,000; el señor Pablo Mamani aporto con un inmueble valorizado en S/ 200,000. | K4: Pablo Mamani | L4: 200000 | M4: =L4/$L$5 -> 0.20304569 | P4: Total | Q4: =SUM(Q2:Q3) -> 20000 | R4: =SUM(R2:R3) -> 1
K5: Total | L5: =SUM(L2:L4) -> 985000 | M5: =SUM(M2:M4) -> 1
A6: Se solicitó un prestamo por un año al Banco Sur por S/ 600,000 a una tasa del 10% anual, la constitución de la empresa
A7: costo S/ 5,000. | Q7: S/ | R7: %
L8: S/ | M8: % | P8: Socio 1 | Q8: 10000 | R8: =Q8/$Q$11 -> 0.083333333
A9: Se compró a la empresa ABC Corporatión SAC mercaderías por S/ 56,000 | K9: Mateo Quispe | L9: 600000 | M9: =L9/$L$13 -> 0.58536585 | P9: Socio 2 | Q9: 10000 | R9: =Q9/$Q$11 -> 0.083333333
K10: Martha Morales | L10: =150000+35000 -> 185000 | M10: =L10/$L$13 -> 0.1804878 | P10: Socio 3 | Q10: 100000 | R10: =Q10/$Q$11 -> 0.83333333
A11: Luego se realizarón las siguientes transacciones: | K11: Pablo Mamani | L11: 200000 | M11: =L11/$L$13 -> 0.19512195 | P11: Total | Q11: =SUM(Q8:Q10) -> 120000 | R11: =SUM(R8:R10) -> 1
A12: 1. Se compró un edificio por S/ 300,000, se pagó la mitad en efectivo y el resto se pagará en letras | K12: Nuevo socio | L12: 40000 | M12: =L12/$L$13 -> 0.03902439
A13: 2. Se compró mercaderías por S/ 600,000 al contado pagando el 18% adicional por IGV | K13: Total | L13: =SUM(L9:L12) -> 1025000 | M13: =SUM(M9:M12) -> 1
A14: 3. Se vendió mercadería por S/ 400,000, todo a crédito, cobrá el 18% por IGV. Su costo fue S/ 350,000
A15: 4. Se pagarón luz eléctrica, agua y telefono fijo S/ 300, S/ 200 y S/ 450 respectivamente, adicionar el IGV.
A16: 5. Se paga la planilla de los trabajadores por el mes un valor de S/ 8,000 | K16: FUSION
A17: 6. Se pagan tributos por S/ 5,000 efectivo y una multa puesta por la SUNAT por S/ 1,500 | L17: S/ | M17: %
A18: 7. Pagamos seguros adelantados por S/ 4,000 | K18: Mateo Quispe | L18: 600000 | M18: =L18/$L$23 -> 0.59701493
A19: 8. Compramos útiles de escritorio por S/ 400, adicionar el IGV | K19: Martha Morales | L19: =150000+35000 -> 185000 | M19: =L19/$L$23 -> 0.1840796
A20: 9. Se solicita un préstamo al Banco de Crédito por S/ 30,000 con una tasa de interés del 10%, el préstamo | K20: Pablo Mamani | L20: 200000 | M20: =L20/$L$23 -> 0.19900498
A21: se pagará en un año. | K21: Socio 1 | L21: 10000 | M21: =L21/$L$23 -> 0.0099502488
A22: 10. Se depreció los activos fijos por S/ 35,000 | K22: Socio 2 | L22: 10000 | M22: =L22/$L$23 -> 0.0099502488
A23: 11. Un nuevo socio ingresa a la empresa con el aporte de una patente valorizada en S/ 40,000 | K23: Total | L23: =SUM(L18:L22) -> 1005000 | M23: =SUM(M18:M22) -> 1
A24: 12. Se provisiona S/ 24,000 por concepto de beneficios sociales, S/ 4,500 por desvalorización de mercaderias,
A25: S/ 6,000 por amortización de intangibles
A26: 13. Se adquirió mercaderia por un valor de S/ 35,000. Este se pagó 50% al contado y 50% a crédito, pagandose
A27: adicionalmente el IGV.
A28: 14. Se presta dinero por 6 meses a una empresa por S/ 50,000 a un interés del 10% anual
A29: 15. Se cobra a los clientes S/ 6,000
A30: 16. Compramos bonos corporativos por S/ 9,000
A31: 17. Se venden mercaderías por S/ 50,000 para ser pagadas 30% al contado y el resto a crédito a 30 días
A32: con un interés del 5% por mes. El costo de la mercadería es de S/ 40,000
A33: 18. Se pagan el 50% de las planillas un valor de S/ 4,000
A34: 19. Se recibió S/ 5,000 por una venta futura
A35: 20. Se incremento en 10% el valor de los activos fijos
... A39: Se pide: elaborar el Estado de Situación Financiera y el Estado de Resultados

Sheet DIARIO
A1: ASIENTOS DE DIARIO
A10: Transacciones | E10: Asiento Apertura | F10: Debe | G10: Haber
B11: 10 | D11: Efectivo y equivalente de efectivo | F11: 600000
E12: Capital Social | G12: 600000
D13: Inmueble maquinaria y Equipo | F13: 150000
E14: Capital Social | G14: 150000
B15: 33 | D15: Intangibles | F15: 35000
B16: 34 | E16: Capital Social | G16: 35000
B17: 33 | D17: Inmueble maquinaria y Equipo | F17: 200000
E18: Capital Social | G18: 200000
B19: 10 | D19: Efectivo y equivalente de efectivo | F19: 600000
E20: Cuentas por Pagar | G20: 600000
B21: 20 | D21: Efectivo y equivalente de efectivo | F21: 5000
C22: 46 | E22: Capital Social | G22: 5000
D23: Mercaderias | F23: 56000
E24: Efectivo y equivalente de efectivo | G24: 56000
F25: =SUM(F11:F24) -> 1646000 | G25: =SUM(G11:G24) -> 1646000
E26: 1
B27: 33 | D27: Edificios | F27: 300000
C28: 46 | E28: Cuentas por Pagar | G28: 150000
C29: 10 | E29: Efectivo y equivalente de efectivo | G29: 150000
F30: =SUM(F27:F29) -> 300000 | G30: =SUM(G27:G29) -> 300000
E31: 2
B32: 60 | D32: Mercaderias | F32: 600000
E33: Efectivo y equivalente de efectivo | G33: 600000
B34: 40 | D34: Tributos por pagar (IGV) | F34: =0.18*F32 -> 108000
C35: 10 | E35: Efectivo y equivalente de efectivo | G35: =F34 -> 108000
F36: =SUM(F32:F35) -> 708000 | G36: =SUM(G32:G35) -> 708000
E37: 3
D38: Ventas | G38: 400000
E39: Clientes | F39: 400000
B40: 10 | D40: Clientes | F40: =18%*F39 -> 72000
B41: 12 | E41: Tributos por pagar (IGV) | G41: =F40 -> 72000
C42: 40 | D42: Costo de Ventas | F42: 350000
C43: 70 | E43: Mercaderias | G43: 350000
F44: =SUM(F38:F43) -> 822000 | G44: =SUM(G38:G43) -> 822000
E45: 4
B46: 63 | D46: Efectivo y equivalente de efectivo | G46: 300
B47: 63 | E47: Servicios Prestados por terceros (luz) | F47: 300
B48: 63 | D48: Efectivo y equivalente de efectivo | G48: 200
B49: 40 | E49: Servicios Prestados por terceros (agua) | F49: 200
C50: 10 | D50: Efectivo y equivalente de efectivo | G50: 450
E51: Servicios Prestados por terceros (telef) | F51: 450
D52: Efectivo y equivalente de efectivo | G52: =(F47+F49+F51)*18% -> 171
E53: Tributos por pagar (IGV) | F53: =G52 -> 171
F54: =SUM(F46:F53) -> 1121 | G54: =SUM(G46:G53) -> 1121
E55: 5
B56: 62 | D56: Cargas de personal | F56: 8000
C57: 10 | E57: Efectivo y equivalente de efectivo | G57: 8000
F58: =SUM(F56:F57) -> 8000 | G58: =SUM(G56:G57) -> 8000
E59: 6
B60: 64 | D60: Tributos por pagar | F60: 5000
E61: Efectivo y equivalente de efectivo | G61: 5000
B62: 66 | D62: Cargas Excepcionales | F62: 1500
C63: 10 | E63: Efectivo y equivalente de efectivo | G63: 1500
F64: =SUM(F60:F63) -> 6500 | G64: =SUM(G60:G63) -> 6500
E65: 7
B66: 38 | D66: Cargas Diferidas (seguros) | F66: 4000
C67: 10 | E67: Efectivo y equivalente de efectivo | G67: 4000
F68: =SUM(F66:F67) -> 4000 | G68: =SUM(G66:G67) -> 4000
E69: 8
B70: 65 | D70: Cargas de Gestion (gastos administrativos) | F70: 400
B71: 40 | E71: Efectivo y equivalente de efectivo | G71: =F70 -> 400
C72: 10 | D72: Tributos por pagar (IGV) | F72: =F70*18% -> 72
C73: 10 | E73: Efectivo y equivalente de efectivo | G73: =F72 -> 72
F74: =SUM(F70:F73) -> 472 | G74: =SUM(G70:G73) -> 472
E75: 9
B76: 10 | D76: Efectivo y equivalente de efectivo | F76: 30000
E77: Cuentas por Pagar | G77: 30000
B78: 67 | D78: Gastos Financieros | F78: =10%*F76 -> 3000
C79: 46 | E79: Cuentas por Pagar | G79: =10%*G77 -> 3000
F80: =SUM(F76:F79) -> 33000 | G80: =SUM(G76:G79) -> 33000
E81: 10
B82: 68 | D82: Provision del Ejercicio (Gasto Administrativo) | F82: 35000
C83: 39 | E83: Depreciacion y amortizacion acumulada | G83: 35000
F84: =SUM(F82:F83) -> 35000 | G84: =SUM(G82:G83) -> 35000
E85: 11
B86: 34 | D86: Intangibles (patente) | F86: 40000
C87: 50 | E87: Capital Social | G87: 40000
F88: =SUM(F86:F87) -> 40000 | G88: =SUM(G86:G87) -> 40000
E89: 12
B90: 68 | D90: Provision del Ejercicio | F90: 24000
E91: CTS Beneficios sociales | G91: 24000
B92: 68 | D92: Provision del Ejercicio (Existencias) | F92: 4500
B93: 68 | E93: Provision por devaluacion Mercader | G93: 4500
C94: 47 | D94: Provision del Ejercicio (gasto comercial) | F94: 6000
C95: 39 | E95: Depreciacion y amortizacion acumulada | G95: 6000
F96: =SUM(F90:F95) -> 34500 | G96: =SUM(G90:G95) -> 34500
E97: 13
B98: 60 | D98: Mercaderias | F98: 35000
E99: Efectivo y equivalente de efectivo | G99: =F98*50% -> 17500
B100: 40 | E100: Proveedores | G100: =G99 -> 17500
C101: 10 | D101: Tributos por Pagar | F101: =18%*F98 -> 6300
C102: 10 | E102: Efectivo y equivalente de efectivo | G102: =F101 -> 6300
F103: =SUM(F98:F102) -> 41300 | G103: =SUM(G98:G102) -> 41300
E104: 14
B105: 16 | D105: Cuentas por Cobrar diversas | F105: 50000
E106: Efectivo y equivalente de efectivo | G106: 50000
B107: 16 | D107: Cuentas por Cobrar diversas | F107: 5000
C108: 77 | E108: Ingresos Financieros | G108: 5000
...

Sheet DD
A1: Asiento Apertura | B1: Debe | C1: Haber | D1: IDC
A2: Efectivo y equivalente de efectivo | B2: 600000 | D2: 1
A3: Capital Social | C3: 600000 | D3: 2
A4: Inmueble maquinaria y Equipo | B4: 150000 | D4: 3
A5: Capital Social | C5: 150000 | D5: 2
A6: Intangibles | B6: 35000 | D6: 4
A7: Capital Social | C7: 35000 | D7: 2
A8: Inmueble maquinaria y Equipo | B8: 200000 | D8: 3
A9: Capital Social | C9: 200000 | D9: 2
A10: Efectivo y equivalente de efectivo | B10: 600000 | D10: 1
A11: Cuentas por Pagar | C11: 600000 | D11: 5
A12: Efectivo y equivalente de efectivo | B12: 5000 | D12: 1
A13: Capital Social | C13: 5000 | D13: 2
A14: Mercaderias | B14: 56000 | D14: 8
A15: Efectivo y equivalente de efectivo | C15: 56000 | D15: 1
A16: Edificios | B16: 300000 | D16: 7
A17: Cuentas por Pagar | C17: 150000 | D17: 5
A18: Efectivo y equivalente de efectivo | C18: 150000 | D18: 1
A19: Mercaderias | B19: 600000 | D19: 8
A20: Efectivo y equivalente de efectivo | C20: 600000 | D20: 1
A21: Tributos por pagar (IGV) | B21: =0.18*B19 -> 108000 | D21: 9
A22: Efectivo y equivalente de efectivo | C22: =B21 -> 108000 | D22: 1
A23: Ventas | C23: 400000 | D23: 10
A24: Clientes | B24: 400000 | D24: 11
A25: Clientes | B25: =18%*B24 -> 72000 | D25: 11
A26: Tributos por pagar (IGV) | C26: =B25 -> 72000 | D26: 9
A27: Costo de Ventas | B27: 350000 | D27: 12
A28: Mercaderias | C28: 350000 | D28: 8
A29: Efectivo y equivalente de efectivo | C29: 300 | D29: 1
A30: Servicios Prestados por terceros (luz) | B30: 300 | D30: 13
A31: Efectivo y equivalente de efectivo | C31: 200 | D31: 1
A32: Servicios Prestados por terceros (agua) | B32: 200 | D32: 13
A33: Efectivo y equivalente de efectivo | C33: 450 | D33: 1
A34: Servicios Prestados por terceros (telef) | B34: 450 | D34: 13
A35: Efectivo y equivalente de efectivo | C35: =(B30+B32+B34)*18% -> 171 | D35: 1
A36: Tributos por pagar (IGV) | B36: =C35 -> 171 | D36: 9
A37: Cargas de personal | B37: 8000 | D37: 14
A38: Efectivo y equivalente de efectivo | C38: 8000 | D38: 1
A39: Tributos por pagar | B39: 5000 | D39: 9
A40: Efectivo y equivalente de efectivo | C40: 5000 | D40: 1
A41: Cargas Excepcionales | B41: 1500 | D41: 15
A42: Efectivo y equivalente de efectivo | C42: 1500 | D42: 1
A43: Cargas Diferidas (seguros) | B43: 4000 | D43: 16
A44: Efectivo y equivalente de efectivo | C44: 4000 | D44: 1
A45: Cargas de Gestion (gastos administrativos) | B45: 400 | D45: 6
A46: Efectivo y equivalente de efectivo | C46: =B45 -> 400 | D46: 1
A47: Tributos por pagar (IGV) | B47: =B45*18% -> 72 | D47: 9
A48: Efectivo y equivalente de efectivo | C48: =B47 -> 72 | D48: 1
A49: Efectivo y equivalente de efectivo | B49: 30000 | D49: 1
A50: Cuentas por Pagar | C50: 30000 | D50: 5
A51: Gastos Financieros | B51: =10%*B49 -> 3000 | D51: 18
A52: Cuentas por Pagar | C52: =10%*C50 -> 3000 | D52: 5
A53: Provision del Ejercicio (Gasto Administrativo) | B53: 35000 | D53: 6
A54: Depreciacion y amortizacion acumulada | C54: 35000 | D54: 20
A55: Intangibles (patente) | B55: 40000 | D55: 4
A56: Capital Social | C56: 40000 | D56: 2
A57: Provision del Ejercicio | B57: 24000 | D57: 19
A58: CTS Beneficios sociales | C58: 24000 | D58: 28
A59: Provision del Ejercicio (Existencias) | B59: 4500 | D59: 19
A60: Provision por devaluacion Mercader | C60: 4500 | D60: 19
A61: Provision del Ejercicio (gasto comercial) | B61: 6000 | D61: 19
A62: Depreciacion y amortizacion acumulada | C62: 6000 | D62: 20
A63: Mercaderias | B63: 35000 | D63: 8
A64: Efectivo y equivalente de efectivo | C64: =B63*50% -> 17500 | D64: 1
A65: Proveedores | C65: =C64 -> 17500 | D65: 21
A66: Tributos por Pagar | B66: =18%*B63 -> 6300 | D66: 9
A67: Efectivo y equivalente de efectivo | C67: =B66 -> 6300 | D67: 1
A68: Cuentas por Cobrar diversas | B68: 50000 | D68: 22
A69: Efectivo y equivalente de efectivo | C69: 50000 | D69: 1
A70: Cuentas por Cobrar diversas | B70: 5000 | D70: 22
A71: Ingresos Financieros | C71: 5000 | D71: 23
A72: Efectivo y equivalente de efectivo | B72: 6000 | D72: 1
A73: Clientes | C73: 6000 | D73: 11
A74: Valores | B74: 9000 | D74: 24
A75: Efectivo y equivalente de efectivo | C75: 9000 | D75: 1
A76: Ventas | C76: 50000 | D76: 10
A77: Efectivo y equivalente de efectivo | B77: =C76*30% -> 15000 | D77: 1
A78: Clientes | B78: =C76-B77 -> 35000 | D78: 11
A79: Mercaderias | C79: 40000 | D79: 8
A80: Costo de ventas | B80: 40000 | D80: 12
A81: Ingresos financieros | B81: =5%*B78 -> 1750 | D81: 23
A82: Clientes | C82: =B81 -> 1750 | D82: 11
A83: Cargas de personal (Gastos administrativos) | B83: 4000 | D83: 14
A84: Efectivo y equivalente de efectivo | C84: 4000 | D84: 1
A85: Efectivo y equivalente de efectivo | B85: 5000 | D85: 1
A86: Ingreso diferido | C86: 5000 | D86: 27
A87: Inmueble maquinaria y Equipo | B87: =10%*(B4+B8) -> 35000 | D87: 3
A88: Edificios | B88: =10%*(B16) -> 30000 | D88: 7
A89: Excedente de Revaluacion | C89: =B87+B88 -> 65000 | D89: 25
A90: Efectivo y equivalente de efectivo | B90: 5000 | D90: 1
A91: Otros ingresos | C91: 5000 | D91: 26
A92: Efectivo y equivalente de efectivo | B92: 14000 | D92: 1
A93: Inmueble maquinaria y equipo | C93: 14000 | D93: 3
B96: =SUM(B2:B93) -> 3934643 | C96: =SUM(C2:C93) -> 3934643 | D96: =B96-C96 -> 0

Sheet MAYOR
A1: MAYORIZACION
A3: (1) Efectivo y Equivalente de Efectivo | D3: ACTIVO | F3: (2) Capital Social | I3: PATRIMONIO | K3: (3) Inmueble, Maquinaria y Equipo | N3: ACTIVO
A4: Transacción | B4: Fecha | C4: Debe | D4: Haber | F4: Transacción | G4: Fecha | H4: Debe | I4: Haber | K4: Transacción | L4: Fecha | M4: Debe | N4: Haber
A5: Apertura | C5: =DIARIO!F11 -> 600000 | F5: Apertura | I5: =DIARIO!G12 -> 600000 | K5: Apertura | M5: =DIARIO!F13 -> 150000
A6: Apertura | C6: =DIARIO!F19 -> 600000 | F6: Apertura | I6: =DIARIO!G14 -> 150000 | K6: Apertura | M6: =DIARIO!F17 -> 200000
A7: Apertura | C7: =DIARIO!F21 -> 5000 | F7: Apertura | I7: =DIARIO!G16 -> 35000 | K7: 20 | M7: =DIARIO!F136 -> 35000
A8: Apertura | D8: =DIARIO!G24 -> 56000 | F8: Apertura | I8: =DIARIO!G18 -> 200000 | K8: 22 | N8: =DIARIO!G146 -> 14000
A9: 1 | D9: =DIARIO!G29 -> 150000 | F9: Apertura | I9: 5000
A10: 2 | D10: =DIARIO!G33 -> 600000 | F10: 11 | I10: =DIARIO!G87 -> 40000
A11: 2 | D11: =DIARIO!G35 -> 108000
A12: 4 | D12: =DIARIO!G46 -> 300
A13: 4 | D13: =DIARIO!G48 -> 200
A14: 4 | D14: =DIARIO!G50 -> 450
A15: 4 | D15: =DIARIO!G52 -> 171
A16: 5 | D16: =DIARIO!G57 -> 8000
A17: 6 | D17: =DIARIO!G61 -> 5000
A18: 6 | D18: =DIARIO!G63 -> 1500
A19: 7 | D19: =DIARIO!G67 -> 4000
A20: 8 | D20: =DIARIO!G71 -> 400
A21: 8 | D21: =DIARIO!G73 -> 72
A22: 9 | C22: =DIARIO!F76 -> 30000
A23: 13 | D23: =DIARIO!G99 -> 17500
A24: 13 | D24: =DIARIO!G102 -> 6300
A25: 14 | D25: =DIARIO!G106 -> 50000
A26: 15 | C26: =DIARIO!F111 -> 6000
A27: 16 | D27: =DIARIO!G116 -> 9000
A28: 17 | C28: =DIARIO!F120 -> 15000
A29: 18 | D29: =DIARIO!G129 -> 4000
A30: 19 | C30: =DIARIO!F132 -> 5000
A31: 21 | C31: =DIARIO!F141 -> 5000
A32: 22 | C32: 14000
B33: Total | C33: =SUM(C5:C32) -> 1280000 | D33: =SUM(D5:D32) -> 1020893 | E33: OK | G33: Total | H33: =SUM(H5:H32) -> 0 | I33: =SUM(I5:I32) -> 1030000 | J33: OK | L33: Total | M33: =SUM(M5:M32) -> 385000 | N33: =SUM(N5:N32) -> 14000 | O33: OK
B34: Saldo Final | C34: =C33-D33 -> 259107 | G34: Saldo Final | I34: =I33-H33 -> 1030000 | L34: Saldo Final | M34: =M33-N33 -> 371000
A37: (4) Intangibles | D37: ACTIVO | F37: (5) Cuentas por Pagar | I37: PASIVO | K37: (6) Gastos Administrativos | N37: GASTO
A38: Transacción | B38: Fecha | C38: Debe | D38: Haber | F38: Transacción | G38: Fecha | H38: Debe | I38: Haber | K38: Transacción | L38: Fecha | M38: Debe | N38: Haber
A39: Apertura | C39: =DIARIO!F15 -> 35000 | F39: Apertura | I39: =DIARIO!G20 -> 600000 | K39: 8 | M39: =DIARIO!F70 -> 400
A40: 11 | C40: =DIARIO!F86 -> 40000 | F40: 1 | I40: =DIARIO!G28 -> 150000 | K40: 10 | M40: =DIARIO!F82 -> 35000
F41: 9 | I41: =DIARIO!G77 -> 30000
F42: 9 | I42: =DIARIO!G79 -> 3000
B46: Total | C46: =SUM(C39:C45) -> 75000 | D46: =SUM(D39:D45) -> 0 | E46: OK | G46: Total | H46: =SUM(H39:H45) -> 0 | I46: =SUM(I39:I45) -> 783000 | J46: OK | L46: Total | M46: =SUM(M39:M45) -> 35400 | N46: =SUM(N39:N45) -> 0 | O46: OK
B47: Saldo Final | C47: =C46-D46 -> 75000 | G47: Saldo Final | I47: =I46-H46 -> 783000 | L47: Saldo Final | M47: =M46-N46 -> 35400
A50: (7) Edificios | D50: ACTIVO | F50: (8) Mercaderias | I50: ACTIVO | K50: (9) Tributos por pagar | N50: PASIVO
A51: Transacción | B51: Fecha | C51: Debe | D51: Haber | F51: Transacción | G51: Fecha | H51: Debe | I51: Haber | K51: Transacción | L51: Fecha | M51: Debe | N51: Haber
A52: 1 | C52: =DIARIO!F27 -> 300000 | F52: Apertura | H52: =DIARIO!F23 -> 56000 | K52: 2 | M52: =DIARIO!F34 -> 108000
A53: 20 | C53: =DIARIO!F137 -> 30000 | F53: 2 | H53: =DIARIO!F32 -> 600000 | K53: 3 | N53: =DIARIO!G41 -> 72000
F54: 3 | I54: =DIARIO!G43 -> 350000 | K54: 4 | M54: =DIARIO!F53 -> 171
F55: 13 | H55: =DIARIO!F98 -> 35000 | K55: 6 | M55: =DIARIO!F60 -> 5000
F56: 17 | I56: =DIARIO!G122 -> 40000 | K56: 8 | M56: =DIARIO!F72 -> 72
K57: 13 | M57: =DIARIO!F101 -> 6300
B59: Total | C59: =SUM(C52:C58) -> 330000 | D59: =SUM(D52:D58) -> 0 | E59: OK | G59: Total | H59: =SUM(H52:H58) -> 691000 | I59: =SUM(I52:I58) -> 390000 | J59: OK | L59: Total | M59: =SUM(M52:M58) -> 119543 | N59: =SUM(N52:N58) -> 72000 | O59: OK
B60: Saldo Final | C60: =C59-D59 -> 330000 | G60: Saldo Final | H60: =H59-I59 -> 301000 | L60: Saldo Final | M60: =M59-N59 -> 47543
A63: (10) Ventas | D63: INGRESO | F63: (11) Clientes | I63: ACTIVO | K63: (12) Costo de Ventas | N63: COSTOS
A64: Transacción | B64: Fecha | C64: Debe | D64: Haber | F64: Transacción | G64: Fecha | H64: Debe | I64: Haber | K64: Transacción | L64: Fecha | M64: Debe | N64: Haber
A65: 3 | D65: =DIARIO!G38 -> 400000 | F65: 3 | H65: =DIARIO!F39 -> 400000 | K65: 3 | M65: =DIARIO!F42 -> 350000
A66: 17 | D66: =DIARIO!G119 -> 50000 | F66: 3 | H66: =DIARIO!F40 -> 72000 | K66: 17 | M66: =DIARIO!F123 -> 40000
F67: 15 | I67: =DIARIO!G112 -> 6000
F68: 17 | H68: =DIARIO!F121 -> 35000
F69: 17 | I69: =DIARIO!G125 -> 1750
B72: Total | C72: =SUM(C65:C71) -> 0 | D72: =SUM(D65:D71) -> 450000 | E72: OK | G72: Total | H72: =SUM(H65:H71) -> 507000 | I72: =SUM(I65:I71) -> 7750 | J72: OK | L72: Total | M72: =SUM(M65:M71) -> 390000 | N72: =SUM(N65:N71) -> 0 | O72: OK
B73: Saldo Final | D73: =D72-C72 -> 450000 | G73: Saldo Final | H73: =H72-I72 -> 499250 | L73: Saldo Final | M73: =M72-N72 -> 390000
A76: (13) Servicio Prestado por Terceros | D76: GASTO | F76: (14) Cargas de Personal | I76: GASTO | K76: (15) Cargas Excepcionales | N76: GASTO
A77: Transacción | B77: Fecha | C77: Debe | D77: Haber | F77: Transacción | G77: Fecha | H77: Debe | I77: Haber | K77: Transacción | L77: Fecha | M77: Debe | N77: Haber
A78: 3 | C78: =DIARIO!F47 -> 300 | F78: 5 | H78: =DIARIO!F56 -> 8000 | K78: 6 | M78: =DIARIO!F62 -> 1500
A79: 3 | C79: =DIARIO!F49 -> 200 | F79: 18 | H79: =DIARIO!F128 -> 4000
A80: 3 | C80: =DIARIO!F51 -> 450
B85: Total | C85: =SUM(C78:C84) -> 950 | D85: =SUM(D78:D84) -> 0 | E85: OK | G85: Total | H85: =SUM(H78:H84) -> 12000 | I85: =SUM(I78:I84) -> 0 | J85: OK | L85: Total | M85: =SUM(M78:M84) -> 1500 | N85: =SUM(N78:N84) -> 0 | O85: OK
B86: Saldo Final | C86: =C85-D85 -> 950 | G86: Saldo Final | H86: =H85-I85 -> 12000 | L86: Saldo Final | M86: =M85-N85 -> 1500
A89: (16) Cargas Diferidas | D89: ACTIVO | F89: (17) Cargas de Gestión | I89: GASTO | K89: (18) Gastos Financieros | N89: GASTO
A90: Transacción | B90: Fecha | C90: Debe | D90: Haber | F90: Transacción | G90: Fecha | H90: Debe | I90: Haber | K90: Transacción | L90: Fecha | M90: Debe | N90: Haber
A91: 7 | C91: =DIARIO!F66 -> 4000 | K91: 9 | M91: =DIARIO!F78 -> 3000
B98: Total | C98: =SUM(C91:C97) -> 4000 | D98: =SUM(D91:D97) -> 0 | E98: OK | G98: Total | H98: =SUM(H91:H97) -> 0 | I98: =SUM(I91:I97) -> 0 | J98: OK | L98: Total | M98: =SUM(M91:M97) -> 3000 | N98: =SUM(N91:N97) -> 0 | O98: OK
B99: Saldo Final | C99: =C98-D98 -> 4000 | G99: Saldo Final | H99: =H98-I98 -> 0 | L99: Saldo Final | M99: =M98-N98 -> 3000
I101: ACTIVO
A102: (19) Provisión del Ejercicio | D102: GASTO | F102: (20) Depreciacion y amortiza acum | I102: GASTO | K102: (21) Proveedores | N102: PASIVO
A103: Transacción | B103: Fecha | C103: Debe | D103: Haber | F103: Transacción | G103: Fecha | H103: Debe | I103: Haber | K103: Transacción | L103: Fecha | M103: Debe | N103: Haber
A104: 12 | D104: =DIARIO!G93 -> 4500 | F104: 10 | I104: =DIARIO!G83 -> 35000 | K104: 13 | N104: =DIARIO!G100 -> 17500
A105: 12 | C105: =DIARIO!F94 -> 6000 | F105: 12 | I105: =DIARIO!G95 -> 6000
A106: 12 | C106: =DIARIO!F90 -> 24000
A107: 12 | C107: =DIARIO!F92 -> 4500
B111: Total | C111: =SUM(C104:C110) -> 34500 | D111: =SUM(D104:D110) -> 4500 | E111: OK | G111: Total | H111: =SUM(H104:H110) -> 0 | I111: =SUM(I104:I110) -> 41000 | J111: OK | L111: Total | M111: =SUM(M104:M110) -> 0 | N111: =SUM(N104:N110) -> 17500 | O111: OK
B112: Saldo Final | C112: =C111-D111 -> 30000 | G112: Saldo Final | I112: =I111-H111 -> 41000 | L112: Saldo Final | N112: =N111-M111 -> 17500
A115: (22) Cuentas por cobrar diversas | D115: Activo | F115: (23) Ingreso Financiero | I115: GASTO | K115: (24) Valores | N115: ACTIVO
A116: Transacción | B116: Fecha | C116: Debe | D116: Haber | F116: Transacción | G116: Fecha | H116: Debe | I116: Haber | K116: Transacción | L116: Fecha | M116: Debe | N116: Haber
A117: 14 | C117: =DIARIO!F105 -> 50000 | F117: 14 | I117: =DIARIO!G108 -> 5000 | K117: 16 | M117: =DIARIO!F115 -> 9000
A118: 14 | C118: =DIARIO!F107 -> 5000 | F118: 17 | H118: =DIARIO!F124 -> 1750
B124: Total | C124: =SUM(C117:C123) -> 55000 | D124: =SUM(D117:D123) -> 0 | E124: OK | G124: Total | H124: =SUM(H117:H123) -> 1750 | I124: =SUM(I117:I123) -> 5000 | J124: OK | L124: Total | M124: =SUM(M117:M123) -> 9000 | N124: =SUM(N117:N123) -> 0 | O124: OK
B125: Saldo Final | C125: =C124-D124 -> 55000 | G125: Saldo Final | I125: =I124-H124 -> 3250 | L125: Saldo Final | M125: =M124-N124 -> 9000
A128: (25) Excedente de revaluacion | D128: ACTIVO | F128: (26) Otros ingresos | I128: GASTO | K128: (27) Ingreso diferido | N128: PASIVO
A129: Transacción | B129: Fecha | C129: Debe | D129: Haber | F129: Transacción | G129: Fecha | H129: Debe | I129: Haber | K129: Transacción | L129: Fecha | M129: Debe | N129: Haber
A130: 20 | D130: =DIARIO!G138 -> 65000 | F130: 21 | I130: =DIARIO!G142 -> 5000 | K130: 19 | N130: =DIARIO!G133 -> 5000
B137: Total | C137: =SUM(C130:C136) -> 0 | D137: =SUM(D130:D136) -> 65000 | E137: OK | G137: Total | H137: =SUM(H130:H136) -> 0 | I137: =SUM(I130:I136) -> 5000 | J137: OK | L137: Total | M137: =SUM(M130:M136) -> 0 | N137: =SUM(N130:N136) -> 5000 | O137: OK
B138: Saldo Final | D138: =D137-C137 -> 65000 | G138: Saldo Final | I138: =I137-H137 -> 5000 | L138: Saldo Final | N138: =N137-M137 -> 5000
A141: (28) CTS | D141: PASIVO
A142: Transacción | B142: Fecha | C142: Debe | D142: Haber
A143: 12 | D143: =DIARIO!G91 -> 24000
B150: Total | C150: =SUM(C143:C149) -> 0 | D150: =SUM(D143:D149) -> 24000 | E150: OK
B151: Saldo Final | D151: =D150-C150 -> 24000
A154: TOTAL DEBE | C154: =C33+H33+M33+C46+H46+M46+C59+H59+M59+C72+H72+M72+C85+H85+M85+C98+H98+M98+C111+H111+M111+C124+H124+M124+C137+H137+M137+C150 -> 3934643
A155: TOTAL HABER | C155: =D33+I33+N33+D46+I46+N46+D59+I59+N59+D72+I72+N72+D85+I85+N85+D98+I98+N98+D111+I111+N111+D124+I124+N124+D137+I137+N137+D150 -> 3934643
C157: =C155-C154 -> 0

Sheet BC
A1: BALANCE DE COMPROBACION
A2: No | B2: Cuenta | D2: Tipo | E2: Debe | F2: Haber | G2: Saldo D | H2: Saldo A
A3: 1 | B3: Efectivo y Equivalente de efectivo | D3: Activo | E3: =MAYOR!C33 -> 1280000 | F3: =MAYOR!D33 -> 1020893 | G3: =E3-F3 -> 259107 | I3: ESF
A4: 2 | B4: Capital Social | D4: Patrimonio | E4: =MAYOR!H33 -> 0 | F4: =MAYOR!I33 -> 1030000 | H4: =F4-E4 -> 1030000 | I4: PAT
A5: 3 | B5: Inmuebles, Maquinaria y Equipo | D5: Activo | E5: =MAYOR!M33 -> 385000 | F5: =MAYOR!N33 -> 14000 | G5: =E5-F5 -> 371000 | I5: ESF
A6: 4 | B6: Intangibles | D6: Activo | E6: =MAYOR!C46 -> 75000 | F6: =MAYOR!D46 -> 0 | G6: =E6-F6 -> 75000 | I6: ESF
A7: 5 | B7: Cuentas por Pagar | D7: Pasivo | E7: =MAYOR!H46 -> 0 | F7: =MAYOR!I46 -> 783000 | H7: =F7-E7 -> 783000 | I7: ESF
A8: 6 | B8: Gastos Administrativos | D8: Gasto | E8: =MAYOR!M46 -> 35400 | F8: =MAYOR!N46 -> 0 | G8: =E8-F8 -> 35400 | I8: ER
A9: 7 | B9: Edificios | D9: Activo | E9: =MAYOR!C59 -> 330000 | F9: =MAYOR!D59 -> 0 | G9: =E9-F9 -> 330000 | I9: ESF
A10: 8 | B10: Mercaderias | D10: Activo | E10: =MAYOR!H59 -> 691000 | F10: =MAYOR!I59 -> 390000 | G10: =E10-F10 -> 301000 | I10: ESF
A11: 9 | B11: Tributos por pagar | D11: Pasivo | E11: =MAYOR!M59 -> 119543 | F11: =MAYOR!N59 -> 72000 | G11: =E11-F11 -> 47543 | I11: ESF
A12: 10 | B12: Ventas | D12: Ingresos | E12: =MAYOR!C72 -> 0 | F12: =MAYOR!D72 -> 450000 | H12: =F12-E12 -> 450000 | I12: ER
A13: 11 | B13: Clientes | D13: Activo | E13: =MAYOR!H72 -> 507000 | F13: =MAYOR!I72 -> 7750 | G13: =E13-F13 -> 499250 | I13: ESF
A14: 12 | B14: Costo de Ventas | D14: Costos | E14: =MAYOR!M72 -> 390000 | F14: =MAYOR!N72 -> 0 | G14: =E14-F14 -> 390000 | I14: ER
A15: 13 | B15: Servicio Prestdo por Terceros | D15: Gastos | E15: =MAYOR!C85 -> 950 | F15: =MAYOR!D85 -> 0 | G15: =E15-F15 -> 950 | I15: ER
A16: 14 | B16: Cargas de Personal | D16: Gastos | E16: =MAYOR!H85 -> 12000 | F16: =MAYOR!I85 -> 0 | G16: =E16-F16 -> 12000 | I16: ER
A17: 15 | B17: Cargas excepcionales | D17: Gastos | E17: =MAYOR!M85 -> 1500 | F17: =MAYOR!N85 -> 0 | G17: =E17-F17 -> 1500 | I17: ER
A18: 16 | B18: Cargas diferidas | D18: Activo | E18: =MAYOR!C98 -> 4000 | F18: =MAYOR!D98 -> 0 | G18: =E18-F18 -> 4000 | I18: BG
A19: 17 | B19: Cargas de Gestión | D19: Gastos | E19: =MAYOR!H98 -> 0 | F19: =MAYOR!I98 -> 0 | I19: ER
A20: 18 | B20: Gastos Financieros | D20: Gastos | E20: =MAYOR!M98 -> 3000 | F20: =MAYOR!N98 -> 0 | G20: =E20-F20 -> 3000 | I20: ER
A21: 19 | B21: Provisiones del ejercicio | D21: Gastos | E21: =MAYOR!C111 -> 34500 | F21: =MAYOR!D111 -> 4500 | G21: =E21-F21 -> 30000 | I21: ER
A22: 20 | B22: Depreciación y amortizac acum | D22: Activo / Gasto | E22: =MAYOR!H111 -> 0 | F22: =MAYOR!I111 -> 41000 | H22: =F22-E22 -> 41000 | I22: BG/EPG
A23: 21 | B23: Proveedores | D23: Pasivo | E23: =MAYOR!M111 -> 0 | F23: =MAYOR!N111 -> 17500 | H23: =F23-E23 -> 17500 | I23: ESF
A24: 22 | B24: Cuentas por cobrar diversas | D24: Activo | E24: =MAYOR!C124 -> 55000 | F24: =MAYOR!D124 -> 0 | G24: =E24-F24 -> 55000 | I24: ESF
A25: 23 | B25: Ingresos Financieros | D25: Ingreso | E25: =MAYOR!H124 -> 1750 | F25: =MAYOR!I124 -> 5000 | H25: =F25-E25 -> 3250 | I25: ER
A26: 24 | B26: Valores | D26: Activo | E26: =MAYOR!M124 -> 9000 | F26: =MAYOR!N124 -> 0 | G26: =E26-F26 -> 9000 | I26: ESF
A27: 25 | B27: Excedente de revaluacion | D27: Activo | E27: =MAYOR!C137 -> 0 | F27: =MAYOR!D137 -> 65000 | H27: =F27-E27 -> 65000 | I27: ESF
A28: 26 | B28: Otros ingresos | D28: Ingresos | E28: =MAYOR!H137 -> 0 | F28: =MAYOR!I137 -> 5000 | H28: =F28-E28 -> 5000 | I28: ER
A29: 27 | B29: Ingreso diferido | D29: Pasivo | E29: =MAYOR!M137 -> 0 | F29: =MAYOR!N137 -> 5000 | H29: =F29-E29 -> 5000 | I29: ESF
A30: 28 | B30: CTS | D30: Pasivo/Gasto | E30: =MAYOR!C150 -> 0 | F30: =MAYOR!D150 -> 24000 | H30: =F30-E30 -> 24000 | I30: ESF
B33: Total | E33: =SUM(E3:E30) -> 3934643 | F33: =SUM(F3:F30) -> 3934643 | G33: =SUM(G3:G30) -> 2423750 | H33: =SUM(H3:H30) -> 2423750
E35: =E33-F33 -> 0 | G35: =G33-H33 -> 0
F37: ACTIVO | G37: =G3+G5+G6+G9+G10+G13+G18+G24+G26-H22-H27 -> 1797357
F38: PASIVO | G38: =H7-G11+H23+H29+H30 -> 781957
F39: PATRIMONIO | G39: =H4 -> 1030000
F40: VENTAS | G40: =H12 -> 450000
F41: COSTO VENTAS | G41: =G14 -> 390000
F42: GASTOS

Sheet ESF
B1: ESTADO DE SITUACION FINANCIERA
B2: EMPRESA PLANETA SAC.
B4: ACTIVOS | E4: PASIVOS Y PATRIMONIO
B5: ACTIVOS CORRIENTES | E5: PASIVOS CORRIENTES
A6: 10 | B6: Efectivo y equivalente de efectivo | C6: =BC!G3 -> 259107 | E6: Tributos por pagar | F6: =-BC!G11 -> -47543
A7: 12 | B7: Clientes | C7: =BC!G13 -> 499250 | E7: Proveedores | F7: =BC!H23 -> 17500
A8: 16 | B8: Cuentas por cobrar diversas | C8: =BC!G24 -> 55000 | E8: Cuentas por pagar | F8: =BC!H7 -> 783000
A9: 20 | B9: Mercaderías | C9: =BC!G10 -> 301000 | E9: Impuesto a la renta | F9: =ER!C24 -> 0
A10: 29 | B10: Cargas diferidas | C10: =BC!G18 -> 4000 | E10: CTS | F10: =BC!H30 -> 24000
B11: Activos corrientes totales | C11: =SUM(C6:C10) -> 1118357 | E11: Pasivos corrientes totales | F11: =SUM(F6:F10) -> 776957
B12: ACTIVOS NO CORRIENTES | E12: PASIVOS NO CORRIENTES
A13: 31 | B13: Valores | C13: =BC!G26 -> 9000 | E13: Ingreso diferido | F13: =BC!H29 -> 5000
A14: 33 | B14: Inmueble, maquinaria y equipo menos | C14: =BC!G5 -> 371000
A15: 34 | B15: Intangibles | C15: =BC!G6 -> 75000
A16: 35 | B16: Valorizacion adicinal del IME | C16: =-BC!H27 -> -65000
A17: 38 | B17: Depreciación y Amortizacion acumulada | C17: =-BC!H22 -> -41000
A18: 39 | B18: Edificios | C18: =BC!G9 -> 330000
E19: Pasivos no corrientes totales | F19: =SUM(F13:F18) -> 5000
E20: PASIVOS TOTALES | F20: =F11+F19 -> 781957
E22: PATRIMONIO
E23: Capital | F23: =BC!H4 -> 1030000
A24: 40
A25: 42 | E25: Exedente de revaluacion | F25: =-C16 -> 65000
A26: 46 | E26: Resultado del ejercicio | F26: =ER!C25 -> -79600
A27: 47 | B27: Activos no corrientes totales | C27: =SUM(C13:C18) -> 679000 | E27: TOTAL PATRIMONIO | F27: =SUM(F23:F26) -> 1015400
B28: ACTIVOS TOTALES | C28: =C11+C27 -> 1797357 | E28: TOTAL PASIVOS Y PATRIMONIO | F28: =F20+F27 -> 1797357
A30: 49 | F30: =F28-C28 -> 0
A34: 50
A35: 56
A36: 57
A37: 59
F128: =+E128/D128 -> #DIV/0!
F129: =+E129/D129 -> #DIV/0!
F130: =+E130/D130 -> #DIV/0!

Sheet ER
A1: ESTADO DE RESULTADOS
B3: EMPRESA PLANETA SAC
A5: 70 | B5: Ventas | C5: =BC!H12 -> 450000
A6: 69 | B6: Costo de ventas | C6: =BC!G14 -> 390000
B7: Utilidad Bruta | C7: =C5-C6 -> 60000
B8: Gastos operativos
A9: 62 | B9: Gastos administrativos | C9: =BC!G8 -> 35400
A10: 63 | B10: Servicios prestados por terceros | C10: =BC!G15 -> 950
A11: 64 | B11: Cargas de personal | C11: =BC!G16 -> 12000
B12: CTS | C12: =BC!H30 -> 24000
A13: 66 | B13: Cargas de gestión | C13: =BC!G19 -> 0
B14: Provisiones del ejercicio | C14: =BC!G21 -> 30000
B15: Depreciación y amortización | C15: =BC!H22 -> 41000
B16: Gastos operativos totales | C16: =SUM(C9:C15) -> 143350
B17: Utilidades operativas | C17: =C7-C16 -> -83350
A18: 67 | B18: Gastos Financieros | C18: =BC!G20 -> 3000
A19: 68 | B19: Cargas excepcionales | C19: =BC!G17 -> 1500
B20: Otros ingresos | C20: =-BC!H28 -> -5000
B21: Ingresos financieros | C21: =-BC!H25 -> -3250
B22: Otros egresos e ingresos diversos | C22: =SUM(C18:C21) -> -3750
B23: Utilidad antes de impuesto | C23: =C17-C22 -> -79600
B24: Impuesto a la Renta (29.5%) | C24: 0
B25: Utilidad Neta | C25: =C23-C24 -> -79600
